Workbook

Sheet Спр отношение элементов в сезон
A1: id | B1: nm_season | C1: element_season | D1: nm_elementa_season | E1: coef_element_in_season | F1: key_element_connect | G1: id_element_st | H1: id_element_en | I1: nm_elemet_st | J1: nm_element_en | K1: id_connect | L1: nm_connect | M1: coef_connect | N1: coef_st_elemnt_in_season | O1: total_coef_in_season | P1: key_season_el_st_el_en
A2: 1 | B2: Начало весны | C2: 1 | D2: Дерево | E2: 1 | F2: 1_1 | G2: 1 | H2: 1 | I2: Дерево | J2: Дерево | K2: 5 | L2: Партнерство | M2: 1 | N2: 1 | O2: 1 | P2: 1_1_1
A3: 1 | B3: Начало весны | C3: 1 | D3: Дерево | E3: 1 | F3: 1_2 | G3: 1 | H3: 2 | I3: Дерево | J3: Огонь | K3: 3 | L3: Ослабление | M3: 0.5 | N3: 1 | O3: 0.5 | P3: 1_1_2
A4: 1 | B4: Начало весны | C4: 1 | D4: Дерево | E4: 1 | F4: 1_3 | G4: 1 | H4: 3 | I4: Дерево | J4: Земля | K4: 4 | L4: Истощение | M4: 0 | N4: 1 | O4: 0 | P4: 1_1_3
A5: 1 | B5: Начало весны | C5: 1 | D5: Дерево | E5: 1 | F5: 1_4 | G5: 1 | H5: 4 | I5: Дерево | J5: Металл | K5: 2 | L5: Контроль | M5: 0.9 | N5: 1 | O5: 0.9 | P5: 1_1_4
A6: 1 | B6: Начало весны | C6: 1 | D6: Дерево | E6: 1 | F6: 1_5 | G6: 1 | H6: 5 | I6: Дерево | J6: Вода | K6: 1 | L6: Усиление | M6: 1.15 | N6: 1 | O6: 1.15 | P6: 1_1_5
A7: 1 | B7: Начало весны | C7: 1 | D7: Дерево | E7: 1 | F7: 2_1 | G7: 2 | H7: 1 | I7: Огонь | J7: Дерево | K7: 1 | L7: Усиление | M7: 1.15 | N7: 1.15 | O7: 1.3225 | P7: 1_2_1
A8: 1 | B8: Начало весны | C8: 1 | D8: Дерево | E8: 1 | F8: 2_2 | G8: 2 | H8: 2 | I8: Огонь | J8: Огонь | K8: 5 | L8: Партнерство | M8: 1 | N8: 1.15 | O8: 1.15 | P8: 1_2_2
A9: 1 | B9: Начало весны | C9: 1 | D9: Дерево | E9: 1 | F9: 2_3 | G9: 2 | H9: 3 | I9: Огонь | J9: Земля | K9: 3 | L9: Ослабление | M9: 0.5 | N9: 1.15 | O9: 0.575 | P9: 1_2_3
A10: 1 | B10: Начало весны | C10: 1 | D10: Дерево | E10: 1 | F10: 2_4 | G10: 2 | H10: 4 | I10: Огонь | J10: Металл | K10: 4 | L10: Истощение | M10: 0 | N10: 1.15 | O10: 0 | P10: 1_2_4
A11: 1 | B11: Начало весны | C11: 1 | D11: Дерево | E11: 1 | F11: 2_5 | G11: 2 | H11: 5 | I11: Огонь | J11: Вода | K11: 2 | L11: Контроль | M11: 0.9 | N11: 1.15 | O11: 1.035 | P11: 1_2_5
A12: 1 | B12: Начало весны | C12: 1 | D12: Дерево | E12: 1 | F12: 3_1 | G12: 3 | H12: 1 | I12: Земля | J12: Дерево | K12: 2 | L12: Контроль | M12: 0.9 | N12: 0.9 | O12: 0.81 | P12: 1_3_1
A13: 1 | B13: Начало весны | C13: 1 | D13: Дерево | E13: 1 | F13: 3_2 | G13: 3 | H13: 2 | I13: Земля | J13: Огонь | K13: 1 | L13: Усиление | M13: 1.15 | N13: 0.9 | O13: 1.035 | P13: 1_3_2
... A601: 24 | B601: Большие холода | C601: 3 | D601: Земля | E601: 1 | F601: 5_5 | G601: 5 | H601: 5 | I601: Вода | J601: Вода | K601: 5 | L601: Партнерство | M601: 1 | N601: 0.9 | O601: 0.9 | P601: 24_5_5

Sheet Спр 5 элементов
A1: id_element | B1: nm_elementa_rus | C1: nm_element_cha
A2: 1 | B2: Дерево | C2: 木
A3: 2 | B3: Огонь | C3: 火
A4: 3 | B4: Земля | C4: 土
A5: 4 | B5: Металл | C5: 金
A6: 5 | B6: Вода | C6: 水

Sheet Спр 10 НС
A1: id | B1: hieroglyph_cha | C1: yin_yan | D1: element | E1: orientation | F1: nm_rus
A2: 1 | B2: 甲 | C2: 1 | D2: 1 | E2: 1 | F2: Цзя
A3: 2 | B3: 乙 | C3: 2 | D3: 1 | E3: 1 | F3: И
A4: 3 | B4: 丙 | C4: 1 | D4: 2 | E4: 3 | F4: Бин
A5: 4 | B5: 丁 | C5: 2 | D5: 2 | E5: 3 | F5: Дин
A6: 5 | B6: 戊 | C6: 1 | D6: 3 | E6: 0 | F6: У
A7: 6 | B7: 己 | C7: 2 | D7: 3 | E7: 0 | F7: Цзи
A8: 7 | B8: 庚 | C8: 1 | D8: 4 | E8: 5 | F8: Гэн
A9: 8 | B9: 辛 | C9: 2 | D9: 4 | E9: 5 | F9: Синь
A10: 9 | B10: 壬 | C10: 1 | D10: 5 | E10: 7 | F10: Жэнь
A11: 10 | B11: 癸 | C11: 2 | D11: 5 | E11: 7 | F11: Гуй

Sheet Спр 12 Земных ветвей
A1: id_animal | B1: nm_animal_rus | C1: hieroglyph_cha | D1: nm_animal_cha | E1: yin_yan | F1: element | G1: orientation | H1: month_grigorian | I1: coef_element_month
A2: 1 | B2: Тигр | C2: 寅 | D2: Инь | E2: 1 | F2: 1 | G2: 1 | H2: 2 | I2: 1
A3: 2 | B3: Кролик | C3: 卯 | D3: Мао | E3: 2 | F3: 1 | G3: 1 | H3: 3 | I3: 1.15
A4: 3 | B4: Дракон | C4: 辰 | D4: Чэнь | E4: 1 | F4: 3 | G4: 0 | H4: 4 | I4: 1
A5: 4 | B5: Змея | C5: 巳 | D5: Сы | E5: 2 | F5: 2 | G5: 3 | H5: 5 | I5: 1
A6: 5 | B6: Лошадь | C6: 午 | D6: У | E6: 1 | F6: 2 | G6: 3 | H6: 6 | I6: 1.15
A7: 6 | B7: Коза | C7: 未 | D7: Вэй | E7: 2 | F7: 3 | G7: 0 | H7: 7 | I7: 1
A8: 7 | B8: Обезьяна | C8: 申 | D8: Шэнь | E8: 1 | F8: 4 | G8: 5 | H8: 8 | I8: 1
A9: 8 | B9: Петух | C9: 酉 | D9: Ю | E9: 2 | F9: 4 | G9: 5 | H9: 9 | I9: 1.15
A10: 9 | B10: Собака | C10: 戌 | D10: Сюй | E10: 1 | F10: 3 | G10: 0 | H10: 10 | I10: 1
A11: 10 | B11: Свинья | C11: 亥 | D11: Хай | E11: 2 | F11: 5 | G11: 7 | H11: 11 | I11: 1
A12: 11 | B12: Крыса | C12: 子 | D12: Цзы | E12: 1 | F12: 5 | G12: 7 | H12: 12 | I12: 1.15
A13: 12 | B13: Бык | C13: 丑 | D13: Чоу | E13: 2 | F13: 3 | G13: 0 | H13: 1 | I13: 1

Sheet Спр круга Усин
A1: id_element_st | B1: id_element_en | C1: id_connect | D1: nm_elemet_st | E1: nm_element_en | F1: nm_connect | G1: key_element_connect | H1: coef_connect
A2: 1 | B2: 1 | C2: 5 | D2: Дерево | E2: Дерево | F2: Партнерство | G2: 1_1 | H2: 1
A3: 1 | B3: 2 | C3: 3 | D3: Дерево | E3: Огонь | F3: Ослабление | G3: 1_2 | H3: 0.5
A4: 1 | B4: 3 | C4: 4 | D4: Дерево | E4: Земля | F4: Истощение | G4: 1_3 | H4: 0
A5: 1 | B5: 4 | C5: 2 | D5: Дерево | E5: Металл | F5: Контроль | G5: 1_4 | H5: 0.9
A6: 1 | B6: 5 | C6: 1 | D6: Дерево | E6: Вода | F6: Усиление | G6: 1_5 | H6: 1.15
A7: 2 | B7: 1 | C7: 1 | D7: Огонь | E7: Дерево | F7: Усиление | G7: 2_1 | H7: 1.15
A8: 2 | B8: 2 | C8: 5 | D8: Огонь | E8: Огонь | F8: Партнерство | G8: 2_2 | H8: 1
A9: 2 | B9: 3 | C9: 3 | D9: Огонь | E9: Земля | F9: Ослабление | G9: 2_3 | H9: 0.5
A10: 2 | B10: 4 | C10: 4 | D10: Огонь | E10: Металл | F10: Истощение | G10: 2_4 | H10: 0
A11: 2 | B11: 5 | C11: 2 | D11: Огонь | E11: Вода | F11: Контроль | G11: 2_5 | H11: 0.9
A12: 3 | B12: 1 | C12: 2 | D12: Земля | E12: Дерево | F12: Контроль | G12: 3_1 | H12: 0.9
A13: 3 | B13: 2 | C13: 1 | D13: Земля | E13: Огонь | F13: Усиление | G13: 3_2 | H13: 1.15
... A26: 5 | B26: 5 | C26: 5 | D26: Вода | E26: Вода | F26: Партнерство | G26: 5_5 | H26: 1

Sheet Спр дворцов
A1: id | B1: nm_cha | C1: nm_rus | D1: id_element | E1: num | F1: direction | G1: id_scdg | K1: Дворец | L1: Животное | M1: Знак животного | N1: Какая полярность года | O1: Направление дворца | P1: Направление животного | Q1: Удачные для меня градусы
A2: 1 | B2: 坎 | C2: Кань | D2: 5 | E2: 1 | F2: Север | K2: 4 | L2: Дракон | M2: 辰 | N2: Инь | O2: =VLOOKUP(K2,Спр_дворцов[[num]:[direction]],2,FALSE) -> Юго-Восток | P2: ЮВ-1 | Q2: 123,75-127,5 | R2: =_xlfn.CONCAT(P2," (",Q2,")") -> ЮВ-1 (123,75-127,5)
A3: 8 | C3: Гэнь | D3: 3 | E3: 8 | F3: Северо-восток | K3: 4 | L3: Змея | M3: 巳 | N3: Ян | O3: =VLOOKUP(K3,Спр_дворцов[[num]:[direction]],2,FALSE) -> Юго-Восток | P3: ЮВ-3 | Q3: 142,5-146,25 | R3: =_xlfn.CONCAT(P3," (",Q3,")") -> ЮВ-3 (142,5-146,25)
A4: 3 | B4: 震 | C4: Чжэнь | D4: 1 | E4: 3 | F4: Восток | K4: 9 | L4: Лошадь | M4: 午 | N4: Инь | O4: =VLOOKUP(K4,Спр_дворцов[[num]:[direction]],2,FALSE) -> Юг | P4: Ю-2 | Q4: 172,5-187,5 | R4: =_xlfn.CONCAT(P4," (",Q4,")") -> Ю-2 (172,5-187,5)
A5: 4 | B5: 巽 | C5: Сюнь | D5: 1 | E5: 4 | F5: Юго-Восток | K5: 2 | L5: Коза | M5: 未 | N5: Ян | O5: =VLOOKUP(K5,Спр_дворцов[[num]:[direction]],2,FALSE) -> Юго-Запад | P5: ЮЗ-1 | Q5: 213,75-217,5 | R5: =_xlfn.CONCAT(P5," (",Q5,")") -> ЮЗ-1 (213,75-217,5)
A6: 9 | B6: 离 | C6: Ли | D6: 2 | E6: 9 | F6: Юг | K6: 2 | L6: Обезьяна | M6: 申 | N6: Инь | O6: =VLOOKUP(K6,Спр_дворцов[[num]:[direction]],2,FALSE) -> Юго-Запад | P6: ЮЗ-3 | Q6: 232,5-236,25 | R6: =_xlfn.CONCAT(P6," (",Q6,")") -> ЮЗ-3 (232,5-236,25)
A7: 2 | B7: 坤 | C7: Кунь | D7: 3 | E7: 2 | F7: Юго-Запад | K7: 7 | L7: Петух | M7: 酉 | N7: Ян | O7: =VLOOKUP(K7,Спр_дворцов[[num]:[direction]],2,FALSE) -> Запад | P7: З-2 | Q7: 262,5-277,5 | R7: =_xlfn.CONCAT(P7," (",Q7,")") -> З-2 (262,5-277,5)
A8: 7 | B8: 兑 | C8: Дуй | D8: 4 | E8: 7 | F8: Запад | K8: 6 | L8: Собака | M8: 戌 | N8: Инь | O8: =VLOOKUP(K8,Спр_дворцов[[num]:[direction]],2,FALSE) -> Северо-Запад | P8: СЗ-1 | Q8: 303,75-307,5 | R8: =_xlfn.CONCAT(P8," (",Q8,")") -> СЗ-1 (303,75-307,5)
A9: 6 | B9: 乾 | C9: Цянь | D9: 4 | E9: 6 | F9: Северо-Запад | K9: 6 | L9: Свинья | M9: 亥 | N9: Ян | O9: =VLOOKUP(K9,Спр_дворцов[[num]:[direction]],2,FALSE) -> Северо-Запад | P9: СЗ-3 | Q9: 322,5-326,25 | R9: =_xlfn.CONCAT(P9," (",Q9,")") -> СЗ-3 (322,5-326,25)
K10: 1 | L10: Крыса | M10: 子 | N10: Инь | O10: =VLOOKUP(K10,Спр_дворцов[[num]:[direction]],2,FALSE) -> Север | P10: С-2 | Q10: 352,5-7,5 | R10: =_xlfn.CONCAT(P10," (",Q10,")") -> С-2 (352,5-7,5)
K11: 8 | L11: Бык | M11: 丑 | N11: Ян | O11: =VLOOKUP(K11,Спр_дворцов[[num]:[direction]],2,FALSE) -> Северо-восток | P11: СВ-1 | Q11: 33,75-37,5 | R11: =_xlfn.CONCAT(P11," (",Q11,")") -> СВ-1 (33,75-37,5)
K12: 8 | L12: Тигр | M12: 寅 | N12: Инь | O12: =VLOOKUP(K12,Спр_дворцов[[num]:[direction]],2,FALSE) -> Северо-восток | P12: СВ-3 | Q12: 52,5-56,25 | R12: =_xlfn.CONCAT(P12," (",Q12,")") -> СВ-3 (52,5-56,25)
K13: 3 | L13: Кролик | M13: 卯 | N13: Ян | O13: =VLOOKUP(K13,Спр_дворцов[[num]:[direction]],2,FALSE) -> Восток | P13: В-2 | Q13: 82,5-97,5 | R13: =_xlfn.CONCAT(P13," (",Q13,")") -> В-2 (82,5-97,5)

Sheet Спр звезд
A1: id | B1: star_cha | C1: star_rus_1 | D1: star_rus_2 | E1: id_element | F1: id_palace | G1: koef
A2: 1 | B2: 蓬 | C2: Тянь Пэн | D2: Разбойник на воде | E2: 5 | F2: 1 | G2: -1
A3: 2 | B3: 任 | C3: Тянь Жэнь | D3: Небесный Чиновник | E3: 3 | F3: 8 | G3: 1
A4: 3 | B4: 冲 | C4: Тянь Чун | D4: Небесный Пробой | E4: 1 | F4: 3 | G4: -1
A5: 4 | B5: 辅 | C5: Тянь Фу | D5: Небесная Помощь | E5: 1 | F5: 4 | G5: 1
A6: 5 | B6: 英 | C6: Тянь Ин | D6: Небесный блеск | E6: 2 | F6: 9 | G6: -1
A7: 6 | B7: 芮 | C7: Тянь Жуй | D7: Небесный росток | E7: 3 | F7: 2 | G7: -1
A8: 7 | B8: 禽 | C8: Тянь Цинь | D8: Дикая Птица | E8: 3 | F8: 5 | G8: 1
A9: 8 | B9: 柱 | C9: Тянь Чжу | D9: Разбитая армия | E9: 4 | F9: 7 | G9: -1
A10: 9 | B10: 心 | C10: Тянь Синь | D10: Небесное сердце | E10: 4 | F10: 6 | G10: -1

Sheet Спр духов
A1: id | B1: spirit_cha | C1: spirit_rus_1 | D1: spirit_rus_2 | E1: id_element | F1: id_palace | G1: koef
A2: 1 | B2: 符 | C2: Чжи Фу | D2: Главный дух | E2: 3 | G2: 1.15
A3: 2 | B3: 蛇 | C3: Тэн Шэ | D3: Дух Пернатого Змея | E3: 2 | G3: -1
A4: 3 | B4: 陰 | C4: Тай Инь | D4: Дух Великого Инь | E4: 4 | G4: 1
A5: 4 | B5: 合 | C5: Лю Хэ | D5: Дух Шести соединений | E5: 1 | G5: 1
A6: 5 | B6: 虎 | C6: Бай Ху | D6: Дух Белого Тигра | E6: 4 | G6: -1
A7: 6 | B7: 武 | C7: Сюань У | D7: Дух Темного воина | E7: 5 | G7: -1
A8: 7 | B8: 地 | C8: Дзю Ди | D8: Дух Девяти Земель | E8: 3 | G8: 1
A9: 8 | B9: 天 | C9: Дзю Тянь | D9: Дух Девяти Небес | E9: 4 | G9: 1

Sheet Спр Фаза Ци
A1: id | B1: sky | C1: earth | D1: jazi | E1: id_faza | F1: nm_faza_ci | G1: koef_ci
A2: 1 | B2: 甲 | C2: 亥 | D2: 甲亥 | E2: 1 | F2: Рост и развитие (Рождение) | G2: 1.15
A3: 2 | B3: 甲 | C3: 子 | D3: 甲子 | E3: 2 | F3: Ванная (Купание) | G3: 0
A4: 3 | B4: 甲 | C4: 丑 | D4: 甲丑 | E4: 3 | F4: Шапка и поясн (Надевание шапки, опоясывание, школа) | G4: 1
A5: 4 | B5: 甲 | C5: 寅 | D5: 甲寅 | E5: 4 | F5: Формирование дуачи (Поступление на службу, жалование) | G5: 1
A6: 5 | B6: 甲 | C6: 卯 | D6: 甲卯 | E6: 5 | F6: Императорский светильник (Расцвет) | G6: 1.15
A7: 7 | B7: 甲 | C7: 辰 | D7: 甲辰 | E7: 6 | F7: Ослабление (Пенсия) | G7: 0.5
A8: 8 | B8: 甲 | C8: 巳 | D8: 甲巳 | E8: 7 | F8: Болезнь | G8: 0.5
A9: 9 | B9: 甲 | C9: 午 | D9: 甲午 | E9: 8 | F9: Смерть | G9: 0.15
A10: 10 | B10: 甲 | C10: 未 | D10: 甲未 | E10: 9 | F10: Могила | G10: 0
A11: 11 | B11: 甲 | C11: 申 | D11: 甲申 | E11: 10 | F11: Разложение (Исчезновение, обрыв) | G11: 0
A12: 12 | B12: 甲 | C12: 酉 | D12: 甲酉 | E12: 11 | F12: Эмбрион (Зачатие) | G12: 0.5
A13: 13 | B13: 甲 | C13: 戌 | D13: 甲戌 | E13: 12 | F13: Питание (Вынашивание, зародыш) | G13: 0.5
... A121: 121 | B121: 癸 | C121: 辰 | D121: 癸辰 | E121: 12 | F121: Питание (Вынашивание, зародыш) | G121: 0.5

Sheet Спр НС
A1: id | B1: hieroglyph_cha | C1: yin_yan | D1: element | E1: orientation | F1: nm_rus
A2: 1 | B2: 甲 | C2: 1 | D2: 1 | E2: 1 | F2: Цзя
A3: 2 | B3: 乙 | C3: 2 | D3: 1 | E3: 1 | F3: И
A4: 3 | B4: 丙 | C4: 1 | D4: 2 | E4: 3 | F4: Бин
A5: 4 | B5: 丁 | C5: 2 | D5: 2 | E5: 3 | F5: Дин
A6: 5 | B6: 戊 | C6: 1 | D6: 3 | E6: 0 | F6: У
A7: 6 | B7: 己 | C7: 2 | D7: 3 | E7: 0 | F7: Цзи
A8: 7 | B8: 庚 | C8: 1 | D8: 4 | E8: 5 | F8: Гэн
A9: 8 | B9: 辛 | C9: 2 | D9: 4 | E9: 5 | F9: Синь
A10: 9 | B10: 壬 | C10: 1 | D10: 5 | E10: 7 | F10: Жэнь
A11: 10 | B11: 癸 | C11: 2 | D11: 5 | E11: 7 | F11: Гуй

Sheet Спр ворот
A1: id | B1: gate_cha | C1: gate_rus_1 | D1: gate_rus_2 | E1: id_element | F1: id_palace | G1: koef | H1: vstroika_in_gate
A2: 1 | B2: 休 | C2: Сю Мэнь | D2: Отдых | E2: 5 | F2: 1 | G2: 1 | H2: 1) расслабляться, отдыхать, кайфовать, восстанавливать силы в СПА, бассейне около водоема или попивая чай, пиво, вино 2) кататься на лодке, пойти в порт 3) чай, чайная лавка – пить, выбирать, посещать 4) рыба, морепродукты, водоросли – ловить, собирать, покупать, готовить 5) моряк, водолаз – общаться, стать им, одеться в форму и сделать селфи 6) заниматься сексом 7) моющее средство, шампунь – покупать, использовать
A3: 2 | B3: 生 | C3: Шэн Мэнь | D3: Жизнь | E3: 3 | F3: 8 | G3: 1 | H3: Все, что связано с деньгами и прибылью, а также рождением чего-то нового, торжеством жизни:1) Ребенок – играть с ним, гулять, заниматься, ухаживать за ним, пойти на детскую площадку 2) Нос, пальцы – обратить на них внимание 3) надеть перчатки 4) холм, гора, арка, тоннель – пойти в такое место 5) изделия из камня, керамика – делать, покупать, расписывать 6) деньги – считать, получать в кассе или банкомате
A4: 3 | B4: 傷 | C4: Шан Мэнь | D4: Ранение | E4: 1 | F4: 3 | G4: 0
A5: 4 | B5: 杜 | C5: Ду Мэнь | D5: Непроходимость | E5: 1 | F5: 4 | G5: 0
A6: 5 | B6: 景 | C6: Цзин Мэнь | D6: Сцена | E6: 2 | F6: 9 | G6: 0.75 | H6: Привлекать к себе внимание или участвовать в чем-то зрелищном: 1) Красивая женщина – выглядеть великолепно, отлично от большинства. 2) Либо идти вместе с красивой женщиной 3) Косметолог – посетить 4)офтальмолог – сходить к доктору 5) дворец, театр, кинотеатр – посетить 6) выйти на любую сцену, хоть деревянную в парке 7) доспехи надеть, в них сфотографироваться, посмеяться, отправить фото друзьям 8) красивый торт – купить и торжественно нести, дарить 9) потанцевать
A7: 6 | B7: 死 | C7: Сы Мэнь | D7: Смерть | E7: 3 | F7: 2 | G7: 0
A8: 7 | B8: 驚 | C8: Цзин Мэнь | D8: Шока | E8: 4 | F8: 7 | G8: 0
A9: 8 | B9: 開 | C9: Кай Мэнь | D9: Открытие | E9: 4 | F9: 6 | G9: 1 | H9: 1) шары из камня или металла – крутить в руках, привлекая внимание, желательно 6 штук. 2) можно запустить 6 (белых) воздушных шаров с гелием 3) корона – носить (в Бургер Кинге раздают) 4) голова – например взять с собой гипсовый бюст 5) зеркало (особенно круглое, овальное) – покупать, носить в руках, смотреться 6) старый человек – поговорить, спросить совета, помочь… 7) императорский дворец, президентская резиденция – посетить, сделать коллаж со своим фото… 8) памятник, статуя, особенно очень известная – подойти к ним 9) надеть белую одежду, обувь сумку, можно с металлическим отливом (если это необычно для вас или в том месте, куда вы направляетесь)

Sheet Rule
A1: в базу | B1: Описание | C1: lvl_1_nm | D1: lvl_2_nm | E1: lvl_3_nm | F1: lvl_4_nm | G1: lvl_5_nm | H1: lvl_6_nm | I1: lvl_1 | J1: lvl_2 | K1: lvl_3 | L1: lvl_4 | M1: lvl_5 | N1: lvl_6 | O1: lvl_7 | P1: gr | Q1: id | R1: nm | S1: des | T1: id_season_start | U1: god_stolp_sky | V1: god_stolp_sky_id_5_element | W1: god_stolp_earth | X1: god_stolp_earth_5_element | Y1: god_scdg_element_num | Z1: god_scdg_period_num | AA1: god_scdg_id_5_element | AB1: mes_stolp_sky | AC1: mes_stolp_sky_id_5_element | AD1: mes_stolp_earth | AE1: mes_stolp_earth_id_5_element | AF1: mes_scdg_element_num | AG1: mes_scdg_period_num | AH1: mes_scdg_id_5_element | AI1: den_stolp_sky | AJ1: den_stolp_sky_id_5_element | AK1: den_stolp_earth | AL1: den_stolp_earth_id_5_element | AM1: den_scdg_element_num | AN1: den_scdg_period_num | AO1: den_scdg_id_5_element | AP1: chas_stolp_sky | AQ1: chas_stolp_sky_id_5_element | AR1: chas_stolp_earth | AS1: chas_stolp_earth_id_5_element | AT1: chas_scdg_element_num | AU1: chas_scdg_period_num | AV1: chas_scdg_id_5_element | AW1: palace | AX1: flag_sky_fou_tou | AY1: sky | AZ1: flag_earth_fou_tou | BA1: earth | BB1: gate | BC1: flag_main_gate | BD1: star | BE1: flag_main_star | BF1: spirit | BG1: coef | BH1: activation_use | BI1: activation_stop_factor | BJ1: walk_use | BK1: walk_stop_factor | BL1: scdg_use | BM1: scdg_stop_factor | BN1: date_analyze_use | BO1: date_analyze_stop_factor
A2: 1 | B2: =_xlfn.CONCAT(C2,". ", D2,". ", E2,". ", F2,". ", G2,". ", H2) -> Общий расчет. Ци Мень. Анализ Дворца. Структуры. Благоприятность. Нет | C2: =IFERROR(VLOOKUP(I2,lvl_1[],2,FALSE),"Нет") -> Общий расчет | D2: =IFERROR(VLOOKUP(Rule!J2,lvl_2[],2,FALSE),"Нет") -> Ци Мень | E2: =IFERROR(VLOOKUP(Rule!K2,lvl_3[],2,FALSE),"Нет") -> Анализ Дворца | F2: =IFERROR(INDEX(lvl_4[],MATCH(L2,lvl_4[ID],0),MATCH(TEXT(K2,"##0"),lvl_4[#Headers],0)),"Нет") -> Структуры | G2: =IFERROR(INDEX(lvl_5[],MATCH(M2,lvl_5[ID],0),MATCH(_xlfn.CONCAT(TEXT(K2,"##0"),"_",TEXT(L2,"##0")),lvl_5[#Headers],0)),"Нет") -> Благоприятность | H2: =IFERROR(INDEX(lvl_6[],MATCH(N2,lvl_6[ID],0),MATCH(_xlfn.CONCAT(K2,"_",L2,"_",M2),lvl_6[#Headers],0)),"Нет") -> Нет | I2: 1 | J2: 2 | K2: 2 | L2: 1 | M2: 0 | N2: 0 | O2: =COUNTIF($P$2:P2,P2) -> 1 | P2: =_xlfn.CONCAT(I2, J2, K2, IF(LEN(L2)=1,_xlfn.CONCAT(0,L2),L2), IF(LEN(M2)=1,_xlfn.CONCAT(0,M2),M2), IF(LEN(N2)=1,_xlfn.CONCAT(0,N2),N2)) -> 122010000 | Q2: =_xlfn.CONCAT(I2, J2, K2, IF(LEN(L2)=1,_xlfn.CONCAT(0,L2),L2), IF(LEN(M2)=1,_xlfn.CONCAT(0,M2),M2), IF(LEN(N2)=1,_xlfn.CONCAT(0,N2),N2), IF(LEN(O2)=1,_xlfn.CONCAT("000",O2),IF(LEN(O2)=2,_xlfn.CONCAT("00",O2),IF(LEN(O2)=3,_xlfn.CONCAT(0,O2),O2)))) -> 1220100000001 | R2: Зеленый дракон поворачивает голову | S2: Огонь идет снизу-вверх. Используем, когда нужна поддержка. Действия принесут большую прибыль славу и богатство. Медленный старт, но потом устойчивый рост. Применяют для назначения на новый пост, начала судебного процесса в борьбе за правое дело, переезда, прибыльных проектов, строительства и всех позитивных дел. Не подходит для скрытых целей. | AY2: 戊 | BA2: 丙 | BG2: 1 | BJ2: 1
A3: 1 | B3: =_xlfn.CONCAT(C3,". ", D3,". ", E3,". ", F3,". ", G3,". ", H3) -> Общий расчет. Ци Мень. Анализ Дворца. Структуры. Благоприятность. Нет | C3: =IFERROR(VLOOKUP(I3,lvl_1[],2,FALSE),"Нет") -> Общий расчет | D3: =IFERROR(VLOOKUP(Rule!J3,lvl_2[],2,FALSE),"Нет") -> Ци Мень | E3: =IFERROR(VLOOKUP(Rule!K3,lvl_3[],2,FALSE),"Нет") -> Анализ Дворца | F3: =IFERROR(INDEX(lvl_4[],MATCH(L3,lvl_4[ID],0),MATCH(TEXT(K3,"##0"),lvl_4[#Headers],0)),"Нет") -> Структуры | G3: =IFERROR(INDEX(lvl_5[],MATCH(M3,lvl_5[ID],0),MATCH(_xlfn.CONCAT(TEXT(K3,"##0"),"_",TEXT(L3,"##0")),lvl_5[#Headers],0)),"Нет") -> Благоприятность | H3: =IFERROR(INDEX(lvl_6[],MATCH(N3,lvl_6[ID],0),MATCH(_xlfn.CONCAT(K3,"_",L3,"_",M3),lvl_6[#Headers],0)),"Нет") -> Нет | I3: 1 | J3: 2 | K3: 2 | L3: 1 | M3: 0 | N3: 0 | O3: =COUNTIF($P$2:P3,P3) -> 2 | P3: =_xlfn.CONCAT(I3, J3, K3, IF(LEN(L3)=1,_xlfn.CONCAT(0,L3),L3), IF(LEN(M3)=1,_xlfn.CONCAT(0,M3),M3), IF(LEN(N3)=1,_xlfn.CONCAT(0,N3),N3)) -> 122010000 | Q3: =_xlfn.CONCAT(I3, J3, K3, IF(LEN(L3)=1,_xlfn.CONCAT(0,L3),L3), IF(LEN(M3)=1,_xlfn.CONCAT(0,M3),M3), IF(LEN(N3)=1,_xlfn.CONCAT(0,N3),N3), IF(LEN(O3)=1,_xlfn.CONCAT("000",O3),IF(LEN(O3)=2,_xlfn.CONCAT("00",O3),IF(LEN(O3)=3,_xlfn.CONCAT(0,O3),O3)))) -> 1220100000002 | R3: Структура. Благоприятность. 003 甲/丙(Цзя/Бин). Зеленый дракон поворачивает голову | S3: Очень благоприятная комбинаци, любое действие приносит большую прибыль, славу и богатство. Благоприятно действовать. Однако если он встречает могилу или наказание - хорошая ситуация превращается в неблагоприятную | AX3: 1 | AY3: 戊 | BA3: 丙 | BG3: 1 | BJ3: 1
A4: 1 | B4: =_xlfn.CONCAT(C4,". ", D4,". ", E4,". ", F4,". ", G4,". ", H4) -> Общий расчет. Ци Мень. Анализ Дворца. Комбинации. Нет. Нет | C4: =IFERROR(VLOOKUP(I4,lvl_1[],2,FALSE),"Нет") -> Общий расчет | D4: =IFERROR(VLOOKUP(Rule!J4,lvl_2[],2,FALSE),"Нет") -> Ци Мень | E4: =IFERROR(VLOOKUP(Rule!K4,lvl_3[],2,FALSE),"Нет") -> Анализ Дворца | F4: =IFERROR(INDEX(lvl_4[],MATCH(L4,lvl_4[ID],0),MATCH(TEXT(K4,"##0"),lvl_4[#Headers],0)),"Нет") -> Комбинации | G4: =IFERROR(INDEX(lvl_5[],MATCH(M4,lvl_5[ID],0),MATCH(_xlfn.CONCAT(TEXT(K4,"##0"),"_",TEXT(L4,"##0")),lvl_5[#Headers],0)),"Нет") -> Нет | H4: =IFERROR(INDEX(lvl_6[],MATCH(N4,lvl_6[ID],0),MATCH(_xlfn.CONCAT(K4,"_",L4,"_",M4),lvl_6[#Headers],0)),"Нет") -> Нет | I4: 1 | J4: 2 | K4: 2 | L4: 2 | M4: 0 | N4: 0 | O4: =COUNTIF($P$2:P4,P4) -> 1 | P4: =_xlfn.CONCAT(I4, J4, K4, IF(LEN(L4)=1,_xlfn.CONCAT(0,L4),L4), IF(LEN(M4)=1,_xlfn.CONCAT(0,M4),M4), IF(LEN(N4)=1,_xlfn.CONCAT(0,N4),N4)) -> 122020000 | Q4: =_xlfn.CONCAT(I4, J4, K4, IF(LEN(L4)=1,_xlfn.CONCAT(0,L4),L4), IF(LEN(M4)=1,_xlfn.CONCAT(0,M4),M4), IF(LEN(N4)=1,_xlfn.CONCAT(0,N4),N4), IF(LEN(O4)=1,_xlfn.CONCAT("000",O4),IF(LEN(O4)=2,_xlfn.CONCAT("00",O4),IF(LEN(O4)=3,_xlfn.CONCAT(0,O4),O4)))) -> 1220200000001 | R4: Птица падает в гнездо | S4: Огонь приходит с неба, чтобы произвести землю. Мы получаем что-то с неба. Получение прибыли или награды без усилий. У всех вещей есть потенциал быть успешными. Можно замышлять большие дела. Подходит для продвижения по карьерной лестнице, прибыльных проектов, судебного процесса за правое дело, строительства, свадьбы и всех позитивных дел | AW4: 4 | AX4: 1 | AY4: 丙 | BA4: 戊 | BG4: 1 | BJ4: 1
A5: 1 | B5: =_xlfn.CONCAT(C5,". ", D5,". ", E5,". ", F5,". ", G5,". ", H5) -> Общий расчет. Ци Мень. Анализ Дворца. Комбинации. Нет. Нет | C5: =IFERROR(VLOOKUP(I5,lvl_1[],2,FALSE),"Нет") -> Общий расчет | D5: =IFERROR(VLOOKUP(Rule!J5,lvl_2[],2,FALSE),"Нет") -> Ци Мень | E5: =IFERROR(VLOOKUP(Rule!K5,lvl_3[],2,FALSE),"Нет") -> Анализ Дворца | F5: =IFERROR(INDEX(lvl_4[],MATCH(L5,lvl_4[ID],0),MATCH(TEXT(K5,"##0"),lvl_4[#Headers],0)),"Нет") -> Комбинации | G5: =IFERROR(INDEX(lvl_5[],MATCH(M5,lvl_5[ID],0),MATCH(_xlfn.CONCAT(TEXT(K5,"##0"),"_",TEXT(L5,"##0")),lvl_5[#Headers],0)),"Нет") -> Нет | H5: =IFERROR(INDEX(lvl_6[],MATCH(N5,lvl_6[ID],0),MATCH(_xlfn.CONCAT(K5,"_",L5,"_",M5),lvl_6[#Headers],0)),"Нет") -> Нет | I5: 1 | J5: 2 | K5: 2 | L5: 2 | M5: 0 | N5: 0 | O5: =COUNTIF($P$2:P5,P5) -> 2 | P5: =_xlfn.CONCAT(I5, J5, K5, IF(LEN(L5)=1,_xlfn.CONCAT(0,L5),L5), IF(LEN(M5)=1,_xlfn.CONCAT(0,M5),M5), IF(LEN(N5)=1,_xlfn.CONCAT(0,N5),N5)) -> 122020000 | Q5: =_xlfn.CONCAT(I5, J5, K5, IF(LEN(L5)=1,_xlfn.CONCAT(0,L5),L5), IF(LEN(M5)=1,_xlfn.CONCAT(0,M5),M5), IF(LEN(N5)=1,_xlfn.CONCAT(0,N5),N5), IF(LEN(O5)=1,_xlfn.CONCAT("000",O5),IF(LEN(O5)=2,_xlfn.CONCAT("00",O5),IF(LEN(O5)=3,_xlfn.CONCAT(0,O5),O5)))) -> 1220200000002 | R5: Три генерала допущены в главный зал | S5: Посредничество знатного человека поможет в денежных вопросах | AW5: 9 | AY5: 丙 | BB5: 生 | BG5: 1 | BJ5: 1
A6: 1 | B6: =_xlfn.CONCAT(C6,". ", D6,". ", E6,". ", F6,". ", G6,". ", H6) -> Общий расчет. Ци Мень. Анализ Дворца. Комбинации. Нет. Нет | C6: =IFERROR(VLOOKUP(I6,lvl_1[],2,FALSE),"Нет") -> Общий расчет | D6: =IFERROR(VLOOKUP(Rule!J6,lvl_2[],2,FALSE),"Нет") -> Ци Мень | E6: =IFERROR(VLOOKUP(Rule!K6,lvl_3[],2,FALSE),"Нет") -> Анализ Дворца | F6: =IFERROR(INDEX(lvl_4[],MATCH(L6,lvl_4[ID],0),MATCH(TEXT(K6,"##0"),lvl_4[#Headers],0)),"Нет") -> Комбинации | G6: =IFERROR(INDEX(lvl_5[],MATCH(M6,lvl_5[ID],0),MATCH(_xlfn.CONCAT(TEXT(K6,"##0"),"_",TEXT(L6,"##0")),lvl_5[#Headers],0)),"Нет") -> Нет | H6: =IFERROR(INDEX(lvl_6[],MATCH(N6,lvl_6[ID],0),MATCH(_xlfn.CONCAT(K6,"_",L6,"_",M6),lvl_6[#Headers],0)),"Нет") -> Нет | I6: 1 | J6: 2 | K6: 2 | L6: 2 | M6: 0 | N6: 0 | O6: =COUNTIF($P$2:P6,P6) -> 3 | P6: =_xlfn.CONCAT(I6, J6, K6, IF(LEN(L6)=1,_xlfn.CONCAT(0,L6),L6), IF(LEN(M6)=1,_xlfn.CONCAT(0,M6),M6), IF(LEN(N6)=1,_xlfn.CONCAT(0,N6),N6)) -> 122020000 | Q6: =_xlfn.CONCAT(I6, J6, K6, IF(LEN(L6)=1,_xlfn.CONCAT(0,L6),L6), IF(LEN(M6)=1,_xlfn.CONCAT(0,M6),M6), IF(LEN(N6)=1,_xlfn.CONCAT(0,N6),N6), IF(LEN(O6)=1,_xlfn.CONCAT("000",O6),IF(LEN(O6)=2,_xlfn.CONCAT("00",O6),IF(LEN(O6)=3,_xlfn.CONCAT(0,O6),O6)))) -> 1220200000003 | R6: Три генерала допущены в главный зал | S6: Посредничество знатного человека поможет в денежных вопросах | AW6: 9 | AY6: 丙 | BB6: 休 | BG6: 1 | BJ6: 1
A7: 1 | B7: =_xlfn.CONCAT(C7,". ", D7,". ", E7,". ", F7,". ", G7,". ", H7) -> Общий расчет. Ци Мень. Анализ Дворца. Комбинации. Нет. Нет | C7: =IFERROR(VLOOKUP(I7,lvl_1[],2,FALSE),"Нет") -> Общий расчет | D7: =IFERROR(VLOOKUP(Rule!J7,lvl_2[],2,FALSE),"Нет") -> Ци Мень | E7: =IFERROR(VLOOKUP(Rule!K7,lvl_3[],2,FALSE),"Нет") -> Анализ Дворца | F7: =IFERROR(INDEX(lvl_4[],MATCH(L7,lvl_4[ID],0),MATCH(TEXT(K7,"##0"),lvl_4[#Headers],0)),"Нет") -> Комбинации | G7: =IFERROR(INDEX(lvl_5[],MATCH(M7,lvl_5[ID],0),MATCH(_xlfn.CONCAT(TEXT(K7,"##0"),"_",TEXT(L7,"##0")),lvl_5[#Headers],0)),"Нет") -> Нет | H7: =IFERROR(INDEX(lvl_6[],MATCH(N7,lvl_6[ID],0),MATCH(_xlfn.CONCAT(K7,"_",L7,"_",M7),lvl_6[#Headers],0)),"Нет") -> Нет | I7: 1 | J7: 2 | K7: 2 | L7: 2 | M7: 0 | N7: 0 | O7: =COUNTIF($P$2:P7,P7) -> 4 | P7: =_xlfn.CONCAT(I7, J7, K7, IF(LEN(L7)=1,_xlfn.CONCAT(0,L7),L7), IF(LEN(M7)=1,_xlfn.CONCAT(0,M7),M7), IF(LEN(N7)=1,_xlfn.CONCAT(0,N7),N7)) -> 122020000 | Q7: =_xlfn.CONCAT(I7, J7, K7, IF(LEN(L7)=1,_xlfn.CONCAT(0,L7),L7), IF(LEN(M7)=1,_xlfn.CONCAT(0,M7),M7), IF(LEN(N7)=1,_xlfn.CONCAT(0,N7),N7), IF(LEN(O7)=1,_xlfn.CONCAT("000",O7),IF(LEN(O7)=2,_xlfn.CONCAT("00",O7),IF(LEN(O7)=3,_xlfn.CONCAT(0,O7),O7)))) -> 1220200000004 | R7: Три генерала допущены в главный зал | S7: Посредничество знатного человека поможет в денежных вопросах | AW7: 9 | AY7: 丙 | BB7: 開 | BG7: 1 | BJ7: 1
A8: 1 | B8: =_xlfn.CONCAT(C8,". ", D8,". ", E8,". ", F8,". ", G8,". ", H8) -> Общий расчет. Ци Мень. Анализ Дворца. Комбинации. Нет. Нет | C8: =IFERROR(VLOOKUP(I8,lvl_1[],2,FALSE),"Нет") -> Общий расчет | D8: =IFERROR(VLOOKUP(Rule!J8,lvl_2[],2,FALSE),"Нет") -> Ци Мень | E8: =IFERROR(VLOOKUP(Rule!K8,lvl_3[],2,FALSE),"Нет") -> Анализ Дворца | F8: =IFERROR(INDEX(lvl_4[],MATCH(L8,lvl_4[ID],0),MATCH(TEXT(K8,"##0"),lvl_4[#Headers],0)),"Нет") -> Комбинации | G8: =IFERROR(INDEX(lvl_5[],MATCH(M8,lvl_5[ID],0),MATCH(_xlfn.CONCAT(TEXT(K8,"##0"),"_",TEXT(L8,"##0")),lvl_5[#Headers],0)),"Нет") -> Нет | H8: =IFERROR(INDEX(lvl_6[],MATCH(N8,lvl_6[ID],0),MATCH(_xlfn.CONCAT(K8,"_",L8,"_",M8),lvl_6[#Headers],0)),"Нет") -> Нет | I8: 1 | J8: 2 | K8: 2 | L8: 2 | M8: 0 | N8: 0 | O8: =COUNTIF($P$2:P8,P8) -> 5 | P8: =_xlfn.CONCAT(I8, J8, K8, IF(LEN(L8)=1,_xlfn.CONCAT(0,L8),L8), IF(LEN(M8)=1,_xlfn.CONCAT(0,M8),M8), IF(LEN(N8)=1,_xlfn.CONCAT(0,N8),N8)) -> 122020000 | Q8: =_xlfn.CONCAT(I8, J8, K8, IF(LEN(L8)=1,_xlfn.CONCAT(0,L8),L8), IF(LEN(M8)=1,_xlfn.CONCAT(0,M8),M8), IF(LEN(N8)=1,_xlfn.CONCAT(0,N8),N8), IF(LEN(O8)=1,_xlfn.CONCAT("000",O8),IF(LEN(O8)=2,_xlfn.CONCAT("00",O8),IF(LEN(O8)=3,_xlfn.CONCAT(0,O8),O8)))) -> 1220200000005 | R8: Три генерала допущены в главный зал | S8: Посредничество знатного человека поможет в денежных вопросах | AW8: 7 | AY8: 丁 | BB8: 生 | BG8: 1 | BJ8: 1
A9: 1 | B9: =_xlfn.CONCAT(C9,". ", D9,". ", E9,". ", F9,". ", G9,". ", H9) -> Общий расчет. Ци Мень. Анализ Дворца. Комбинации. Нет. Нет | C9: =IFERROR(VLOOKUP(I9,lvl_1[],2,FALSE),"Нет") -> Общий расчет | D9: =IFERROR(VLOOKUP(Rule!J9,lvl_2[],2,FALSE),"Нет") -> Ци Мень | E9: =IFERROR(VLOOKUP(Rule!K9,lvl_3[],2,FALSE),"Нет") -> Анализ Дворца | F9: =IFERROR(INDEX(lvl_4[],MATCH(L9,lvl_4[ID],0),MATCH(TEXT(K9,"##0"),lvl_4[#Headers],0)),"Нет") -> Комбинации | G9: =IFERROR(INDEX(lvl_5[],MATCH(M9,lvl_5[ID],0),MATCH(_xlfn.CONCAT(TEXT(K9,"##0"),"_",TEXT(L9,"##0")),lvl_5[#Headers],0)),"Нет") -> Нет | H9: =IFERROR(INDEX(lvl_6[],MATCH(N9,lvl_6[ID],0),MATCH(_xlfn.CONCAT(K9,"_",L9,"_",M9),lvl_6[#Headers],0)),"Нет") -> Нет | I9: 1 | J9: 2 | K9: 2 | L9: 2 | M9: 0 | N9: 0 | O9: =COUNTIF($P$2:P9,P9) -> 6 | P9: =_xlfn.CONCAT(I9, J9, K9, IF(LEN(L9)=1,_xlfn.CONCAT(0,L9),L9), IF(LEN(M9)=1,_xlfn.CONCAT(0,M9),M9), IF(LEN(N9)=1,_xlfn.CONCAT(0,N9),N9)) -> 122020000 | Q9: =_xlfn.CONCAT(I9, J9, K9, IF(LEN(L9)=1,_xlfn.CONCAT(0,L9),L9), IF(LEN(M9)=1,_xlfn.CONCAT(0,M9),M9), IF(LEN(N9)=1,_xlfn.CONCAT(0,N9),N9), IF(LEN(O9)=1,_xlfn.CONCAT("000",O9),IF(LEN(O9)=2,_xlfn.CONCAT("00",O9),IF(LEN(O9)=3,_xlfn.CONCAT(0,O9),O9)))) -> 1220200000006 | R9: Три генерала допущены в главный зал | S9: Посредничество знатного человека поможет в денежных вопросах | AW9: 7 | AY9: 丁 | BB9: 休 | BG9: 1 | BJ9: 1
A10: 1 | B10: =_xlfn.CONCAT(C10,". ", D10,". ", E10,". ", F10,". ", G10,". ", H10) -> Общий расчет. Ци Мень. Анализ Дворца. Комбинации. Нет. Нет | C10: =IFERROR(VLOOKUP(I10,lvl_1[],2,FALSE),"Нет") -> Общий расчет | D10: =IFERROR(VLOOKUP(Rule!J10,lvl_2[],2,FALSE),"Нет") -> Ци Мень | E10: =IFERROR(VLOOKUP(Rule!K10,lvl_3[],2,FALSE),"Нет") -> Анализ Дворца | F10: =IFERROR(INDEX(lvl_4[],MATCH(L10,lvl_4[ID],0),MATCH(TEXT(K10,"##0"),lvl_4[#Headers],0)),"Нет") -> Комбинации | G10: =IFERROR(INDEX(lvl_5[],MATCH(M10,lvl_5[ID],0),MATCH(_xlfn.CONCAT(TEXT(K10,"##0"),"_",TEXT(L10,"##0")),lvl_5[#Headers],0)),"Нет") -> Нет | H10: =IFERROR(INDEX(lvl_6[],MATCH(N10,lvl_6[ID],0),MATCH(_xlfn.CONCAT(K10,"_",L10,"_",M10),lvl_6[#Headers],0)),"Нет") -> Нет | I10: 1 | J10: 2 | K10: 2 | L10: 2 | M10: 0 | N10: 0 | O10: =COUNTIF($P$2:P10,P10) -> 7 | P10: =_xlfn.CONCAT(I10, J10, K10, IF(LEN(L10)=1,_xlfn.CONCAT(0,L10),L10), IF(LEN(M10)=1,_xlfn.CONCAT(0,M10),M10), IF(LEN(N10)=1,_xlfn.CONCAT(0,N10),N10)) -> 122020000 | Q10: =_xlfn.CONCAT(I10, J10, K10, IF(LEN(L10)=1,_xlfn.CONCAT(0,L10),L10), IF(LEN(M10)=1,_xlfn.CONCAT(0,M10),M10), IF(LEN(N10)=1,_xlfn.CONCAT(0,N10),N10), IF(LEN(O10)=1,_xlfn.CONCAT("000",O10),IF(LEN(O10)=2,_xlfn.CONCAT("00",O10),IF(LEN(O10)=3,_xlfn.CONCAT(0,O10),O10)))) -> 1220200000007 | R10: Три генерала допущены в главный зал | S10: Посредничество знатного человека поможет в денежных вопросах | AW10: 7 | AY10: 丁 | BB10: 開 | BG10: 1 | BJ10: 1
A11: 1 | B11: =_xlfn.CONCAT(C11,". ", D11,". ", E11,". ", F11,". ", G11,". ", H11) -> Общий расчет. Ци Мень. Анализ Дворца. Комбинации. Нет. Нет | C11: =IFERROR(VLOOKUP(I11,lvl_1[],2,FALSE),"Нет") -> Общий расчет | D11: =IFERROR(VLOOKUP(Rule!J11,lvl_2[],2,FALSE),"Нет") -> Ци Мень | E11: =IFERROR(VLOOKUP(Rule!K11,lvl_3[],2,FALSE),"Нет") -> Анализ Дворца | F11: =IFERROR(INDEX(lvl_4[],MATCH(L11,lvl_4[ID],0),MATCH(TEXT(K11,"##0"),lvl_4[#Headers],0)),"Нет") -> Комбинации | G11: =IFERROR(INDEX(lvl_5[],MATCH(M11,lvl_5[ID],0),MATCH(_xlfn.CONCAT(TEXT(K11,"##0"),"_",TEXT(L11,"##0")),lvl_5[#Headers],0)),"Нет") -> Нет | H11: =IFERROR(INDEX(lvl_6[],MATCH(N11,lvl_6[ID],0),MATCH(_xlfn.CONCAT(K11,"_",L11,"_",M11),lvl_6[#Headers],0)),"Нет") -> Нет | I11: 1 | J11: 2 | K11: 2 | L11: 2 | M11: 0 | N11: 0 | O11: =COUNTIF($P$2:P11,P11) -> 8 | P11: =_xlfn.CONCAT(I11, J11, K11, IF(LEN(L11)=1,_xlfn.CONCAT(0,L11),L11), IF(LEN(M11)=1,_xlfn.CONCAT(0,M11),M11), IF(LEN(N11)=1,_xlfn.CONCAT(0,N11),N11)) -> 122020000 | Q11: =_xlfn.CONCAT(I11, J11, K11, IF(LEN(L11)=1,_xlfn.CONCAT(0,L11),L11), IF(LEN(M11)=1,_xlfn.CONCAT(0,M11),M11), IF(LEN(N11)=1,_xlfn.CONCAT(0,N11),N11), IF(LEN(O11)=1,_xlfn.CONCAT("000",O11),IF(LEN(O11)=2,_xlfn.CONCAT("00",O11),IF(LEN(O11)=3,_xlfn.CONCAT(0,O11),O11)))) -> 1220200000008 | R11: Три генерала допущены в главный зал | S11: Посредничество знатного человека поможет в денежных вопросах | AW11: 3 | AY11: 乙 | BB11: 生 | BG11: 1 | BJ11: 1
A12: 1 | B12: =_xlfn.CONCAT(C12,". ", D12,". ", E12,". ", F12,". ", G12,". ", H12) -> Общий расчет. Ци Мень. Анализ Дворца. Комбинации. Нет. Нет | C12: =IFERROR(VLOOKUP(I12,lvl_1[],2,FALSE),"Нет") -> Общий расчет | D12: =IFERROR(VLOOKUP(Rule!J12,lvl_2[],2,FALSE),"Нет") -> Ци Мень | E12: =IFERROR(VLOOKUP(Rule!K12,lvl_3[],2,FALSE),"Нет") -> Анализ Дворца | F12: =IFERROR(INDEX(lvl_4[],MATCH(L12,lvl_4[ID],0),MATCH(TEXT(K12,"##0"),lvl_4[#Headers],0)),"Нет") -> Комбинации | G12: =IFERROR(INDEX(lvl_5[],MATCH(M12,lvl_5[ID],0),MATCH(_xlfn.CONCAT(TEXT(K12,"##0"),"_",TEXT(L12,"##0")),lvl_5[#Headers],0)),"Нет") -> Нет | H12: =IFERROR(INDEX(lvl_6[],MATCH(N12,lvl_6[ID],0),MATCH(_xlfn.CONCAT(K12,"_",L12,"_",M12),lvl_6[#Headers],0)),"Нет") -> Нет | I12: 1 | J12: 2 | K12: 2 | L12: 2 | M12: 0 | N12: 0 | O12: =COUNTIF($P$2:P12,P12) -> 9 | P12: =_xlfn.CONCAT(I12, J12, K12, IF(LEN(L12)=1,_xlfn.CONCAT(0,L12),L12), IF(LEN(M12)=1,_xlfn.CONCAT(0,M12),M12), IF(LEN(N12)=1,_xlfn.CONCAT(0,N12),N12)) -> 122020000 | Q12: =_xlfn.CONCAT(I12, J12, K12, IF(LEN(L12)=1,_xlfn.CONCAT(0,L12),L12), IF(LEN(M12)=1,_xlfn.CONCAT(0,M12),M12), IF(LEN(N12)=1,_xlfn.CONCAT(0,N12),N12), IF(LEN(O12)=1,_xlfn.CONCAT("000",O12),IF(LEN(O12)=2,_xlfn.CONCAT("00",O12),IF(LEN(O12)=3,_xlfn.CONCAT(0,O12),O12)))) -> 1220200000009 | R12: Три генерала допущены в главный зал | S12: Посредничество знатного человека поможет в денежных вопросах | AW12: 3 | AY12: 乙 | BB12: 休 | BG12: 1 | BJ12: 1
A13: 1 | B13: =_xlfn.CONCAT(C13,". ", D13,". ", E13,". ", F13,". ", G13,". ", H13) -> Общий расчет. Ци Мень. Анализ Дворца. Комбинации. Нет. Нет | C13: =IFERROR(VLOOKUP(I13,lvl_1[],2,FALSE),"Нет") -> Общий расчет | D13: =IFERROR(VLOOKUP(Rule!J13,lvl_2[],2,FALSE),"Нет") -> Ци Мень | E13: =IFERROR(VLOOKUP(Rule!K13,lvl_3[],2,FALSE),"Нет") -> Анализ Дворца | F13: =IFERROR(INDEX(lvl_4[],MATCH(L13,lvl_4[ID],0),MATCH(TEXT(K13,"##0"),lvl_4[#Headers],0)),"Нет") -> Комбинации | G13: =IFERROR(INDEX(lvl_5[],MATCH(M13,lvl_5[ID],0),MATCH(_xlfn.CONCAT(TEXT(K13,"##0"),"_",TEXT(L13,"##0")),lvl_5[#Headers],0)),"Нет") -> Нет | H13: =IFERROR(INDEX(lvl_6[],MATCH(N13,lvl_6[ID],0),MATCH(_xlfn.CONCAT(K13,"_",L13,"_",M13),lvl_6[#Headers],0)),"Нет") -> Нет | I13: 1 | J13: 2 | K13: 2 | L13: 2 | M13: 0 | N13: 0 | O13: =COUNTIF($P$2:P13,P13) -> 10 | P13: =_xlfn.CONCAT(I13, J13, K13, IF(LEN(L13)=1,_xlfn.CONCAT(0,L13),L13), IF(LEN(M13)=1,_xlfn.CONCAT(0,M13),M13), IF(LEN(N13)=1,_xlfn.CONCAT(0,N13),N13)) -> 122020000 | Q13: =_xlfn.CONCAT(I13, J13, K13, IF(LEN(L13)=1,_xlfn.CONCAT(0,L13),L13), IF(LEN(M13)=1,_xlfn.CONCAT(0,M13),M13), IF(LEN(N13)=1,_xlfn.CONCAT(0,N13),N13), IF(LEN(O13)=1,_xlfn.CONCAT("000",O13),IF(LEN(O13)=2,_xlfn.CONCAT("00",O13),IF(LEN(O13)=3,_xlfn.CONCAT(0,O13),O13)))) -> 1220200000010 | R13: Три генерала допущены в главный зал | S13: Посредничество знатного человека поможет в денежных вопросах | AW13: 3 | AY13: 乙 | BB13: 開 | BG13: 1 | BJ13: 1
A14: 1 | B14: =_xlfn.CONCAT(C14,". ", D14,". ", E14,". ", F14,". ", G14,". ", H14) -> Общий расчет. Ци Мень. Анализ Дворца. Комбинации. Нет. Нет | C14: =IFERROR(VLOOKUP(I14,lvl_1[],2,FALSE),"Нет") -> Общий расчет | D14: =IFERROR(VLOOKUP(Rule!J14,lvl_2[],2,FALSE),"Нет") -> Ци Мень | E14: =IFERROR(VLOOKUP(Rule!K14,lvl_3[],2,FALSE),"Нет") -> Анализ Дворца | F14: =IFERROR(INDEX(lvl_4[],MATCH(L14,lvl_4[ID],0),MATCH(TEXT(K14,"##0"),lvl_4[#Headers],0)),"Нет") -> Комбинации | G14: =IFERROR(INDEX(lvl_5[],MATCH(M14,lvl_5[ID],0),MATCH(_xlfn.CONCAT(TEXT(K14,"##0"),"_",TEXT(L14,"##0")),lvl_5[#Headers],0)),"Нет") -> Нет | H14: =IFERROR(INDEX(lvl_6[],MATCH(N14,lvl_6[ID],0),MATCH(_xlfn.CONCAT(K14,"_",L14,"_",M14),lvl_6[#Headers],0)),"Нет") -> Нет | I14: 1 | J14: 2 | K14: 2 | L14: 2 | M14: 0 | N14: 0 | O14: =COUNTIF($P$2:P14,P14) -> 11 | P14: =_xlfn.CONCAT(I14, J14, K14, IF(LEN(L14)=1,_xlfn.CONCAT(0,L14),L14), IF(LEN(M14)=1,_xlfn.CONCAT(0,M14),M14), IF(LEN(N14)=1,_xlfn.CONCAT(0,N14),N14)) -> 122020000 | Q14: =_xlfn.CONCAT(I14, J14, K14, IF(LEN(L14)=1,_xlfn.CONCAT(0,L14),L14), IF(LEN(M14)=1,_xlfn.CONCAT(0,M14),M14), IF(LEN(N14)=1,_xlfn.CONCAT(0,N14),N14), IF(LEN(O14)=1,_xlfn.CONCAT("000",O14),IF(LEN(O14)=2,_xlfn.CONCAT("00",O14),IF(LEN(O14)=3,_xlfn.CONCAT(0,O14),O14)))) -> 1220200000011 | R14: 9 Дунь. Человеческая структура (Рэн Дунь – Ren Dun) | S14: Энергия для решения проблем и устранения негатива в человеческих отношениях, для поиска помощи, получения рекомендаций, назначения свиданий, сватовства, брака, переговоров, тайных договоров, торговли и финансовых сделок | AY14: 乙 | BB14: 休 | BF14: 合 | BG14: 1 | BJ14: 1
A15: 1 | B15: =_xlfn.CONCAT(C15,". ", D15,". ", E15,". ", F15,". ", G15,". ", H15) -> Общий расчет. Ци Мень. Анализ Дворца. Комбинации. Нет. Нет | C15: =IFERROR(VLOOKUP(I15,lvl_1[],2,FALSE),"Нет") -> Общий расчет | D15: =IFERROR(VLOOKUP(Rule!J15,lvl_2[],2,FALSE),"Нет") -> Ци Мень | E15: =IFERROR(VLOOKUP(Rule!K15,lvl_3[],2,FALSE),"Нет") -> Анализ Дворца | F15: =IFERROR(INDEX(lvl_4[],MATCH(L15,lvl_4[ID],0),MATCH(TEXT(K15,"##0"),lvl_4[#Headers],0)),"Нет") -> Комбинации | G15: =IFERROR(INDEX(lvl_5[],MATCH(M15,lvl_5[ID],0),MATCH(_xlfn.CONCAT(TEXT(K15,"##0"),"_",TEXT(L15,"##0")),lvl_5[#Headers],0)),"Нет") -> Нет | H15: =IFERROR(INDEX(lvl_6[],MATCH(N15,lvl_6[ID],0),MATCH(_xlfn.CONCAT(K15,"_",L15,"_",M15),lvl_6[#Headers],0)),"Нет") -> Нет | I15: 1 | J15: 2 | K15: 2 | L15: 2 | M15: 0 | N15: 0 | O15: =COUNTIF($P$2:P15,P15) -> 12 | P15: =_xlfn.CONCAT(I15, J15, K15, IF(LEN(L15)=1,_xlfn.CONCAT(0,L15),L15), IF(LEN(M15)=1,_xlfn.CONCAT(0,M15),M15), IF(LEN(N15)=1,_xlfn.CONCAT(0,N15),N15)) -> 122020000 | Q15: =_xlfn.CONCAT(I15, J15, K15, IF(LEN(L15)=1,_xlfn.CONCAT(0,L15),L15), IF(LEN(M15)=1,_xlfn.CONCAT(0,M15),M15), IF(LEN(N15)=1,_xlfn.CONCAT(0,N15),N15), IF(LEN(O15)=1,_xlfn.CONCAT("000",O15),IF(LEN(O15)=2,_xlfn.CONCAT("00",O15),IF(LEN(O15)=3,_xlfn.CONCAT(0,O15),O15)))) -> 1220200000012 | R15: 9 Дунь. Человеческая структура (Рэн Дунь – Ren Dun) | S15: Энергия для решения проблем и устранения негатива в человеческих отношениях, для поиска помощи, получения рекомендаций, назначения свиданий, сватовства, брака, переговоров, тайных договоров, торговли и финансовых сделок | AY15: 乙 | BB15: 生 | BF15: 合 | BG15: 1 | BJ15: 1
A16: 1 | B16: =_xlfn.CONCAT(C16,". ", D16,". ", E16,". ", F16,". ", G16,". ", H16) -> Общий расчет. Ци Мень. Анализ Дворца. Комбинации. Нет. Нет | C16: =IFERROR(VLOOKUP(I16,lvl_1[],2,FALSE),"Нет") -> Общий расчет | D16: =IFERROR(VLOOKUP(Rule!J16,lvl_2[],2,FALSE),"Нет") -> Ци Мень | E16: =IFERROR(VLOOKUP(Rule!K16,lvl_3[],2,FALSE),"Нет") -> Анализ Дворца | F16: =IFERROR(INDEX(lvl_4[],MATCH(L16,lvl_4[ID],0),MATCH(TEXT(K16,"##0"),lvl_4[#Headers],0)),"Нет") -> Комбинации | G16: =IFERROR(INDEX(lvl_5[],MATCH(M16,lvl_5[ID],0),MATCH(_xlfn.CONCAT(TEXT(K16,"##0"),"_",TEXT(L16,"##0")),lvl_5[#Headers],0)),"Нет") -> Нет | H16: =IFERROR(INDEX(lvl_6[],MATCH(N16,lvl_6[ID],0),MATCH(_xlfn.CONCAT(K16,"_",L16,"_",M16),lvl_6[#Headers],0)),"Нет") -> Нет | I16: 1 | J16: 2 | K16: 2 | L16: 2 | M16: 0 | N16: 0 | O16: =COUNTIF($P$2:P16,P16) -> 13 | P16: =_xlfn.CONCAT(I16, J16, K16, IF(LEN(L16)=1,_xlfn.CONCAT(0,L16),L16), IF(LEN(M16)=1,_xlfn.CONCAT(0,M16),M16), IF(LEN(N16)=1,_xlfn.CONCAT(0,N16),N16)) -> 122020000 | Q16: =_xlfn.CONCAT(I16, J16, K16, IF(LEN(L16)=1,_xlfn.CONCAT(0,L16),L16), IF(LEN(M16)=1,_xlfn.CONCAT(0,M16),M16), IF(LEN(N16)=1,_xlfn.CONCAT(0,N16),N16), IF(LEN(O16)=1,_xlfn.CONCAT("000",O16),IF(LEN(O16)=2,_xlfn.CONCAT("00",O16),IF(LEN(O16)=3,_xlfn.CONCAT(0,O16),O16)))) -> 1220200000013 | R16: 9 Дунь. Человеческая структура (Рэн Дунь – Ren Dun) | S16: Энергия для решения проблем и устранения негатива в человеческих отношениях, для поиска помощи, получения рекомендаций, назначения свиданий, сватовства, брака, переговоров, тайных договоров, торговли и финансовых сделок | AY16: 乙 | BB16: 開 | BF16: 合 | BG16: 1 | BJ16: 1
A17: 1 | B17: =_xlfn.CONCAT(C17,". ", D17,". ", E17,". ", F17,". ", G17,". ", H17) -> Общий расчет. Ци Мень. Анализ Дворца. Комбинации. Нет. Нет | C17: =IFERROR(VLOOKUP(I17,lvl_1[],2,FALSE),"Нет") -> Общий расчет | D17: =IFERROR(VLOOKUP(Rule!J17,lvl_2[],2,FALSE),"Нет") -> Ци Мень | E17: =IFERROR(VLOOKUP(Rule!K17,lvl_3[],2,FALSE),"Нет") -> Анализ Дворца | F17: =IFERROR(INDEX(lvl_4[],MATCH(L17,lvl_4[ID],0),MATCH(TEXT(K17,"##0"),lvl_4[#Headers],0)),"Нет") -> Комбинации | G17: =IFERROR(INDEX(lvl_5[],MATCH(M17,lvl_5[ID],0),MATCH(_xlfn.CONCAT(TEXT(K17,"##0"),"_",TEXT(L17,"##0")),lvl_5[#Headers],0)),"Нет") -> Нет | H17: =IFERROR(INDEX(lvl_6[],MATCH(N17,lvl_6[ID],0),MATCH(_xlfn.CONCAT(K17,"_",L17,"_",M17),lvl_6[#Headers],0)),"Нет") -> Нет | I17: 1 | J17: 2 | K17: 2 | L17: 2 | M17: 0 | N17: 0 | O17: =COUNTIF($P$2:P17,P17) -> 14 | P17: =_xlfn.CONCAT(I17, J17, K17, IF(LEN(L17)=1,_xlfn.CONCAT(0,L17),L17), IF(LEN(M17)=1,_xlfn.CONCAT(0,M17),M17), IF(LEN(N17)=1,_xlfn.CONCAT(0,N17),N17)) -> 122020000 | Q17: =_xlfn.CONCAT(I17, J17, K17, IF(LEN(L17)=1,_xlfn.CONCAT(0,L17),L17), IF(LEN(M17)=1,_xlfn.CONCAT(0,M17),M17), IF(LEN(N17)=1,_xlfn.CONCAT(0,N17),N17), IF(LEN(O17)=1,_xlfn.CONCAT("000",O17),IF(LEN(O17)=2,_xlfn.CONCAT("00",O17),IF(LEN(O17)=3,_xlfn.CONCAT(0,O17),O17)))) -> 1220200000014 | R17: 9 Дунь. Человеческая структура (Рэн Дунь – Ren Dun) | S17: Энергия для решения проблем и устранения негатива в человеческих отношениях, для поиска помощи, получения рекомендаций, назначения свиданий, сватовства, брака, переговоров, тайных договоров, торговли и финансовых сделок | AY17: 丙 | BB17: 休 | BF17: 合 | BG17: 1 | BJ17: 1
A18: 1 | B18: =_xlfn.CONCAT(C18,". ", D18,". ", E18,". ", F18,". ", G18,". ", H18) -> Общий расчет. Ци Мень. Анализ Дворца. Комбинации. Нет. Нет | C18: =IFERROR(VLOOKUP(I18,lvl_1[],2,FALSE),"Нет") -> Общий расчет | D18: =IFERROR(VLOOKUP(Rule!J18,lvl_2[],2,FALSE),"Нет") -> Ци Мень | E18: =IFERROR(VLOOKUP(Rule!K18,lvl_3[],2,FALSE),"Нет") -> Анализ Дворца | F18: =IFERROR(INDEX(lvl_4[],MATCH(L18,lvl_4[ID],0),MATCH(TEXT(K18,"##0"),lvl_4[#Headers],0)),"Нет") -> Комбинации | G18: =IFERROR(INDEX(lvl_5[],MATCH(M18,lvl_5[ID],0),MATCH(_xlfn.CONCAT(TEXT(K18,"##0"),"_",TEXT(L18,"##0")),lvl_5[#Headers],0)),"Нет") -> Нет | H18: =IFERROR(INDEX(lvl_6[],MATCH(N18,lvl_6[ID],0),MATCH(_xlfn.CONCAT(K18,"_",L18,"_",M18),lvl_6[#Headers],0)),"Нет") -> Нет | I18: 1 | J18: 2 | K18: 2 | L18: 2 | M18: 0 | N18: 0 | O18: =COUNTIF($P$2:P18,P18) -> 15 | P18: =_xlfn.CONCAT(I18, J18, K18, IF(LEN(L18)=1,_xlfn.CONCAT(0,L18),L18), IF(LEN(M18)=1,_xlfn.CONCAT(0,M18),M18), IF(LEN(N18)=1,_xlfn.CONCAT(0,N18),N18)) -> 122020000 | Q18: =_xlfn.CONCAT(I18, J18, K18, IF(LEN(L18)=1,_xlfn.CONCAT(0,L18),L18), IF(LEN(M18)=1,_xlfn.CONCAT(0,M18),M18), IF(LEN(N18)=1,_xlfn.CONCAT(0,N18),N18), IF(LEN(O18)=1,_xlfn.CONCAT("000",O18),IF(LEN(O18)=2,_xlfn.CONCAT("00",O18),IF(LEN(O18)=3,_xlfn.CONCAT(0,O18),O18)))) -> 1220200000015 | R18: 9 Дунь. Человеческая структура (Рэн Дунь – Ren Dun) | S18: Энергия для решения проблем и устранения негатива в человеческих отношениях, для поиска помощи, получения рекомендаций, назначения свиданий, сватовства, брака, переговоров, тайных договоров, торговли и финансовых сделок | AY18: 丙 | BB18: 生 | BF18: 合 | BG18: 1 | BJ18: 1
A19: 1 | B19: =_xlfn.CONCAT(C19,". ", D19,". ", E19,". ", F19,". ", G19,". ", H19) -> Общий расчет. Ци Мень. Анализ Дворца. Комбинации. Нет. Нет | C19: =IFERROR(VLOOKUP(I19,lvl_1[],2,FALSE),"Нет") -> Общий расчет | D19: =IFERROR(VLOOKUP(Rule!J19,lvl_2[],2,FALSE),"Нет") -> Ци Мень | E19: =IFERROR(VLOOKUP(Rule!K19,lvl_3[],2,FALSE),"Нет") -> Анализ Дворца | F19: =IFERROR(INDEX(lvl_4[],MATCH(L19,lvl_4[ID],0),MATCH(TEXT(K19,"##0"),lvl_4[#Headers],0)),"Нет") -> Комбинации | G19: =IFERROR(INDEX(lvl_5[],MATCH(M19,lvl_5[ID],0),MATCH(_xlfn.CONCAT(TEXT(K19,"##0"),"_",TEXT(L19,"##0")),lvl_5[#Headers],0)),"Нет") -> Нет | H19: =IFERROR(INDEX(lvl_6[],MATCH(N19,lvl_6[ID],0),MATCH(_xlfn.CONCAT(K19,"_",L19,"_",M19),lvl_6[#Headers],0)),"Нет") -> Нет | I19: 1 | J19: 2 | K19: 2 | L19: 2 | M19: 0 | N19: 0 | O19: =COUNTIF($P$2:P19,P19) -> 16 | P19: =_xlfn.CONCAT(I19, J19, K19, IF(LEN(L19)=1,_xlfn.CONCAT(0,L19),L19), IF(LEN(M19)=1,_xlfn.CONCAT(0,M19),M19), IF(LEN(N19)=1,_xlfn.CONCAT(0,N19),N19)) -> 122020000 | Q19: =_xlfn.CONCAT(I19, J19, K19, IF(LEN(L19)=1,_xlfn.CONCAT(0,L19),L19), IF(LEN(M19)=1,_xlfn.CONCAT(0,M19),M19), IF(LEN(N19)=1,_xlfn.CONCAT(0,N19),N19), IF(LEN(O19)=1,_xlfn.CONCAT("000",O19),IF(LEN(O19)=2,_xlfn.CONCAT("00",O19),IF(LEN(O19)=3,_xlfn.CONCAT(0,O19),O19)))) -> 1220200000016 | R19: 9 Дунь. Человеческая структура (Рэн Дунь – Ren Dun) | S19: Энергия для решения проблем и устранения негатива в человеческих отношениях, для поиска помощи, получения рекомендаций, назначения свиданий, сватовства, брака, переговоров, тайных договоров, торговли и финансовых сделок | AY19: 丙 | BB19: 開 | BF19: 合 | BG19: 1 | BJ19: 1
A20: 1 | B20: =_xlfn.CONCAT(C20,". ", D20,". ", E20,". ", F20,". ", G20,". ", H20) -> Общий расчет. Ци Мень. Анализ Дворца. Комбинации. Нет. Нет | C20: =IFERROR(VLOOKUP(I20,lvl_1[],2,FALSE),"Нет") -> Общий расчет | D20: =IFERROR(VLOOKUP(Rule!J20,lvl_2[],2,FALSE),"Нет") -> Ци Мень | E20: =IFERROR(VLOOKUP(Rule!K20,lvl_3[],2,FALSE),"Нет") -> Анализ Дворца | F20: =IFERROR(INDEX(lvl_4[],MATCH(L20,lvl_4[ID],0),MATCH(TEXT(K20,"##0"),lvl_4[#Headers],0)),"Нет") -> Комбинации | G20: =IFERROR(INDEX(lvl_5[],MATCH(M20,lvl_5[ID],0),MATCH(_xlfn.CONCAT(TEXT(K20,"##0"),"_",TEXT(L20,"##0")),lvl_5[#Headers],0)),"Нет") -> Нет | H20: =IFERROR(INDEX(lvl_6[],MATCH(N20,lvl_6[ID],0),MATCH(_xlfn.CONCAT(K20,"_",L20,"_",M20),lvl_6[#Headers],0)),"Нет") -> Нет | I20: 1 | J20: 2 | K20: 2 | L20: 2 | M20: 0 | N20: 0 | O20: =COUNTIF($P$2:P20,P20) -> 17 | P20: =_xlfn.CONCAT(I20, J20, K20, IF(LEN(L20)=1,_xlfn.CONCAT(0,L20),L20), IF(LEN(M20)=1,_xlfn.CONCAT(0,M20),M20), IF(LEN(N20)=1,_xlfn.CONCAT(0,N20),N20)) -> 122020000 | Q20: =_xlfn.CONCAT(I20, J20, K20, IF(LEN(L20)=1,_xlfn.CONCAT(0,L20),L20), IF(LEN(M20)=1,_xlfn.CONCAT(0,M20),M20), IF(LEN(N20)=1,_xlfn.CONCAT(0,N20),N20), IF(LEN(O20)=1,_xlfn.CONCAT("000",O20),IF(LEN(O20)=2,_xlfn.CONCAT("00",O20),IF(LEN(O20)=3,_xlfn.CONCAT(0,O20),O20)))) -> 1220200000017 | R20: 9 Дунь. Человеческая структура (Рэн Дунь – Ren Dun) | S20: Энергия для решения проблем и устранения негатива в человеческих отношениях, для поиска помощи, получения рекомендаций, назначения свиданий, сватовства, брака, переговоров, тайных договоров, торговли и финансовых сделок | AY20: 丁 | BB20: 休 | BF20: 合 | BG20: 1 | BJ20: 1
A21: 1 | B21: =_xlfn.CONCAT(C21,". ", D21,". ", E21,". ", F21,". ", G21,". ", H21) -> Общий расчет. Ци Мень. Анализ Дворца. Комбинации. Нет. Нет | C21: =IFERROR(VLOOKUP(I21,lvl_1[],2,FALSE),"Нет") -> Общий расчет | D21: =IFERROR(VLOOKUP(Rule!J21,lvl_2[],2,FALSE),"Нет") -> Ци Мень | E21: =IFERROR(VLOOKUP(Rule!K21,lvl_3[],2,FALSE),"Нет") -> Анализ Дворца | F21: =IFERROR(INDEX(lvl_4[],MATCH(L21,lvl_4[ID],0),MATCH(TEXT(K21,"##0"),lvl_4[#Headers],0)),"Нет") -> Комбинации | G21: =IFERROR(INDEX(lvl_5[],MATCH(M21,lvl_5[ID],0),MATCH(_xlfn.CONCAT(TEXT(K21,"##0"),"_",TEXT(L21,"##0")),lvl_5[#Headers],0)),"Нет") -> Нет | H21: =IFERROR(INDEX(lvl_6[],MATCH(N21,lvl_6[ID],0),MATCH(_xlfn.CONCAT(K21,"_",L21,"_",M21),lvl_6[#Headers],0)),"Нет") -> Нет | I21: 1 | J21: 2 | K21: 2 | L21: 2 | M21: 0 | N21: 0 | O21: =COUNTIF($P$2:P21,P21) -> 18 | P21: =_xlfn.CONCAT(I21, J21, K21, IF(LEN(L21)=1,_xlfn.CONCAT(0,L21),L21), IF(LEN(M21)=1,_xlfn.CONCAT(0,M21),M21), IF(LEN(N21)=1,_xlfn.CONCAT(0,N21),N21)) -> 122020000 | Q21: =_xlfn.CONCAT(I21, J21, K21, IF(LEN(L21)=1,_xlfn.CONCAT(0,L21),L21), IF(LEN(M21)=1,_xlfn.CONCAT(0,M21),M21), IF(LEN(N21)=1,_xlfn.CONCAT(0,N21),N21), IF(LEN(O21)=1,_xlfn.CONCAT("000",O21),IF(LEN(O21)=2,_xlfn.CONCAT("00",O21),IF(LEN(O21)=3,_xlfn.CONCAT(0,O21),O21)))) -> 1220200000018 | R21: 9 Дунь. Человеческая структура (Рэн Дунь – Ren Dun) | S21: Энергия для решения проблем и устранения негатива в человеческих отношениях, для поиска помощи, получения рекомендаций, назначения свиданий, сватовства, брака, переговоров, тайных договоров, торговли и финансовых сделок | AY21: 丁 | BB21: 生 | BF21: 合 | BG21: 1 | BJ21: 1
A22: 1 | B22: =_xlfn.CONCAT(C22,". ", D22,". ", E22,". ", F22,". ", G22,". ", H22) -> Общий расчет. Ци Мень. Анализ Дворца. Комбинации. Нет. Нет | C22: =IFERROR(VLOOKUP(I22,lvl_1[],2,FALSE),"Нет") -> Общий расчет | D22: =IFERROR(VLOOKUP(Rule!J22,lvl_2[],2,FALSE),"Нет") -> Ци Мень | E22: =IFERROR(VLOOKUP(Rule!K22,lvl_3[],2,FALSE),"Нет") -> Анализ Дворца | F22: =IFERROR(INDEX(lvl_4[],MATCH(L22,lvl_4[ID],0),MATCH(TEXT(K22,"##0"),lvl_4[#Headers],0)),"Нет") -> Комбинации | G22: =IFERROR(INDEX(lvl_5[],MATCH(M22,lvl_5[ID],0),MATCH(_xlfn.CONCAT(TEXT(K22,"##0"),"_",TEXT(L22,"##0")),lvl_5[#Headers],0)),"Нет") -> Нет | H22: =IFERROR(INDEX(lvl_6[],MATCH(N22,lvl_6[ID],0),MATCH(_xlfn.CONCAT(K22,"_",L22,"_",M22),lvl_6[#Headers],0)),"Нет") -> Нет | I22: 1 | J22: 2 | K22: 2 | L22: 2 | M22: 0 | N22: 0 | O22: =COUNTIF($P$2:P22,P22) -> 19 | P22: =_xlfn.CONCAT(I22, J22, K22, IF(LEN(L22)=1,_xlfn.CONCAT(0,L22),L22), IF(LEN(M22)=1,_xlfn.CONCAT(0,M22),M22), IF(LEN(N22)=1,_xlfn.CONCAT(0,N22),N22)) -> 122020000 | Q22: =_xlfn.CONCAT(I22, J22, K22, IF(LEN(L22)=1,_xlfn.CONCAT(0,L22),L22), IF(LEN(M22)=1,_xlfn.CONCAT(0,M22),M22), IF(LEN(N22)=1,_xlfn.CONCAT(0,N22),N22), IF(LEN(O22)=1,_xlfn.CONCAT("000",O22),IF(LEN(O22)=2,_xlfn.CONCAT("00",O22),IF(LEN(O22)=3,_xlfn.CONCAT(0,O22),O22)))) -> 1220200000019 | R22: 9 Дунь. Человеческая структура (Рэн Дунь – Ren Dun) | S22: Энергия для решения проблем и устранения негатива в человеческих отношениях, для поиска помощи, получения рекомендаций, назначения свиданий, сватовства, брака, переговоров, тайных договоров, торговли и финансовых сделок | AY22: 丁 | BB22: 開 | BF22: 合 | BG22: 1 | BJ22: 1
A23: 1 | B23: =_xlfn.CONCAT(C23,". ", D23,". ", E23,". ", F23,". ", G23,". ", H23) -> Общий расчет. Ци Мень. Анализ Дворца. Комбинации. Нет. Нет | C23: =IFERROR(VLOOKUP(I23,lvl_1[],2,FALSE),"Нет") -> Общий расчет | D23: =IFERROR(VLOOKUP(Rule!J23,lvl_2[],2,FALSE),"Нет") -> Ци Мень | E23: =IFERROR(VLOOKUP(Rule!K23,lvl_3[],2,FALSE),"Нет") -> Анализ Дворца | F23: =IFERROR(INDEX(lvl_4[],MATCH(L23,lvl_4[ID],0),MATCH(TEXT(K23,"##0"),lvl_4[#Headers],0)),"Нет") -> Комбинации | G23: =IFERROR(INDEX(lvl_5[],MATCH(M23,lvl_5[ID],0),MATCH(_xlfn.CONCAT(TEXT(K23,"##0"),"_",TEXT(L23,"##0")),lvl_5[#Headers],0)),"Нет") -> Нет | H23: =IFERROR(INDEX(lvl_6[],MATCH(N23,lvl_6[ID],0),MATCH(_xlfn.CONCAT(K23,"_",L23,"_",M23),lvl_6[#Headers],0)),"Нет") -> Нет | I23: 1 | J23: 2 | K23: 2 | L23: 2 | M23: 0 | N23: 0 | O23: =COUNTIF($P$2:P23,P23) -> 20 | P23: =_xlfn.CONCAT(I23, J23, K23, IF(LEN(L23)=1,_xlfn.CONCAT(0,L23),L23), IF(LEN(M23)=1,_xlfn.CONCAT(0,M23),M23), IF(LEN(N23)=1,_xlfn.CONCAT(0,N23),N23)) -> 122020000 | Q23: =_xlfn.CONCAT(I23, J23, K23, IF(LEN(L23)=1,_xlfn.CONCAT(0,L23),L23), IF(LEN(M23)=1,_xlfn.CONCAT(0,M23),M23), IF(LEN(N23)=1,_xlfn.CONCAT(0,N23),N23), IF(LEN(O23)=1,_xlfn.CONCAT("000",O23),IF(LEN(O23)=2,_xlfn.CONCAT("00",O23),IF(LEN(O23)=3,_xlfn.CONCAT(0,O23),O23)))) -> 1220200000020 | R23: 9 Дунь. Небесный Дунь (Тянь Дунь). Помощь неба | S23: Расцвет во всех делах. Можно подавать прошение, торговать, добиваться повышения. прятать следы, вступать в брак | AY23: 丙 | BA23: 丁 | BB23: 生 | BG23: 1 | BJ23: 1
A24: 1 | B24: =_xlfn.CONCAT(C24,". ", D24,". ", E24,". ", F24,". ", G24,". ", H24) -> Общий расчет. Ци Мень. Анализ Дворца. Комбинации. Нет. Нет | C24: =IFERROR(VLOOKUP(I24,lvl_1[],2,FALSE),"Нет") -> Общий расчет | D24: =IFERROR(VLOOKUP(Rule!J24,lvl_2[],2,FALSE),"Нет") -> Ци Мень | E24: =IFERROR(VLOOKUP(Rule!K24,lvl_3[],2,FALSE),"Нет") -> Анализ Дворца | F24: =IFERROR(INDEX(lvl_4[],MATCH(L24,lvl_4[ID],0),MATCH(TEXT(K24,"##0"),lvl_4[#Headers],0)),"Нет") -> Комбинации | G24: =IFERROR(INDEX(lvl_5[],MATCH(M24,lvl_5[ID],0),MATCH(_xlfn.CONCAT(TEXT(K24,"##0"),"_",TEXT(L24,"##0")),lvl_5[#Headers],0)),"Нет") -> Нет | H24: =IFERROR(INDEX(lvl_6[],MATCH(N24,lvl_6[ID],0),MATCH(_xlfn.CONCAT(K24,"_",L24,"_",M24),lvl_6[#Headers],0)),"Нет") -> Нет | I24: 1 | J24: 2 | K24: 2 | L24: 2 | M24: 0 | N24: 0 | O24: =COUNTIF($P$2:P24,P24) -> 21 | P24: =_xlfn.CONCAT(I24, J24, K24, IF(LEN(L24)=1,_xlfn.CONCAT(0,L24),L24), IF(LEN(M24)=1,_xlfn.CONCAT(0,M24),M24), IF(LEN(N24)=1,_xlfn.CONCAT(0,N24),N24)) -> 122020000 | Q24: =_xlfn.CONCAT(I24, J24, K24, IF(LEN(L24)=1,_xlfn.CONCAT(0,L24),L24), IF(LEN(M24)=1,_xlfn.CONCAT(0,M24),M24), IF(LEN(N24)=1,_xlfn.CONCAT(0,N24),N24), IF(LEN(O24)=1,_xlfn.CONCAT("000",O24),IF(LEN(O24)=2,_xlfn.CONCAT("00",O24),IF(LEN(O24)=3,_xlfn.CONCAT(0,O24),O24)))) -> 1220200000021 | R24: 9 Дунь. Земная структура (Ди Дунь – Di Dun) | S24: Можно легко получить одобрение планов. Можно вести мирные переговоры, подавать прошения, вступать в брак, обороняться | AY24: 乙 | BA24: 己 | BB24: 開 | BG24: 1 | BJ24: 1
A25: 1 | B25: =_xlfn.CONCAT(C25,". ", D25,". ", E25,". ", F25,". ", G25,". ", H25) -> Общий расчет. Ци Мень. Анализ Дворца. Комбинации. Нет. Нет | C25: =IFERROR(VLOOKUP(I25,lvl_1[],2,FALSE),"Нет") -> Общий расчет | D25: =IFERROR(VLOOKUP(Rule!J25,lvl_2[],2,FALSE),"Нет") -> Ци Мень | E25: =IFERROR(VLOOKUP(Rule!K25,lvl_3[],2,FALSE),"Нет") -> Анализ Дворца | F25: =IFERROR(INDEX(lvl_4[],MATCH(L25,lvl_4[ID],0),MATCH(TEXT(K25,"##0"),lvl_4[#Headers],0)),"Нет") -> Комбинации | G25: =IFERROR(INDEX(lvl_5[],MATCH(M25,lvl_5[ID],0),MATCH(_xlfn.CONCAT(TEXT(K25,"##0"),"_",TEXT(L25,"##0")),lvl_5[#Headers],0)),"Нет") -> Нет | H25: =IFERROR(INDEX(lvl_6[],MATCH(N25,lvl_6[ID],0),MATCH(_xlfn.CONCAT(K25,"_",L25,"_",M25),lvl_6[#Headers],0)),"Нет") -> Нет | I25: 1 | J25: 2 | K25: 2 | L25: 2 | M25: 0 | N25: 0 | O25: =COUNTIF($P$2:P25,P25) -> 22 | P25: =_xlfn.CONCAT(I25, J25, K25, IF(LEN(L25)=1,_xlfn.CONCAT(0,L25),L25), IF(LEN(M25)=1,_xlfn.CONCAT(0,M25),M25), IF(LEN(N25)=1,_xlfn.CONCAT(0,N25),N25)) -> 122020000 | Q25: =_xlfn.CONCAT(I25, J25, K25, IF(LEN(L25)=1,_xlfn.CONCAT(0,L25),L25), IF(LEN(M25)=1,_xlfn.CONCAT(0,M25),M25), IF(LEN(N25)=1,_xlfn.CONCAT(0,N25),N25), IF(LEN(O25)=1,_xlfn.CONCAT("000",O25),IF(LEN(O25)=2,_xlfn.CONCAT("00",O25),IF(LEN(O25)=3,_xlfn.CONCAT(0,O25),O25)))) -> 1220200000022 | R25: 9 Дунь. Струтура привидения Гуй Дунь | S25: Для тайных скрытых, ответных действий и передвижений. Благоприятно располагать войска в засаде, шпионить, следить, распространять слухи, заниматься пропагандой | AY25: 乙 | BB25: 杜 | BF25: 地 | BG25: 1 | BJ25: 1
A26: 1 | B26: =_xlfn.CONCAT(C26,". ", D26,". ", E26,". ", F26,". ", G26,". ", H26) -> Общий расчет. Ци Мень. Анализ Дворца. Комбинации. Нет. Нет | C26: =IFERROR(VLOOKUP(I26,lvl_1[],2,FALSE),"Нет") -> Общий расчет | D26: =IFERROR(VLOOKUP(Rule!J26,lvl_2[],2,FALSE),"Нет") -> Ци Мень | E26: =IFERROR(VLOOKUP(Rule!K26,lvl_3[],2,FALSE),"Нет") -> Анализ Дворца | F26: =IFERROR(INDEX(lvl_4[],MATCH(L26,lvl_4[ID],0),MATCH(TEXT(K26,"##0"),lvl_4[#Headers],0)),"Нет") -> Комбинации | G26: =IFERROR(INDEX(lvl_5[],MATCH(M26,lvl_5[ID],0),MATCH(_xlfn.CONCAT(TEXT(K26,"##0"),"_",TEXT(L26,"##0")),lvl_5[#Headers],0)),"Нет") -> Нет | H26: =IFERROR(INDEX(lvl_6[],MATCH(N26,lvl_6[ID],0),MATCH(_xlfn.CONCAT(K26,"_",L26,"_",M26),lvl_6[#Headers],0)),"Нет") -> Нет | I26: 1 | J26: 2 | K26: 2 | L26: 2 | M26: 0 | N26: 0 | O26: =COUNTIF($P$2:P26,P26) -> 23 | P26: =_xlfn.CONCAT(I26, J26, K26, IF(LEN(L26)=1,_xlfn.CONCAT(0,L26),L26), IF(LEN(M26)=1,_xlfn.CONCAT(0,M26),M26), IF(LEN(N26)=1,_xlfn.CONCAT(0,N26),N26)) -> 122020000 | Q26: =_xlfn.CONCAT(I26, J26, K26, IF(LEN(L26)=1,_xlfn.CONCAT(0,L26),L26), IF(LEN(M26)=1,_xlfn.CONCAT(0,M26),M26), IF(LEN(N26)=1,_xlfn.CONCAT(0,N26),N26), IF(LEN(O26)=1,_xlfn.CONCAT("000",O26),IF(LEN(O26)=2,_xlfn.CONCAT("00",O26),IF(LEN(O26)=3,_xlfn.CONCAT(0,O26),O26)))) -> 1220200000023 | R26: 9 Дунь. Структура тигра Ху Дунь | S26: Хорошо для контроля бунтов и мятежей. Можно запугивать противника, чтобы он сдался. Располагать засады. Хорошо для творчества, созидания, можно получить деньги для бизнеса. Возможность счастливых событий | AW26: 8 | AY26: 乙 | BA26: 辛 | BB26: 生 | BG26: 0.5 | BJ26: 1
A27: 1 | B27: =_xlfn.CONCAT(C27,". ", D27,". ", E27,". ", F27,". ", G27,". ", H27) -> Общий расчет. Ци Мень. Анализ Дворца. Комбинации. Нет. Нет | C27: =IFERROR(VLOOKUP(I27,lvl_1[],2,FALSE),"Нет") -> Общий расчет | D27: =IFERROR(VLOOKUP(Rule!J27,lvl_2[],2,FALSE),"Нет") -> Ци Мень | E27: =IFERROR(VLOOKUP(Rule!K27,lvl_3[],2,FALSE),"Нет") -> Анализ Дворца | F27: =IFERROR(INDEX(lvl_4[],MATCH(L27,lvl_4[ID],0),MATCH(TEXT(K27,"##0"),lvl_4[#Headers],0)),"Нет") -> Комбинации | G27: =IFERROR(INDEX(lvl_5[],MATCH(M27,lvl_5[ID],0),MATCH(_xlfn.CONCAT(TEXT(K27,"##0"),"_",TEXT(L27,"##0")),lvl_5[#Headers],0)),"Нет") -> Нет | H27: =IFERROR(INDEX(lvl_6[],MATCH(N27,lvl_6[ID],0),MATCH(_xlfn.CONCAT(K27,"_",L27,"_",M27),lvl_6[#Headers],0)),"Нет") -> Нет | I27: 1 | J27: 2 | K27: 2 | L27: 2 | M27: 0 | N27: 0 | O27: =COUNTIF($P$2:P27,P27) -> 24 | P27: =_xlfn.CONCAT(I27, J27, K27, IF(LEN(L27)=1,_xlfn.CONCAT(0,L27),L27), IF(LEN(M27)=1,_xlfn.CONCAT(0,M27),M27), IF(LEN(N27)=1,_xlfn.CONCAT(0,N27),N27)) -> 122020000 | Q27: =_xlfn.CONCAT(I27, J27, K27, IF(LEN(L27)=1,_xlfn.CONCAT(0,L27),L27), IF(LEN(M27)=1,_xlfn.CONCAT(0,M27),M27), IF(LEN(N27)=1,_xlfn.CONCAT(0,N27),N27), IF(LEN(O27)=1,_xlfn.CONCAT("000",O27),IF(LEN(O27)=2,_xlfn.CONCAT("00",O27),IF(LEN(O27)=3,_xlfn.CONCAT(0,O27),O27)))) -> 1220200000024 | R27: 9 Дунь. Структура ветра. Фэн Дунь – Feng Dun | S27: Хорошо для распространения информации, рекламы, презентаций, продвижения, собраний, путешествий и подготовки к экзаменам | AW27: 4 | AY27: 乙 | BB27: 生 | BG27: 1 | BJ27: 1
A28: 1 | B28: =_xlfn.CONCAT(C28,". ", D28,". ", E28,". ", F28,". ", G28,". ", H28) -> Общий расчет. Ци Мень. Анализ Дворца. Комбинации. Нет. Нет | C28: =IFERROR(VLOOKUP(I28,lvl_1[],2,FALSE),"Нет") -> Общий расчет | D28: =IFERROR(VLOOKUP(Rule!J28,lvl_2[],2,FALSE),"Нет") -> Ци Мень | E28: =IFERROR(VLOOKUP(Rule!K28,lvl_3[],2,FALSE),"Нет") -> Анализ Дворца | F28: =IFERROR(INDEX(lvl_4[],MATCH(L28,lvl_4[ID],0),MATCH(TEXT(K28,"##0"),lvl_4[#Headers],0)),"Нет") -> Комбинации | G28: =IFERROR(INDEX(lvl_5[],MATCH(M28,lvl_5[ID],0),MATCH(_xlfn.CONCAT(TEXT(K28,"##0"),"_",TEXT(L28,"##0")),lvl_5[#Headers],0)),"Нет") -> Нет | H28: =IFERROR(INDEX(lvl_6[],MATCH(N28,lvl_6[ID],0),MATCH(_xlfn.CONCAT(K28,"_",L28,"_",M28),lvl_6[#Headers],0)),"Нет") -> Нет | I28: 1 | J28: 2 | K28: 2 | L28: 2 | M28: 0 | N28: 0 | O28: =COUNTIF($P$2:P28,P28) -> 25 | P28: =_xlfn.CONCAT(I28, J28, K28, IF(LEN(L28)=1,_xlfn.CONCAT(0,L28),L28), IF(LEN(M28)=1,_xlfn.CONCAT(0,M28),M28), IF(LEN(N28)=1,_xlfn.CONCAT(0,N28),N28)) -> 122020000 | Q28: =_xlfn.CONCAT(I28, J28, K28, IF(LEN(L28)=1,_xlfn.CONCAT(0,L28),L28), IF(LEN(M28)=1,_xlfn.CONCAT(0,M28),M28), IF(LEN(N28)=1,_xlfn.CONCAT(0,N28),N28), IF(LEN(O28)=1,_xlfn.CONCAT("000",O28),IF(LEN(O28)=2,_xlfn.CONCAT("00",O28),IF(LEN(O28)=3,_xlfn.CONCAT(0,O28),O28)))) -> 1220200000025 | R28: 9 Дунь. Структура ветра. Фэн Дунь – Feng Dun | S28: Хорошо для распространения информации, рекламы, презентаций, продвижения, собраний, путешествий и подготовки к экзаменам | AW28: 4 | AY28: 乙 | BB28: 開 | BG28: 1 | BJ28: 1
A29: 1 | B29: =_xlfn.CONCAT(C29,". ", D29,". ", E29,". ", F29,". ", G29,". ", H29) -> Общий расчет. Ци Мень. Анализ Дворца. Комбинации. Нет. Нет | C29: =IFERROR(VLOOKUP(I29,lvl_1[],2,FALSE),"Нет") -> Общий расчет | D29: =IFERROR(VLOOKUP(Rule!J29,lvl_2[],2,FALSE),"Нет") -> Ци Мень | E29: =IFERROR(VLOOKUP(Rule!K29,lvl_3[],2,FALSE),"Нет") -> Анализ Дворца | F29: =IFERROR(INDEX(lvl_4[],MATCH(L29,lvl_4[ID],0),MATCH(TEXT(K29,"##0"),lvl_4[#Headers],0)),"Нет") -> Комбинации | G29: =IFERROR(INDEX(lvl_5[],MATCH(M29,lvl_5[ID],0),MATCH(_xlfn.CONCAT(TEXT(K29,"##0"),"_",TEXT(L29,"##0")),lvl_5[#Headers],0)),"Нет") -> Нет | H29: =IFERROR(INDEX(lvl_6[],MATCH(N29,lvl_6[ID],0),MATCH(_xlfn.CONCAT(K29,"_",L29,"_",M29),lvl_6[#Headers],0)),"Нет") -> Нет | I29: 1 | J29: 2 | K29: 2 | L29: 2 | M29: 0 | N29: 0 | O29: =COUNTIF($P$2:P29,P29) -> 26 | P29: =_xlfn.CONCAT(I29, J29, K29, IF(LEN(L29)=1,_xlfn.CONCAT(0,L29),L29), IF(LEN(M29)=1,_xlfn.CONCAT(0,M29),M29), IF(LEN(N29)=1,_xlfn.CONCAT(0,N29),N29)) -> 122020000 | Q29: =_xlfn.CONCAT(I29, J29, K29, IF(LEN(L29)=1,_xlfn.CONCAT(0,L29),L29), IF(LEN(M29)=1,_xlfn.CONCAT(0,M29),M29), IF(LEN(N29)=1,_xlfn.CONCAT(0,N29),N29), IF(LEN(O29)=1,_xlfn.CONCAT("000",O29),IF(LEN(O29)=2,_xlfn.CONCAT("00",O29),IF(LEN(O29)=3,_xlfn.CONCAT(0,O29),O29)))) -> 1220200000026 | R29: 9 Дунь. Структура ветра. Фэн Дунь – Feng Dun | S29: Хорошо для распространения информации, рекламы, презентаций, продвижения, собраний, путешествий и подготовки к экзаменам | AW29: 4 | AY29: 乙 | BB29: 休 | BG29: 1 | BJ29: 1
A30: 1 | B30: =_xlfn.CONCAT(C30,". ", D30,". ", E30,". ", F30,". ", G30,". ", H30) -> Общий расчет. Ци Мень. Анализ Дворца. Комбинации. Нет. Нет | C30: =IFERROR(VLOOKUP(I30,lvl_1[],2,FALSE),"Нет") -> Общий расчет | D30: =IFERROR(VLOOKUP(Rule!J30,lvl_2[],2,FALSE),"Нет") -> Ци Мень | E30: =IFERROR(VLOOKUP(Rule!K30,lvl_3[],2,FALSE),"Нет") -> Анализ Дворца | F30: =IFERROR(INDEX(lvl_4[],MATCH(L30,lvl_4[ID],0),MATCH(TEXT(K30,"##0"),lvl_4[#Headers],0)),"Нет") -> Комбинации | G30: =IFERROR(INDEX(lvl_5[],MATCH(M30,lvl_5[ID],0),MATCH(_xlfn.CONCAT(TEXT(K30,"##0"),"_",TEXT(L30,"##0")),lvl_5[#Headers],0)),"Нет") -> Нет | H30: =IFERROR(INDEX(lvl_6[],MATCH(N30,lvl_6[ID],0),MATCH(_xlfn.CONCAT(K30,"_",L30,"_",M30),lvl_6[#Headers],0)),"Нет") -> Нет | I30: 1 | J30: 2 | K30: 2 | L30: 2 | M30: 0 | N30: 0 | O30: =COUNTIF($P$2:P30,P30) -> 27 | P30: =_xlfn.CONCAT(I30, J30, K30, IF(LEN(L30)=1,_xlfn.CONCAT(0,L30),L30), IF(LEN(M30)=1,_xlfn.CONCAT(0,M30),M30), IF(LEN(N30)=1,_xlfn.CONCAT(0,N30),N30)) -> 122020000 | Q30: =_xlfn.CONCAT(I30, J30, K30, IF(LEN(L30)=1,_xlfn.CONCAT(0,L30),L30), IF(LEN(M30)=1,_xlfn.CONCAT(0,M30),M30), IF(LEN(N30)=1,_xlfn.CONCAT(0,N30),N30), IF(LEN(O30)=1,_xlfn.CONCAT("000",O30),IF(LEN(O30)=2,_xlfn.CONCAT("00",O30),IF(LEN(O30)=3,_xlfn.CONCAT(0,O30),O30)))) -> 1220200000027 | R30: 9 Дунь. Драконий Дунь. Лун Дунь – Long Dun | S30: Хорошо молиться о дожде, плавать по морю, вести бой на воде, копать колодцы, строить мосты, решать водные вопросы, улучшать денежную удачу | AW30: 1 | AY30: 乙 | BB30: 生 | BG30: 1 | BJ30: 1
A31: 1 | B31: =_xlfn.CONCAT(C31,". ", D31,". ", E31,". ", F31,". ", G31,". ", H31) -> Общий расчет. Ци Мень. Анализ Дворца. Комбинации. Нет. Нет | C31: =IFERROR(VLOOKUP(I31,lvl_1[],2,FALSE),"Нет") -> Общий расчет | D31: =IFERROR(VLOOKUP(Rule!J31,lvl_2[],2,FALSE),"Нет") -> Ци Мень | E31: =IFERROR(VLOOKUP(Rule!K31,lvl_3[],2,FALSE),"Нет") -> Анализ Дворца | F31: =IFERROR(INDEX(lvl_4[],MATCH(L31,lvl_4[ID],0),MATCH(TEXT(K31,"##0"),lvl_4[#Headers],0)),"Нет") -> Комбинации | G31: =IFERROR(INDEX(lvl_5[],MATCH(M31,lvl_5[ID],0),MATCH(_xlfn.CONCAT(TEXT(K31,"##0"),"_",TEXT(L31,"##0")),lvl_5[#Headers],0)),"Нет") -> Нет | H31: =IFERROR(INDEX(lvl_6[],MATCH(N31,lvl_6[ID],0),MATCH(_xlfn.CONCAT(K31,"_",L31,"_",M31),lvl_6[#Headers],0)),"Нет") -> Нет | I31: 1 | J31: 2 | K31: 2 | L31: 2 | M31: 0 | N31: 0 | O31: =COUNTIF($P$2:P31,P31) -> 28 | P31: =_xlfn.CONCAT(I31, J31, K31, IF(LEN(L31)=1,_xlfn.CONCAT(0,L31),L31), IF(LEN(M31)=1,_xlfn.CONCAT(0,M31),M31), IF(LEN(N31)=1,_xlfn.CONCAT(0,N31),N31)) -> 122020000 | Q31: =_xlfn.CONCAT(I31, J31, K31, IF(LEN(L31)=1,_xlfn.CONCAT(0,L31),L31), IF(LEN(M31)=1,_xlfn.CONCAT(0,M31),M31), IF(LEN(N31)=1,_xlfn.CONCAT(0,N31),N31), IF(LEN(O31)=1,_xlfn.CONCAT("000",O31),IF(LEN(O31)=2,_xlfn.CONCAT("00",O31),IF(LEN(O31)=3,_xlfn.CONCAT(0,O31),O31)))) -> 1220200000028 | R31: 9 Дунь. Драконий Дунь. Лун Дунь – Long Dun | S31: Хорошо молиться о дожде, плавать по морю, вести бой на воде, копать колодцы, строить мосты, решать водные вопросы, улучшать денежную удачу | AW31: 1 | AY31: 乙 | BB31: 開 | BG31: 1 | BJ31: 1
A32: 1 | B32: =_xlfn.CONCAT(C32,". ", D32,". ", E32,". ", F32,". ", G32,". ", H32) -> Общий расчет. Ци Мень. Анализ Дворца. Комбинации. Нет. Нет | C32: =IFERROR(VLOOKUP(I32,lvl_1[],2,FALSE),"Нет") -> Общий расчет | D32: =IFERROR(VLOOKUP(Rule!J32,lvl_2[],2,FALSE),"Нет") -> Ци Мень | E32: =IFERROR(VLOOKUP(Rule!K32,lvl_3[],2,FALSE),"Нет") -> Анализ Дворца | F32: =IFERROR(INDEX(lvl_4[],MATCH(L32,lvl_4[ID],0),MATCH(TEXT(K32,"##0"),lvl_4[#Headers],0)),"Нет") -> Комбинации | G32: =IFERROR(INDEX(lvl_5[],MATCH(M32,lvl_5[ID],0),MATCH(_xlfn.CONCAT(TEXT(K32,"##0"),"_",TEXT(L32,"##0")),lvl_5[#Headers],0)),"Нет") -> Нет | H32: =IFERROR(INDEX(lvl_6[],MATCH(N32,lvl_6[ID],0),MATCH(_xlfn.CONCAT(K32,"_",L32,"_",M32),lvl_6[#Headers],0)),"Нет") -> Нет | I32: 1 | J32: 2 | K32: 2 | L32: 2 | M32: 0 | N32: 0 | O32: =COUNTIF($P$2:P32,P32) -> 29 | P32: =_xlfn.CONCAT(I32, J32, K32, IF(LEN(L32)=1,_xlfn.CONCAT(0,L32),L32), IF(LEN(M32)=1,_xlfn.CONCAT(0,M32),M32), IF(LEN(N32)=1,_xlfn.CONCAT(0,N32),N32)) -> 122020000 | Q32: =_xlfn.CONCAT(I32, J32, K32, IF(LEN(L32)=1,_xlfn.CONCAT(0,L32),L32), IF(LEN(M32)=1,_xlfn.CONCAT(0,M32),M32), IF(LEN(N32)=1,_xlfn.CONCAT(0,N32),N32), IF(LEN(O32)=1,_xlfn.CONCAT("000",O32),IF(LEN(O32)=2,_xlfn.CONCAT("00",O32),IF(LEN(O32)=3,_xlfn.CONCAT(0,O32),O32)))) -> 1220200000029 | R32: 9 Дунь. Драконий Дунь. Лун Дунь – Long Dun | S32: Хорошо молиться о дожде, плавать по морю, вести бой на воде, копать колодцы, строить мосты, решать водные вопросы, улучшать денежную удачу | AW32: 1 | AY32: 乙 | BB32: 休 | BG32: 1 | BJ32: 1
A33: 1 | B33: =_xlfn.CONCAT(C33,". ", D33,". ", E33,". ", F33,". ", G33,". ", H33) -> Общий расчет. Ци Мень. Анализ Дворца. Комбинации. Нет. Нет | C33: =IFERROR(VLOOKUP(I33,lvl_1[],2,FALSE),"Нет") -> Общий расчет | D33: =IFERROR(VLOOKUP(Rule!J33,lvl_2[],2,FALSE),"Нет") -> Ци Мень | E33: =IFERROR(VLOOKUP(Rule!K33,lvl_3[],2,FALSE),"Нет") -> Анализ Дворца | F33: =IFERROR(INDEX(lvl_4[],MATCH(L33,lvl_4[ID],0),MATCH(TEXT(K33,"##0"),lvl_4[#Headers],0)),"Нет") -> Комбинации | G33: =IFERROR(INDEX(lvl_5[],MATCH(M33,lvl_5[ID],0),MATCH(_xlfn.CONCAT(TEXT(K33,"##0"),"_",TEXT(L33,"##0")),lvl_5[#Headers],0)),"Нет") -> Нет | H33: =IFERROR(INDEX(lvl_6[],MATCH(N33,lvl_6[ID],0),MATCH(_xlfn.CONCAT(K33,"_",L33,"_",M33),lvl_6[#Headers],0)),"Нет") -> Нет | I33: 1 | J33: 2 | K33: 2 | L33: 2 | M33: 0 | N33: 0 | O33: =COUNTIF($P$2:P33,P33) -> 30 | P33: =_xlfn.CONCAT(I33, J33, K33, IF(LEN(L33)=1,_xlfn.CONCAT(0,L33),L33), IF(LEN(M33)=1,_xlfn.CONCAT(0,M33),M33), IF(LEN(N33)=1,_xlfn.CONCAT(0,N33),N33)) -> 122020000 | Q33: =_xlfn.CONCAT(I33, J33, K33, IF(LEN(L33)=1,_xlfn.CONCAT(0,L33),L33), IF(LEN(M33)=1,_xlfn.CONCAT(0,M33),M33), IF(LEN(N33)=1,_xlfn.CONCAT(0,N33),N33), IF(LEN(O33)=1,_xlfn.CONCAT("000",O33),IF(LEN(O33)=2,_xlfn.CONCAT("00",O33),IF(LEN(O33)=3,_xlfn.CONCAT(0,O33),O33)))) -> 1220200000030 | R33: 9 Дунь. Проход ветра (Фэн Дунь) | S33: Благоприятно для распространения информации (рекламы, презентации товара). | AY33: 乙 | BA33: 辛 | BB33: 生 | BG33: 1 | BJ33: 1
A34: 1 | B34: =_xlfn.CONCAT(C34,". ", D34,". ", E34,". ", F34,". ", G34,". ", H34) -> Общий расчет. Ци Мень. Анализ Дворца. Комбинации. Нет. Нет | C34: =IFERROR(VLOOKUP(I34,lvl_1[],2,FALSE),"Нет") -> Общий расчет | D34: =IFERROR(VLOOKUP(Rule!J34,lvl_2[],2,FALSE),"Нет") -> Ци Мень | E34: =IFERROR(VLOOKUP(Rule!K34,lvl_3[],2,FALSE),"Нет") -> Анализ Дворца | F34: =IFERROR(INDEX(lvl_4[],MATCH(L34,lvl_4[ID],0),MATCH(TEXT(K34,"##0"),lvl_4[#Headers],0)),"Нет") -> Комбинации | G34: =IFERROR(INDEX(lvl_5[],MATCH(M34,lvl_5[ID],0),MATCH(_xlfn.CONCAT(TEXT(K34,"##0"),"_",TEXT(L34,"##0")),lvl_5[#Headers],0)),"Нет") -> Нет | H34: =IFERROR(INDEX(lvl_6[],MATCH(N34,lvl_6[ID],0),MATCH(_xlfn.CONCAT(K34,"_",L34,"_",M34),lvl_6[#Headers],0)),"Нет") -> Нет | I34: 1 | J34: 2 | K34: 2 | L34: 2 | M34: 0 | N34: 0 | O34: =COUNTIF($P$2:P34,P34) -> 31 | P34: =_xlfn.CONCAT(I34, J34, K34, IF(LEN(L34)=1,_xlfn.CONCAT(0,L34),L34), IF(LEN(M34)=1,_xlfn.CONCAT(0,M34),M34), IF(LEN(N34)=1,_xlfn.CONCAT(0,N34),N34)) -> 122020000 | Q34: =_xlfn.CONCAT(I34, J34, K34, IF(LEN(L34)=1,_xlfn.CONCAT(0,L34),L34), IF(LEN(M34)=1,_xlfn.CONCAT(0,M34),M34), IF(LEN(N34)=1,_xlfn.CONCAT(0,N34),N34), IF(LEN(O34)=1,_xlfn.CONCAT("000",O34),IF(LEN(O34)=2,_xlfn.CONCAT("00",O34),IF(LEN(O34)=3,_xlfn.CONCAT(0,O34),O34)))) -> 1220200000031 | R34: 9 Дунь. Проход ветра (Фэн Дунь) | S34: Благоприятно для распространения информации (рекламы, презентации товара). | AY34: 乙 | BA34: 辛 | BB34: 開 | BG34: 1 | BJ34: 1
A35: 1 | B35: =_xlfn.CONCAT(C35,". ", D35,". ", E35,". ", F35,". ", G35,". ", H35) -> Общий расчет. Ци Мень. Анализ Дворца. Комбинации. Нет. Нет | C35: =IFERROR(VLOOKUP(I35,lvl_1[],2,FALSE),"Нет") -> Общий расчет | D35: =IFERROR(VLOOKUP(Rule!J35,lvl_2[],2,FALSE),"Нет") -> Ци Мень | E35: =IFERROR(VLOOKUP(Rule!K35,lvl_3[],2,FALSE),"Нет") -> Анализ Дворца | F35: =IFERROR(INDEX(lvl_4[],MATCH(L35,lvl_4[ID],0),MATCH(TEXT(K35,"##0"),lvl_4[#Headers],0)),"Нет") -> Комбинации | G35: =IFERROR(INDEX(lvl_5[],MATCH(M35,lvl_5[ID],0),MATCH(_xlfn.CONCAT(TEXT(K35,"##0"),"_",TEXT(L35,"##0")),lvl_5[#Headers],0)),"Нет") -> Нет | H35: =IFERROR(INDEX(lvl_6[],MATCH(N35,lvl_6[ID],0),MATCH(_xlfn.CONCAT(K35,"_",L35,"_",M35),lvl_6[#Headers],0)),"Нет") -> Нет | I35: 1 | J35: 2 | K35: 2 | L35: 2 | M35: 0 | N35: 0 | O35: =COUNTIF($P$2:P35,P35) -> 32 | P35: =_xlfn.CONCAT(I35, J35, K35, IF(LEN(L35)=1,_xlfn.CONCAT(0,L35),L35), IF(LEN(M35)=1,_xlfn.CONCAT(0,M35),M35), IF(LEN(N35)=1,_xlfn.CONCAT(0,N35),N35)) -> 122020000 | Q35: =_xlfn.CONCAT(I35, J35, K35, IF(LEN(L35)=1,_xlfn.CONCAT(0,L35),L35), IF(LEN(M35)=1,_xlfn.CONCAT(0,M35),M35), IF(LEN(N35)=1,_xlfn.CONCAT(0,N35),N35), IF(LEN(O35)=1,_xlfn.CONCAT("000",O35),IF(LEN(O35)=2,_xlfn.CONCAT("00",O35),IF(LEN(O35)=3,_xlfn.CONCAT(0,O35),O35)))) -> 1220200000032 | R35: 9 Дунь. Проход ветра (Фэн Дунь) | S35: Благоприятно для распространения информации (рекламы, презентации товара). | AY35: 乙 | BA35: 辛 | BB35: 休 | BG35: 1 | BJ35: 1
A36: 1 | B36: =_xlfn.CONCAT(C36,". ", D36,". ", E36,". ", F36,". ", G36,". ", H36) -> Общий расчет. Ци Мень. Анализ Дворца. Комбинации. Нет. Нет | C36: =IFERROR(VLOOKUP(I36,lvl_1[],2,FALSE),"Нет") -> Общий расчет | D36: =IFERROR(VLOOKUP(Rule!J36,lvl_2[],2,FALSE),"Нет") -> Ци Мень | E36: =IFERROR(VLOOKUP(Rule!K36,lvl_3[],2,FALSE),"Нет") -> Анализ Дворца | F36: =IFERROR(INDEX(lvl_4[],MATCH(L36,lvl_4[ID],0),MATCH(TEXT(K36,"##0"),lvl_4[#Headers],0)),"Нет") -> Комбинации | G36: =IFERROR(INDEX(lvl_5[],MATCH(M36,lvl_5[ID],0),MATCH(_xlfn.CONCAT(TEXT(K36,"##0"),"_",TEXT(L36,"##0")),lvl_5[#Headers],0)),"Нет") -> Нет | H36: =IFERROR(INDEX(lvl_6[],MATCH(N36,lvl_6[ID],0),MATCH(_xlfn.CONCAT(K36,"_",L36,"_",M36),lvl_6[#Headers],0)),"Нет") -> Нет | I36: 1 | J36: 2 | K36: 2 | L36: 2 | M36: 0 | N36: 0 | O36: =COUNTIF($P$2:P36,P36) -> 33 | P36: =_xlfn.CONCAT(I36, J36, K36, IF(LEN(L36)=1,_xlfn.CONCAT(0,L36),L36), IF(LEN(M36)=1,_xlfn.CONCAT(0,M36),M36), IF(LEN(N36)=1,_xlfn.CONCAT(0,N36),N36)) -> 122020000 | Q36: =_xlfn.CONCAT(I36, J36, K36, IF(LEN(L36)=1,_xlfn.CONCAT(0,L36),L36), IF(LEN(M36)=1,_xlfn.CONCAT(0,M36),M36), IF(LEN(N36)=1,_xlfn.CONCAT(0,N36),N36), IF(LEN(O36)=1,_xlfn.CONCAT("000",O36),IF(LEN(O36)=2,_xlfn.CONCAT("00",O36),IF(LEN(O36)=3,_xlfn.CONCAT(0,O36),O36)))) -> 1220200000033 | R36: Три притворства (Три лжи). Настоящая ложь (Правильная ложь) | S36: Чтобы преуспеть нужно создать себе правильный образ. Можно получить помощь, если притворитесь слабым, мирным, дружелюбным. Хорошо для бизнес-сделок, религиозных церемоний, благотворительности, совершения добрых дел, награждения других | AY36: 乙 | BB36: 開 | BF36: 陰 | BG36: 1 | BJ36: 1
A37: 1 | B37: =_xlfn.CONCAT(C37,". ", D37,". ", E37,". ", F37,". ", G37,". ", H37) -> Общий расчет. Ци Мень. Анализ Дворца. Комбинации. Нет. Нет | C37: =IFERROR(VLOOKUP(I37,lvl_1[],2,FALSE),"Нет") -> Общий расчет | D37: =IFERROR(VLOOKUP(Rule!J37,lvl_2[],2,FALSE),"Нет") -> Ци Мень | E37: =IFERROR(VLOOKUP(Rule!K37,lvl_3[],2,FALSE),"Нет") -> Анализ Дворца | F37: =IFERROR(INDEX(lvl_4[],MATCH(L37,lvl_4[ID],0),MATCH(TEXT(K37,"##0"),lvl_4[#Headers],0)),"Нет") -> Комбинации | G37: =IFERROR(INDEX(lvl_5[],MATCH(M37,lvl_5[ID],0),MATCH(_xlfn.CONCAT(TEXT(K37,"##0"),"_",TEXT(L37,"##0")),lvl_5[#Headers],0)),"Нет") -> Нет | H37: =IFERROR(INDEX(lvl_6[],MATCH(N37,lvl_6[ID],0),MATCH(_xlfn.CONCAT(K37,"_",L37,"_",M37),lvl_6[#Headers],0)),"Нет") -> Нет | I37: 1 | J37: 2 | K37: 2 | L37: 2 | M37: 0 | N37: 0 | O37: =COUNTIF($P$2:P37,P37) -> 34 | P37: =_xlfn.CONCAT(I37, J37, K37, IF(LEN(L37)=1,_xlfn.CONCAT(0,L37),L37), IF(LEN(M37)=1,_xlfn.CONCAT(0,M37),M37), IF(LEN(N37)=1,_xlfn.CONCAT(0,N37),N37)) -> 122020000 | Q37: =_xlfn.CONCAT(I37, J37, K37, IF(LEN(L37)=1,_xlfn.CONCAT(0,L37),L37), IF(LEN(M37)=1,_xlfn.CONCAT(0,M37),M37), IF(LEN(N37)=1,_xlfn.CONCAT(0,N37),N37), IF(LEN(O37)=1,_xlfn.CONCAT("000",O37),IF(LEN(O37)=2,_xlfn.CONCAT("00",O37),IF(LEN(O37)=3,_xlfn.CONCAT(0,O37),O37)))) -> 1220200000034 | R37: Три притворства (Три лжи). Настоящая ложь (Правильная ложь) | S37: Чтобы преуспеть нужно создать себе правильный образ. Можно получить помощь, если притворитесь слабым, мирным, дружелюбным. Хорошо для бизнес-сделок, религиозных церемоний, благотворительности, совершения добрых дел, награждения других | AY37: 乙 | BB37: 休 | BF37: 陰 | BG37: 1 | BJ37: 1
A38: 1 | B38: =_xlfn.CONCAT(C38,". ", D38,". ", E38,". ", F38,". ", G38,". ", H38) -> Общий расчет. Ци Мень. Анализ Дворца. Комбинации. Нет. Нет | C38: =IFERROR(VLOOKUP(I38,lvl_1[],2,FALSE),"Нет") -> Общий расчет | D38: =IFERROR(VLOOKUP(Rule!J38,lvl_2[],2,FALSE),"Нет") -> Ци Мень | E38: =IFERROR(VLOOKUP(Rule!K38,lvl_3[],2,FALSE),"Нет") -> Анализ Дворца | F38: =IFERROR(INDEX(lvl_4[],MATCH(L38,lvl_4[ID],0),MATCH(TEXT(K38,"##0"),lvl_4[#Headers],0)),"Нет") -> Комбинации | G38: =IFERROR(INDEX(lvl_5[],MATCH(M38,lvl_5[ID],0),MATCH(_xlfn.CONCAT(TEXT(K38,"##0"),"_",TEXT(L38,"##0")),lvl_5[#Headers],0)),"Нет") -> Нет | H38: =IFERROR(INDEX(lvl_6[],MATCH(N38,lvl_6[ID],0),MATCH(_xlfn.CONCAT(K38,"_",L38,"_",M38),lvl_6[#Headers],0)),"Нет") -> Нет | I38: 1 | J38: 2 | K38: 2 | L38: 2 | M38: 0 | N38: 0 | O38: =COUNTIF($P$2:P38,P38) -> 35 | P38: =_xlfn.CONCAT(I38, J38, K38, IF(LEN(L38)=1,_xlfn.CONCAT(0,L38),L38), IF(LEN(M38)=1,_xlfn.CONCAT(0,M38),M38), IF(LEN(N38)=1,_xlfn.CONCAT(0,N38),N38)) -> 122020000 | Q38: =_xlfn.CONCAT(I38, J38, K38, IF(LEN(L38)=1,_xlfn.CONCAT(0,L38),L38), IF(LEN(M38)=1,_xlfn.CONCAT(0,M38),M38), IF(LEN(N38)=1,_xlfn.CONCAT(0,N38),N38), IF(LEN(O38)=1,_xlfn.CONCAT("000",O38),IF(LEN(O38)=2,_xlfn.CONCAT("00",O38),IF(LEN(O38)=3,_xlfn.CONCAT(0,O38),O38)))) -> 1220200000035 | R38: Три притворства (Три лжи). Настоящая ложь (Правильная ложь) | S38: Чтобы преуспеть нужно создать себе правильный образ. Можно получить помощь, если притворитесь слабым, мирным, дружелюбным. Хорошо для бизнес-сделок, религиозных церемоний, благотворительности, совершения добрых дел, награждения других | AY38: 乙 | BB38: 生 | BF38: 陰 | BG38: 1 | BJ38: 1
A39: 1 | B39: =_xlfn.CONCAT(C39,". ", D39,". ", E39,". ", F39,". ", G39,". ", H39) -> Общий расчет. Ци Мень. Анализ Дворца. Комбинации. Нет. Нет | C39: =IFERROR(VLOOKUP(I39,lvl_1[],2,FALSE),"Нет") -> Общий расчет | D39: =IFERROR(VLOOKUP(Rule!J39,lvl_2[],2,FALSE),"Нет") -> Ци Мень | E39: =IFERROR(VLOOKUP(Rule!K39,lvl_3[],2,FALSE),"Нет") -> Анализ Дворца | F39: =IFERROR(INDEX(lvl_4[],MATCH(L39,lvl_4[ID],0),MATCH(TEXT(K39,"##0"),lvl_4[#Headers],0)),"Нет") -> Комбинации | G39: =IFERROR(INDEX(lvl_5[],MATCH(M39,lvl_5[ID],0),MATCH(_xlfn.CONCAT(TEXT(K39,"##0"),"_",TEXT(L39,"##0")),lvl_5[#Headers],0)),"Нет") -> Нет | H39: =IFERROR(INDEX(lvl_6[],MATCH(N39,lvl_6[ID],0),MATCH(_xlfn.CONCAT(K39,"_",L39,"_",M39),lvl_6[#Headers],0)),"Нет") -> Нет | I39: 1 | J39: 2 | K39: 2 | L39: 2 | M39: 0 | N39: 0 | O39: =COUNTIF($P$2:P39,P39) -> 36 | P39: =_xlfn.CONCAT(I39, J39, K39, IF(LEN(L39)=1,_xlfn.CONCAT(0,L39),L39), IF(LEN(M39)=1,_xlfn.CONCAT(0,M39),M39), IF(LEN(N39)=1,_xlfn.CONCAT(0,N39),N39)) -> 122020000 | Q39: =_xlfn.CONCAT(I39, J39, K39, IF(LEN(L39)=1,_xlfn.CONCAT(0,L39),L39), IF(LEN(M39)=1,_xlfn.CONCAT(0,M39),M39), IF(LEN(N39)=1,_xlfn.CONCAT(0,N39),N39), IF(LEN(O39)=1,_xlfn.CONCAT("000",O39),IF(LEN(O39)=2,_xlfn.CONCAT("00",O39),IF(LEN(O39)=3,_xlfn.CONCAT(0,O39),O39)))) -> 1220200000036 | R39: Три притворства (Три лжи). Настоящая ложь (Правильная ложь) | S39: Чтобы преуспеть нужно создать себе правильный образ. Можно получить помощь, если притворитесь слабым, мирным, дружелюбным. Хорошо для бизнес-сделок, религиозных церемоний, благотворительности, совершения добрых дел, награждения других | AY39: 丁 | BB39: 開 | BF39: 陰 | BG39: 1 | BJ39: 1
A40: 1 | B40: =_xlfn.CONCAT(C40,". ", D40,". ", E40,". ", F40,". ", G40,". ", H40) -> Общий расчет. Ци Мень. Анализ Дворца. Комбинации. Нет. Нет | C40: =IFERROR(VLOOKUP(I40,lvl_1[],2,FALSE),"Нет") -> Общий расчет | D40: =IFERROR(VLOOKUP(Rule!J40,lvl_2[],2,FALSE),"Нет") -> Ци Мень | E40: =IFERROR(VLOOKUP(Rule!K40,lvl_3[],2,FALSE),"Нет") -> Анализ Дворца | F40: =IFERROR(INDEX(lvl_4[],MATCH(L40,lvl_4[ID],0),MATCH(TEXT(K40,"##0"),lvl_4[#Headers],0)),"Нет") -> Комбинации | G40: =IFERROR(INDEX(lvl_5[],MATCH(M40,lvl_5[ID],0),MATCH(_xlfn.CONCAT(TEXT(K40,"##0"),"_",TEXT(L40,"##0")),lvl_5[#Headers],0)),"Нет") -> Нет | H40: =IFERROR(INDEX(lvl_6[],MATCH(N40,lvl_6[ID],0),MATCH(_xlfn.CONCAT(K40,"_",L40,"_",M40),lvl_6[#Headers],0)),"Нет") -> Нет | I40: 1 | J40: 2 | K40: 2 | L40: 2 | M40: 0 | N40: 0 | O40: =COUNTIF($P$2:P40,P40) -> 37 | P40: =_xlfn.CONCAT(I40, J40, K40, IF(LEN(L40)=1,_xlfn.CONCAT(0,L40),L40), IF(LEN(M40)=1,_xlfn.CONCAT(0,M40),M40), IF(LEN(N40)=1,_xlfn.CONCAT(0,N40),N40)) -> 122020000 | Q40: =_xlfn.CONCAT(I40, J40, K40, IF(LEN(L40)=1,_xlfn.CONCAT(0,L40),L40), IF(LEN(M40)=1,_xlfn.CONCAT(0,M40),M40), IF(LEN(N40)=1,_xlfn.CONCAT(0,N40),N40), IF(LEN(O40)=1,_xlfn.CONCAT("000",O40),IF(LEN(O40)=2,_xlfn.CONCAT("00",O40),IF(LEN(O40)=3,_xlfn.CONCAT(0,O40),O40)))) -> 1220200000037 | R40: Три притворства (Три лжи). Настоящая ложь (Правильная ложь) | S40: Чтобы преуспеть нужно создать себе правильный образ. Можно получить помощь, если притворитесь слабым, мирным, дружелюбным. Хорошо для бизнес-сделок, религиозных церемоний, благотворительности, совершения добрых дел, награждения других | AY40: 丁 | BB40: 休 | BF40: 陰 | BG40: 1 | BJ40: 1
A41: 1 | B41: =_xlfn.CONCAT(C41,". ", D41,". ", E41,". ", F41,". ", G41,". ", H41) -> Общий расчет. Ци Мень. Анализ Дворца. Комбинации. Нет. Нет | C41: =IFERROR(VLOOKUP(I41,lvl_1[],2,FALSE),"Нет") -> Общий расчет | D41: =IFERROR(VLOOKUP(Rule!J41,lvl_2[],2,FALSE),"Нет") -> Ци Мень | E41: =IFERROR(VLOOKUP(Rule!K41,lvl_3[],2,FALSE),"Нет") -> Анализ Дворца | F41: =IFERROR(INDEX(lvl_4[],MATCH(L41,lvl_4[ID],0),MATCH(TEXT(K41,"##0"),lvl_4[#Headers],0)),"Нет") -> Комбинации | G41: =IFERROR(INDEX(lvl_5[],MATCH(M41,lvl_5[ID],0),MATCH(_xlfn.CONCAT(TEXT(K41,"##0"),"_",TEXT(L41,"##0")),lvl_5[#Headers],0)),"Нет") -> Нет | H41: =IFERROR(INDEX(lvl_6[],MATCH(N41,lvl_6[ID],0),MATCH(_xlfn.CONCAT(K41,"_",L41,"_",M41),lvl_6[#Headers],0)),"Нет") -> Нет | I41: 1 | J41: 2 | K41: 2 | L41: 2 | M41: 0 | N41: 0 | O41: =COUNTIF($P$2:P41,P41) -> 38 | P41: =_xlfn.CONCAT(I41, J41, K41, IF(LEN(L41)=1,_xlfn.CONCAT(0,L41),L41), IF(LEN(M41)=1,_xlfn.CONCAT(0,M41),M41), IF(LEN(N41)=1,_xlfn.CONCAT(0,N41),N41)) -> 122020000 | Q41: =_xlfn.CONCAT(I41, J41, K41, IF(LEN(L41)=1,_xlfn.CONCAT(0,L41),L41), IF(LEN(M41)=1,_xlfn.CONCAT(0,M41),M41), IF(LEN(N41)=1,_xlfn.CONCAT(0,N41),N41), IF(LEN(O41)=1,_xlfn.CONCAT("000",O41),IF(LEN(O41)=2,_xlfn.CONCAT("00",O41),IF(LEN(O41)=3,_xlfn.CONCAT(0,O41),O41)))) -> 1220200000038 | R41: Три притворства (Три лжи). Настоящая ложь (Правильная ложь) | S41: Чтобы преуспеть нужно создать себе правильный образ. Можно получить помощь, если притворитесь слабым, мирным, дружелюбным. Хорошо для бизнес-сделок, религиозных церемоний, благотворительности, совершения добрых дел, награждения других | AY41: 丁 | BB41: 生 | BF41: 陰 | BG41: 1 | BJ41: 1
A42: 1 | B42: =_xlfn.CONCAT(C42,". ", D42,". ", E42,". ", F42,". ", G42,". ", H42) -> Общий расчет. Ци Мень. Анализ Дворца. Комбинации. Нет. Нет | C42: =IFERROR(VLOOKUP(I42,lvl_1[],2,FALSE),"Нет") -> Общий расчет | D42: =IFERROR(VLOOKUP(Rule!J42,lvl_2[],2,FALSE),"Нет") -> Ци Мень | E42: =IFERROR(VLOOKUP(Rule!K42,lvl_3[],2,FALSE),"Нет") -> Анализ Дворца | F42: =IFERROR(INDEX(lvl_4[],MATCH(L42,lvl_4[ID],0),MATCH(TEXT(K42,"##0"),lvl_4[#Headers],0)),"Нет") -> Комбинации | G42: =IFERROR(INDEX(lvl_5[],MATCH(M42,lvl_5[ID],0),MATCH(_xlfn.CONCAT(TEXT(K42,"##0"),"_",TEXT(L42,"##0")),lvl_5[#Headers],0)),"Нет") -> Нет | H42: =IFERROR(INDEX(lvl_6[],MATCH(N42,lvl_6[ID],0),MATCH(_xlfn.CONCAT(K42,"_",L42,"_",M42),lvl_6[#Headers],0)),"Нет") -> Нет | I42: 1 | J42: 2 | K42: 2 | L42: 2 | M42: 0 | N42: 0 | O42: =COUNTIF($P$2:P42,P42) -> 39 | P42: =_xlfn.CONCAT(I42, J42, K42, IF(LEN(L42)=1,_xlfn.CONCAT(0,L42),L42), IF(LEN(M42)=1,_xlfn.CONCAT(0,M42),M42), IF(LEN(N42)=1,_xlfn.CONCAT(0,N42),N42)) -> 122020000 | Q42: =_xlfn.CONCAT(I42, J42, K42, IF(LEN(L42)=1,_xlfn.CONCAT(0,L42),L42), IF(LEN(M42)=1,_xlfn.CONCAT(0,M42),M42), IF(LEN(N42)=1,_xlfn.CONCAT(0,N42),N42), IF(LEN(O42)=1,_xlfn.CONCAT("000",O42),IF(LEN(O42)=2,_xlfn.CONCAT("00",O42),IF(LEN(O42)=3,_xlfn.CONCAT(0,O42),O42)))) -> 1220200000039 | R42: Три притворства (Три лжи). Настоящая ложь (Правильная ложь) | S42: Чтобы преуспеть нужно создать себе правильный образ. Можно получить помощь, если притворитесь слабым, мирным, дружелюбным. Хорошо для бизнес-сделок, религиозных церемоний, благотворительности, совершения добрых дел, награждения других | AY42: 丙 | BB42: 開 | BF42: 陰 | BG42: 1 | BJ42: 1
A43: 1 | B43: =_xlfn.CONCAT(C43,". ", D43,". ", E43,". ", F43,". ", G43,". ", H43) -> Общий расчет. Ци Мень. Анализ Дворца. Комбинации. Нет. Нет | C43: =IFERROR(VLOOKUP(I43,lvl_1[],2,FALSE),"Нет") -> Общий расчет | D43: =IFERROR(VLOOKUP(Rule!J43,lvl_2[],2,FALSE),"Нет") -> Ци Мень | E43: =IFERROR(VLOOKUP(Rule!K43,lvl_3[],2,FALSE),"Нет") -> Анализ Дворца | F43: =IFERROR(INDEX(lvl_4[],MATCH(L43,lvl_4[ID],0),MATCH(TEXT(K43,"##0"),lvl_4[#Headers],0)),"Нет") -> Комбинации | G43: =IFERROR(INDEX(lvl_5[],MATCH(M43,lvl_5[ID],0),MATCH(_xlfn.CONCAT(TEXT(K43,"##0"),"_",TEXT(L43,"##0")),lvl_5[#Headers],0)),"Нет") -> Нет | H43: =IFERROR(INDEX(lvl_6[],MATCH(N43,lvl_6[ID],0),MATCH(_xlfn.CONCAT(K43,"_",L43,"_",M43),lvl_6[#Headers],0)),"Нет") -> Нет | I43: 1 | J43: 2 | K43: 2 | L43: 2 | M43: 0 | N43: 0 | O43: =COUNTIF($P$2:P43,P43) -> 40 | P43: =_xlfn.CONCAT(I43, J43, K43, IF(LEN(L43)=1,_xlfn.CONCAT(0,L43),L43), IF(LEN(M43)=1,_xlfn.CONCAT(0,M43),M43), IF(LEN(N43)=1,_xlfn.CONCAT(0,N43),N43)) -> 122020000 | Q43: =_xlfn.CONCAT(I43, J43, K43, IF(LEN(L43)=1,_xlfn.CONCAT(0,L43),L43), IF(LEN(M43)=1,_xlfn.CONCAT(0,M43),M43), IF(LEN(N43)=1,_xlfn.CONCAT(0,N43),N43), IF(LEN(O43)=1,_xlfn.CONCAT("000",O43),IF(LEN(O43)=2,_xlfn.CONCAT("00",O43),IF(LEN(O43)=3,_xlfn.CONCAT(0,O43),O43)))) -> 1220200000040 | R43: Три притворства (Три лжи). Настоящая ложь (Правильная ложь) | S43: Чтобы преуспеть нужно создать себе правильный образ. Можно получить помощь, если притворитесь слабым, мирным, дружелюбным. Хорошо для бизнес-сделок, религиозных церемоний, благотворительности, совершения добрых дел, награждения других | AY43: 丙 | BB43: 休 | BF43: 陰 | BG43: 1 | BJ43: 1
A44: 1 | B44: =_xlfn.CONCAT(C44,". ", D44,". ", E44,". ", F44,". ", G44,". ", H44) -> Общий расчет. Ци Мень. Анализ Дворца. Комбинации. Нет. Нет | C44: =IFERROR(VLOOKUP(I44,lvl_1[],2,FALSE),"Нет") -> Общий расчет | D44: =IFERROR(VLOOKUP(Rule!J44,lvl_2[],2,FALSE),"Нет") -> Ци Мень | E44: =IFERROR(VLOOKUP(Rule!K44,lvl_3[],2,FALSE),"Нет") -> Анализ Дворца | F44: =IFERROR(INDEX(lvl_4[],MATCH(L44,lvl_4[ID],0),MATCH(TEXT(K44,"##0"),lvl_4[#Headers],0)),"Нет") -> Комбинации | G44: =IFERROR(INDEX(lvl_5[],MATCH(M44,lvl_5[ID],0),MATCH(_xlfn.CONCAT(TEXT(K44,"##0"),"_",TEXT(L44,"##0")),lvl_5[#Headers],0)),"Нет") -> Нет | H44: =IFERROR(INDEX(lvl_6[],MATCH(N44,lvl_6[ID],0),MATCH(_xlfn.CONCAT(K44,"_",L44,"_",M44),lvl_6[#Headers],0)),"Нет") -> Нет | I44: 1 | J44: 2 | K44: 2 | L44: 2 | M44: 0 | N44: 0 | O44: =COUNTIF($P$2:P44,P44) -> 41 | P44: =_xlfn.CONCAT(I44, J44, K44, IF(LEN(L44)=1,_xlfn.CONCAT(0,L44),L44), IF(LEN(M44)=1,_xlfn.CONCAT(0,M44),M44), IF(LEN(N44)=1,_xlfn.CONCAT(0,N44),N44)) -> 122020000 | Q44: =_xlfn.CONCAT(I44, J44, K44, IF(LEN(L44)=1,_xlfn.CONCAT(0,L44),L44), IF(LEN(M44)=1,_xlfn.CONCAT(0,M44),M44), IF(LEN(N44)=1,_xlfn.CONCAT(0,N44),N44), IF(LEN(O44)=1,_xlfn.CONCAT("000",O44),IF(LEN(O44)=2,_xlfn.CONCAT("00",O44),IF(LEN(O44)=3,_xlfn.CONCAT(0,O44),O44)))) -> 1220200000041 | R44: Три притворства (Три лжи). Настоящая ложь (Правильная ложь) | S44: Чтобы преуспеть нужно создать себе правильный образ. Можно получить помощь, если притворитесь слабым, мирным, дружелюбным. Хорошо для бизнес-сделок, религиозных церемоний, благотворительности, совершения добрых дел, награждения других | AY44: 丙 | BB44: 生 | BF44: 陰 | BG44: 1 | BJ44: 1
A45: 1 | B45: =_xlfn.CONCAT(C45,". ", D45,". ", E45,". ", F45,". ", G45,". ", H45) -> Общий расчет. Ци Мень. Анализ Дворца. Комбинации. Нет. Нет | C45: =IFERROR(VLOOKUP(I45,lvl_1[],2,FALSE),"Нет") -> Общий расчет | D45: =IFERROR(VLOOKUP(Rule!J45,lvl_2[],2,FALSE),"Нет") -> Ци Мень | E45: =IFERROR(VLOOKUP(Rule!K45,lvl_3[],2,FALSE),"Нет") -> Анализ Дворца | F45: =IFERROR(INDEX(lvl_4[],MATCH(L45,lvl_4[ID],0),MATCH(TEXT(K45,"##0"),lvl_4[#Headers],0)),"Нет") -> Комбинации | G45: =IFERROR(INDEX(lvl_5[],MATCH(M45,lvl_5[ID],0),MATCH(_xlfn.CONCAT(TEXT(K45,"##0"),"_",TEXT(L45,"##0")),lvl_5[#Headers],0)),"Нет") -> Нет | H45: =IFERROR(INDEX(lvl_6[],MATCH(N45,lvl_6[ID],0),MATCH(_xlfn.CONCAT(K45,"_",L45,"_",M45),lvl_6[#Headers],0)),"Нет") -> Нет | I45: 1 | J45: 2 | K45: 2 | L45: 2 | M45: 0 | N45: 0 | O45: =COUNTIF($P$2:P45,P45) -> 42 | P45: =_xlfn.CONCAT(I45, J45, K45, IF(LEN(L45)=1,_xlfn.CONCAT(0,L45),L45), IF(LEN(M45)=1,_xlfn.CONCAT(0,M45),M45), IF(LEN(N45)=1,_xlfn.CONCAT(0,N45),N45)) -> 122020000 | Q45: =_xlfn.CONCAT(I45, J45, K45, IF(LEN(L45)=1,_xlfn.CONCAT(0,L45),L45), IF(LEN(M45)=1,_xlfn.CONCAT(0,M45),M45), IF(LEN(N45)=1,_xlfn.CONCAT(0,N45),N45), IF(LEN(O45)=1,_xlfn.CONCAT("000",O45),IF(LEN(O45)=2,_xlfn.CONCAT("00",O45),IF(LEN(O45)=3,_xlfn.CONCAT(0,O45),O45)))) -> 1220200000042 | R45: Три притворства (Три лжи). Счастливая ложь | S45: Поиск медицинской помощи, лечение заболеваний, религиозные церемонии, поиск защиты и безопасности, устранение разногласий, повышение статуса и поиск богатства. Можно получить помощь, если притворитесь слабым, мирным, дружелюбным. Благоприятно для бизнеса, путешествий, брака. | AY45: 乙 | BB45: 開 | BF45: 合 | BG45: 1 | BJ45: 1
A46: 1 | B46: =_xlfn.CONCAT(C46,". ", D46,". ", E46,". ", F46,". ", G46,". ", H46) -> Общий расчет. Ци Мень. Анализ Дворца. Комбинации. Нет. Нет | C46: =IFERROR(VLOOKUP(I46,lvl_1[],2,FALSE),"Нет") -> Общий расчет | D46: =IFERROR(VLOOKUP(Rule!J46,lvl_2[],2,FALSE),"Нет") -> Ци Мень | E46: =IFERROR(VLOOKUP(Rule!K46,lvl_3[],2,FALSE),"Нет") -> Анализ Дворца | F46: =IFERROR(INDEX(lvl_4[],MATCH(L46,lvl_4[ID],0),MATCH(TEXT(K46,"##0"),lvl_4[#Headers],0)),"Нет") -> Комбинации | G46: =IFERROR(INDEX(lvl_5[],MATCH(M46,lvl_5[ID],0),MATCH(_xlfn.CONCAT(TEXT(K46,"##0"),"_",TEXT(L46,"##0")),lvl_5[#Headers],0)),"Нет") -> Нет | H46: =IFERROR(INDEX(lvl_6[],MATCH(N46,lvl_6[ID],0),MATCH(_xlfn.CONCAT(K46,"_",L46,"_",M46),lvl_6[#Headers],0)),"Нет") -> Нет | I46: 1 | J46: 2 | K46: 2 | L46: 2 | M46: 0 | N46: 0 | O46: =COUNTIF($P$2:P46,P46) -> 43 | P46: =_xlfn.CONCAT(I46, J46, K46, IF(LEN(L46)=1,_xlfn.CONCAT(0,L46),L46), IF(LEN(M46)=1,_xlfn.CONCAT(0,M46),M46), IF(LEN(N46)=1,_xlfn.CONCAT(0,N46),N46)) -> 122020000 | Q46: =_xlfn.CONCAT(I46, J46, K46, IF(LEN(L46)=1,_xlfn.CONCAT(0,L46),L46), IF(LEN(M46)=1,_xlfn.CONCAT(0,M46),M46), IF(LEN(N46)=1,_xlfn.CONCAT(0,N46),N46), IF(LEN(O46)=1,_xlfn.CONCAT("000",O46),IF(LEN(O46)=2,_xlfn.CONCAT("00",O46),IF(LEN(O46)=3,_xlfn.CONCAT(0,O46),O46)))) -> 1220200000043 | R46: Три притворства (Три лжи). Счастливая ложь | S46: Поиск медицинской помощи, лечение заболеваний, религиозные церемонии, поиск защиты и безопасности, устранение разногласий, повышение статуса и поиск богатства. Можно получить помощь, если притворитесь слабым, мирным, дружелюбным. Благоприятно для бизнеса, путешествий, брака. | AY46: 乙 | BB46: 休 | BF46: 合 | BG46: 1 | BJ46: 1
A47: 1 | B47: =_xlfn.CONCAT(C47,". ", D47,". ", E47,". ", F47,". ", G47,". ", H47) -> Общий расчет. Ци Мень. Анализ Дворца. Комбинации. Нет. Нет | C47: =IFERROR(VLOOKUP(I47,lvl_1[],2,FALSE),"Нет") -> Общий расчет | D47: =IFERROR(VLOOKUP(Rule!J47,lvl_2[],2,FALSE),"Нет") -> Ци Мень | E47: =IFERROR(VLOOKUP(Rule!K47,lvl_3[],2,FALSE),"Нет") -> Анализ Дворца | F47: =IFERROR(INDEX(lvl_4[],MATCH(L47,lvl_4[ID],0),MATCH(TEXT(K47,"##0"),lvl_4[#Headers],0)),"Нет") -> Комбинации | G47: =IFERROR(INDEX(lvl_5[],MATCH(M47,lvl_5[ID],0),MATCH(_xlfn.CONCAT(TEXT(K47,"##0"),"_",TEXT(L47,"##0")),lvl_5[#Headers],0)),"Нет") -> Нет | H47: =IFERROR(INDEX(lvl_6[],MATCH(N47,lvl_6[ID],0),MATCH(_xlfn.CONCAT(K47,"_",L47,"_",M47),lvl_6[#Headers],0)),"Нет") -> Нет | I47: 1 | J47: 2 | K47: 2 | L47: 2 | M47: 0 | N47: 0 | O47: =COUNTIF($P$2:P47,P47) -> 44 | P47: =_xlfn.CONCAT(I47, J47, K47, IF(LEN(L47)=1,_xlfn.CONCAT(0,L47),L47), IF(LEN(M47)=1,_xlfn.CONCAT(0,M47),M47), IF(LEN(N47)=1,_xlfn.CONCAT(0,N47),N47)) -> 122020000 | Q47: =_xlfn.CONCAT(I47, J47, K47, IF(LEN(L47)=1,_xlfn.CONCAT(0,L47),L47), IF(LEN(M47)=1,_xlfn.CONCAT(0,M47),M47), IF(LEN(N47)=1,_xlfn.CONCAT(0,N47),N47), IF(LEN(O47)=1,_xlfn.CONCAT("000",O47),IF(LEN(O47)=2,_xlfn.CONCAT("00",O47),IF(LEN(O47)=3,_xlfn.CONCAT(0,O47),O47)))) -> 1220200000044 | R47: Три притворства (Три лжи). Счастливая ложь | S47: Поиск медицинской помощи, лечение заболеваний, религиозные церемонии, поиск защиты и безопасности, устранение разногласий, повышение статуса и поиск богатства. Можно получить помощь, если притворитесь слабым, мирным, дружелюбным. Благоприятно для бизнеса, путешествий, брака. | AY47: 乙 | BB47: 生 | BF47: 合 | BG47: 1 | BJ47: 1
... A81: 1 | B81: =_xlfn.CONCAT(C81,". ", D81,". ", E81,". ", F81,". ", G81,". ", H81) -> Общий расчет. Ци Мень. Анализ Дворца. Комбинации. Нет. Нет | C81: =IFERROR(VLOOKUP(I81,lvl_1[],2,FALSE),"Нет") -> Общий расчет | D81: =IFERROR(VLOOKUP(Rule!J81,lvl_2[],2,FALSE),"Нет") -> Ци Мень | E81: =IFERROR(VLOOKUP(Rule!K81,lvl_3[],2,FALSE),"Нет") -> Анализ Дворца | F81: =IFERROR(INDEX(lvl_4[],MATCH(L81,lvl_4[ID],0),MATCH(TEXT(K81,"##0"),lvl_4[#Headers],0)),"Нет") -> Комбинации | G81: =IFERROR(INDEX(lvl_5[],MATCH(M81,lvl_5[ID],0),MATCH(_xlfn.CONCAT(TEXT(K81,"##0"),"_",TEXT(L81,"##0")),lvl_5[#Headers],0)),"Нет") -> Нет | H81: =IFERROR(INDEX(lvl_6[],MATCH(N81,lvl_6[ID],0),MATCH(_xlfn.CONCAT(K81,"_",L81,"_",M81),lvl_6[#Headers],0)),"Нет") -> Нет | I81: 1 | J81: 2 | K81: 2 | L81: 2 | M81: 0 | N81: 0 | O81: =COUNTIF($P$2:P81,P81) -> 78 | P81: =_xlfn.CONCAT(I81, J81, K81, IF(LEN(L81)=1,_xlfn.CONCAT(0,L81),L81), IF(LEN(M81)=1,_xlfn.CONCAT(0,M81),M81), IF(LEN(N81)=1,_xlfn.CONCAT(0,N81),N81)) -> 122020000 | Q81: =_xlfn.CONCAT(I81, J81, K81, IF(LEN(L81)=1,_xlfn.CONCAT(0,L81),L81), IF(LEN(M81)=1,_xlfn.CONCAT(0,M81),M81), IF(LEN(N81)=1,_xlfn.CONCAT(0,N81),N81), IF(LEN(O81)=1,_xlfn.CONCAT("000",O81),IF(LEN(O81)=2,_xlfn.CONCAT("00",O81),IF(LEN(O81)=3,_xlfn.CONCAT(0,O81),O81)))) -> 1220200000078 | R81: Пять обманов. Обман духов | S81: Благоприятно для медитаций, молитв, поиска медицинской помощи, похорон. Использовать для устранения странных явлений в доме. Вы будете в безопасности от иньских духов. | AY81: 癸 | BB81: 死 | BF81: 地 | BG81: 1 | BJ81: 1
A82: 1 | B82: =_xlfn.CONCAT(C82,". ", D82,". ", E82,". ", F82,". ", G82,". ", H82) -> Общий расчет. Ци Мень. Анализ Дворца. Комбинации. Нет. Нет | C82: =IFERROR(VLOOKUP(I82,lvl_1[],2,FALSE),"Нет") -> Общий расчет | D82: =IFERROR(VLOOKUP(Rule!J82,lvl_2[],2,FALSE),"Нет") -> Ци Мень | E82: =IFERROR(VLOOKUP(Rule!K82,lvl_3[],2,FALSE),"Нет") -> Анализ Дворца | F82: =IFERROR(INDEX(lvl_4[],MATCH(L82,lvl_4[ID],0),MATCH(TEXT(K82,"##0"),lvl_4[#Headers],0)),"Нет") -> Комбинации | G82: =IFERROR(INDEX(lvl_5[],MATCH(M82,lvl_5[ID],0),MATCH(_xlfn.CONCAT(TEXT(K82,"##0"),"_",TEXT(L82,"##0")),lvl_5[#Headers],0)),"Нет") -> Нет | H82: =IFERROR(INDEX(lvl_6[],MATCH(N82,lvl_6[ID],0),MATCH(_xlfn.CONCAT(K82,"_",L82,"_",M82),lvl_6[#Headers],0)),"Нет") -> Нет | I82: 1 | J82: 2 | K82: 2 | L82: 2 | M82: 0 | N82: 0 | O82: =COUNTIF($P$2:P82,P82) -> 79 | P82: =_xlfn.CONCAT(I82, J82, K82, IF(LEN(L82)=1,_xlfn.CONCAT(0,L82),L82), IF(LEN(M82)=1,_xlfn.CONCAT(0,M82),M82), IF(LEN(N82)=1,_xlfn.CONCAT(0,N82),N82)) -> 122020000 | Q82: =_xlfn.CONCAT(I82, J82, K82, IF(LEN(L82)=1,_xlfn.CONCAT(0,L82),L82), IF(LEN(M82)=1,_xlfn.CONCAT(0,M82),M82), IF(LEN(N82)=1,_xlfn.CONCAT(0,N82),N82), IF(LEN(O82)=1,_xlfn.CONCAT("000",O82),IF(LEN(O82)=2,_xlfn.CONCAT("00",O82),IF(LEN(O82)=3,_xlfn.CONCAT(0,O82),O82)))) -> 1220200000079 | R82: Структура периода | S82: Хорошо для планирования, учебы, деловых встреч и собраний | AW82: 2 | BA82: 乙 | BB82: 生 | BG82: 1 | BJ82: 1
A83: 1 | B83: =_xlfn.CONCAT(C83,". ", D83,". ", E83,". ", F83,". ", G83,". ", H83) -> Общий расчет. Ци Мень. Анализ Дворца. Комбинации. Нет. Нет | C83: =IFERROR(VLOOKUP(I83,lvl_1[],2,FALSE),"Нет") -> Общий расчет | D83: =IFERROR(VLOOKUP(Rule!J83,lvl_2[],2,FALSE),"Нет") -> Ци Мень | E83: =IFERROR(VLOOKUP(Rule!K83,lvl_3[],2,FALSE),"Нет") -> Анализ Дворца | F83: =IFERROR(INDEX(lvl_4[],MATCH(L83,lvl_4[ID],0),MATCH(TEXT(K83,"##0"),lvl_4[#Headers],0)),"Нет") -> Комбинации | G83: =IFERROR(INDEX(lvl_5[],MATCH(M83,lvl_5[ID],0),MATCH(_xlfn.CONCAT(TEXT(K83,"##0"),"_",TEXT(L83,"##0")),lvl_5[#Headers],0)),"Нет") -> Нет | H83: =IFERROR(INDEX(lvl_6[],MATCH(N83,lvl_6[ID],0),MATCH(_xlfn.CONCAT(K83,"_",L83,"_",M83),lvl_6[#Headers],0)),"Нет") -> Нет | I83: 1 | J83: 2 | K83: 2 | L83: 2 | M83: 0 | N83: 0 | O83: =COUNTIF($P$2:P83,P83) -> 80 | P83: =_xlfn.CONCAT(I83, J83, K83, IF(LEN(L83)=1,_xlfn.CONCAT(0,L83),L83), IF(LEN(M83)=1,_xlfn.CONCAT(0,M83),M83), IF(LEN(N83)=1,_xlfn.CONCAT(0,N83),N83)) -> 122020000 | Q83: =_xlfn.CONCAT(I83, J83, K83, IF(LEN(L83)=1,_xlfn.CONCAT(0,L83),L83), IF(LEN(M83)=1,_xlfn.CONCAT(0,M83),M83), IF(LEN(N83)=1,_xlfn.CONCAT(0,N83),N83), IF(LEN(O83)=1,_xlfn.CONCAT("000",O83),IF(LEN(O83)=2,_xlfn.CONCAT("00",O83),IF(LEN(O83)=3,_xlfn.CONCAT(0,O83),O83)))) -> 1220200000080 | R83: Структура периода | S83: Хорошо для планирования, учебы, деловых встреч и собраний | AW83: 2 | BA83: 乙 | BB83: 開 | BG83: 1 | BJ83: 1
A84: 1 | B84: =_xlfn.CONCAT(C84,". ", D84,". ", E84,". ", F84,". ", G84,". ", H84) -> Общий расчет. Ци Мень. Анализ Дворца. Комбинации. Нет. Нет | C84: =IFERROR(VLOOKUP(I84,lvl_1[],2,FALSE),"Нет") -> Общий расчет | D84: =IFERROR(VLOOKUP(Rule!J84,lvl_2[],2,FALSE),"Нет") -> Ци Мень | E84: =IFERROR(VLOOKUP(Rule!K84,lvl_3[],2,FALSE),"Нет") -> Анализ Дворца | F84: =IFERROR(INDEX(lvl_4[],MATCH(L84,lvl_4[ID],0),MATCH(TEXT(K84,"##0"),lvl_4[#Headers],0)),"Нет") -> Комбинации | G84: =IFERROR(INDEX(lvl_5[],MATCH(M84,lvl_5[ID],0),MATCH(_xlfn.CONCAT(TEXT(K84,"##0"),"_",TEXT(L84,"##0")),lvl_5[#Headers],0)),"Нет") -> Нет | H84: =IFERROR(INDEX(lvl_6[],MATCH(N84,lvl_6[ID],0),MATCH(_xlfn.CONCAT(K84,"_",L84,"_",M84),lvl_6[#Headers],0)),"Нет") -> Нет | I84: 1 | J84: 2 | K84: 2 | L84: 2 | M84: 0 | N84: 0 | O84: =COUNTIF($P$2:P84,P84) -> 81 | P84: =_xlfn.CONCAT(I84, J84, K84, IF(LEN(L84)=1,_xlfn.CONCAT(0,L84),L84), IF(LEN(M84)=1,_xlfn.CONCAT(0,M84),M84), IF(LEN(N84)=1,_xlfn.CONCAT(0,N84),N84)) -> 122020000 | Q84: =_xlfn.CONCAT(I84, J84, K84, IF(LEN(L84)=1,_xlfn.CONCAT(0,L84),L84), IF(LEN(M84)=1,_xlfn.CONCAT(0,M84),M84), IF(LEN(N84)=1,_xlfn.CONCAT(0,N84),N84), IF(LEN(O84)=1,_xlfn.CONCAT("000",O84),IF(LEN(O84)=2,_xlfn.CONCAT("00",O84),IF(LEN(O84)=3,_xlfn.CONCAT(0,O84),O84)))) -> 1220200000081 | R84: Структура периода | S84: Хорошо для планирования, учебы, деловых встреч и собраний | AW84: 2 | BA84: 乙 | BB84: 休 | BG84: 1 | BJ84: 1
A85: 1 | B85: =_xlfn.CONCAT(C85,". ", D85,". ", E85,". ", F85,". ", G85,". ", H85) -> Общий расчет. Ци Мень. Анализ Дворца. Комбинации. Нет. Нет | C85: =IFERROR(VLOOKUP(I85,lvl_1[],2,FALSE),"Нет") -> Общий расчет | D85: =IFERROR(VLOOKUP(Rule!J85,lvl_2[],2,FALSE),"Нет") -> Ци Мень | E85: =IFERROR(VLOOKUP(Rule!K85,lvl_3[],2,FALSE),"Нет") -> Анализ Дворца | F85: =IFERROR(INDEX(lvl_4[],MATCH(L85,lvl_4[ID],0),MATCH(TEXT(K85,"##0"),lvl_4[#Headers],0)),"Нет") -> Комбинации | G85: =IFERROR(INDEX(lvl_5[],MATCH(M85,lvl_5[ID],0),MATCH(_xlfn.CONCAT(TEXT(K85,"##0"),"_",TEXT(L85,"##0")),lvl_5[#Headers],0)),"Нет") -> Нет | H85: =IFERROR(INDEX(lvl_6[],MATCH(N85,lvl_6[ID],0),MATCH(_xlfn.CONCAT(K85,"_",L85,"_",M85),lvl_6[#Headers],0)),"Нет") -> Нет | I85: 1 | J85: 2 | K85: 2 | L85: 2 | M85: 0 | N85: 0 | O85: =COUNTIF($P$2:P85,P85) -> 82 | P85: =_xlfn.CONCAT(I85, J85, K85, IF(LEN(L85)=1,_xlfn.CONCAT(0,L85),L85), IF(LEN(M85)=1,_xlfn.CONCAT(0,M85),M85), IF(LEN(N85)=1,_xlfn.CONCAT(0,N85),N85)) -> 122020000 | Q85: =_xlfn.CONCAT(I85, J85, K85, IF(LEN(L85)=1,_xlfn.CONCAT(0,L85),L85), IF(LEN(M85)=1,_xlfn.CONCAT(0,M85),M85), IF(LEN(N85)=1,_xlfn.CONCAT(0,N85),N85), IF(LEN(O85)=1,_xlfn.CONCAT("000",O85),IF(LEN(O85)=2,_xlfn.CONCAT("00",O85),IF(LEN(O85)=3,_xlfn.CONCAT(0,O85),O85)))) -> 1220200000082 | R85: Вам помогают | S85: Благоприятно практически для всего, что является видимым и легальным. Хорошо для благосостояния, репутации, славы. | AX85: 1 | BA85: 丁 | BG85: 1 | BJ85: 1
A86: 1 | B86: =_xlfn.CONCAT(C86,". ", D86,". ", E86,". ", F86,". ", G86,". ", H86) -> Общий расчет. Ци Мень. Анализ Дворца. Комбинации. Нет. Нет | C86: =IFERROR(VLOOKUP(I86,lvl_1[],2,FALSE),"Нет") -> Общий расчет | D86: =IFERROR(VLOOKUP(Rule!J86,lvl_2[],2,FALSE),"Нет") -> Ци Мень | E86: =IFERROR(VLOOKUP(Rule!K86,lvl_3[],2,FALSE),"Нет") -> Анализ Дворца | F86: =IFERROR(INDEX(lvl_4[],MATCH(L86,lvl_4[ID],0),MATCH(TEXT(K86,"##0"),lvl_4[#Headers],0)),"Нет") -> Комбинации | G86: =IFERROR(INDEX(lvl_5[],MATCH(M86,lvl_5[ID],0),MATCH(_xlfn.CONCAT(TEXT(K86,"##0"),"_",TEXT(L86,"##0")),lvl_5[#Headers],0)),"Нет") -> Нет | H86: =IFERROR(INDEX(lvl_6[],MATCH(N86,lvl_6[ID],0),MATCH(_xlfn.CONCAT(K86,"_",L86,"_",M86),lvl_6[#Headers],0)),"Нет") -> Нет | I86: 1 | J86: 2 | K86: 2 | L86: 2 | M86: 0 | N86: 0 | O86: =COUNTIF($P$2:P86,P86) -> 83 | P86: =_xlfn.CONCAT(I86, J86, K86, IF(LEN(L86)=1,_xlfn.CONCAT(0,L86),L86), IF(LEN(M86)=1,_xlfn.CONCAT(0,M86),M86), IF(LEN(N86)=1,_xlfn.CONCAT(0,N86),N86)) -> 122020000 | Q86: =_xlfn.CONCAT(I86, J86, K86, IF(LEN(L86)=1,_xlfn.CONCAT(0,L86),L86), IF(LEN(M86)=1,_xlfn.CONCAT(0,M86),M86), IF(LEN(N86)=1,_xlfn.CONCAT(0,N86),N86), IF(LEN(O86)=1,_xlfn.CONCAT("000",O86),IF(LEN(O86)=2,_xlfn.CONCAT("00",O86),IF(LEN(O86)=3,_xlfn.CONCAT(0,O86),O86)))) -> 1220200000083 | R86: Вам помогают | S86: Благоприятно практически для всего, что является видимым и легальным. Хорошо для благосостояния, репутации, славы. | AX86: 1 | BA86: 丙 | BG86: 1 | BJ86: 1
A87: 1 | B87: =_xlfn.CONCAT(C87,". ", D87,". ", E87,". ", F87,". ", G87,". ", H87) -> Общий расчет. Ци Мень. Анализ Дворца. Комбинации. Нет. Нет | C87: =IFERROR(VLOOKUP(I87,lvl_1[],2,FALSE),"Нет") -> Общий расчет | D87: =IFERROR(VLOOKUP(Rule!J87,lvl_2[],2,FALSE),"Нет") -> Ци Мень | E87: =IFERROR(VLOOKUP(Rule!K87,lvl_3[],2,FALSE),"Нет") -> Анализ Дворца | F87: =IFERROR(INDEX(lvl_4[],MATCH(L87,lvl_4[ID],0),MATCH(TEXT(K87,"##0"),lvl_4[#Headers],0)),"Нет") -> Комбинации | G87: =IFERROR(INDEX(lvl_5[],MATCH(M87,lvl_5[ID],0),MATCH(_xlfn.CONCAT(TEXT(K87,"##0"),"_",TEXT(L87,"##0")),lvl_5[#Headers],0)),"Нет") -> Нет | H87: =IFERROR(INDEX(lvl_6[],MATCH(N87,lvl_6[ID],0),MATCH(_xlfn.CONCAT(K87,"_",L87,"_",M87),lvl_6[#Headers],0)),"Нет") -> Нет | I87: 1 | J87: 2 | K87: 2 | L87: 2 | M87: 0 | N87: 0 | O87: =COUNTIF($P$2:P87,P87) -> 84 | P87: =_xlfn.CONCAT(I87, J87, K87, IF(LEN(L87)=1,_xlfn.CONCAT(0,L87),L87), IF(LEN(M87)=1,_xlfn.CONCAT(0,M87),M87), IF(LEN(N87)=1,_xlfn.CONCAT(0,N87),N87)) -> 122020000 | Q87: =_xlfn.CONCAT(I87, J87, K87, IF(LEN(L87)=1,_xlfn.CONCAT(0,L87),L87), IF(LEN(M87)=1,_xlfn.CONCAT(0,M87),M87), IF(LEN(N87)=1,_xlfn.CONCAT(0,N87),N87), IF(LEN(O87)=1,_xlfn.CONCAT("000",O87),IF(LEN(O87)=2,_xlfn.CONCAT("00",O87),IF(LEN(O87)=3,_xlfn.CONCAT(0,O87),O87)))) -> 1220200000084 | R87: Вам помогают | S87: Благоприятно практически для всего, что является видимым и легальным. Хорошо для благосостояния, репутации, славы. | AX87: 1 | BA87: 乙 | BG87: 1 | BJ87: 1
A88: 1 | B88: =_xlfn.CONCAT(C88,". ", D88,". ", E88,". ", F88,". ", G88,". ", H88) -> Общий расчет. Ци Мень. Анализ Дворца. Комбинации. Нет. Нет | C88: =IFERROR(VLOOKUP(I88,lvl_1[],2,FALSE),"Нет") -> Общий расчет | D88: =IFERROR(VLOOKUP(Rule!J88,lvl_2[],2,FALSE),"Нет") -> Ци Мень | E88: =IFERROR(VLOOKUP(Rule!K88,lvl_3[],2,FALSE),"Нет") -> Анализ Дворца | F88: =IFERROR(INDEX(lvl_4[],MATCH(L88,lvl_4[ID],0),MATCH(TEXT(K88,"##0"),lvl_4[#Headers],0)),"Нет") -> Комбинации | G88: =IFERROR(INDEX(lvl_5[],MATCH(M88,lvl_5[ID],0),MATCH(_xlfn.CONCAT(TEXT(K88,"##0"),"_",TEXT(L88,"##0")),lvl_5[#Headers],0)),"Нет") -> Нет | H88: =IFERROR(INDEX(lvl_6[],MATCH(N88,lvl_6[ID],0),MATCH(_xlfn.CONCAT(K88,"_",L88,"_",M88),lvl_6[#Headers],0)),"Нет") -> Нет | I88: 1 | J88: 2 | K88: 2 | L88: 2 | M88: 0 | N88: 0 | O88: =COUNTIF($P$2:P88,P88) -> 85 | P88: =_xlfn.CONCAT(I88, J88, K88, IF(LEN(L88)=1,_xlfn.CONCAT(0,L88),L88), IF(LEN(M88)=1,_xlfn.CONCAT(0,M88),M88), IF(LEN(N88)=1,_xlfn.CONCAT(0,N88),N88)) -> 122020000 | Q88: =_xlfn.CONCAT(I88, J88, K88, IF(LEN(L88)=1,_xlfn.CONCAT(0,L88),L88), IF(LEN(M88)=1,_xlfn.CONCAT(0,M88),M88), IF(LEN(N88)=1,_xlfn.CONCAT(0,N88),N88), IF(LEN(O88)=1,_xlfn.CONCAT("000",O88),IF(LEN(O88)=2,_xlfn.CONCAT("00",O88),IF(LEN(O88)=3,_xlfn.CONCAT(0,O88),O88)))) -> 1220200000085 | R88: Помощь неба | S88: Все идет гладко, как запланировано | AZ88: 1 | BA88: 丁 | BG88: 1 | BJ88: 1
A89: 1 | B89: =_xlfn.CONCAT(C89,". ", D89,". ", E89,". ", F89,". ", G89,". ", H89) -> Общий расчет. Ци Мень. Анализ Дворца. Комбинации. Нет. Нет | C89: =IFERROR(VLOOKUP(I89,lvl_1[],2,FALSE),"Нет") -> Общий расчет | D89: =IFERROR(VLOOKUP(Rule!J89,lvl_2[],2,FALSE),"Нет") -> Ци Мень | E89: =IFERROR(VLOOKUP(Rule!K89,lvl_3[],2,FALSE),"Нет") -> Анализ Дворца | F89: =IFERROR(INDEX(lvl_4[],MATCH(L89,lvl_4[ID],0),MATCH(TEXT(K89,"##0"),lvl_4[#Headers],0)),"Нет") -> Комбинации | G89: =IFERROR(INDEX(lvl_5[],MATCH(M89,lvl_5[ID],0),MATCH(_xlfn.CONCAT(TEXT(K89,"##0"),"_",TEXT(L89,"##0")),lvl_5[#Headers],0)),"Нет") -> Нет | H89: =IFERROR(INDEX(lvl_6[],MATCH(N89,lvl_6[ID],0),MATCH(_xlfn.CONCAT(K89,"_",L89,"_",M89),lvl_6[#Headers],0)),"Нет") -> Нет | I89: 1 | J89: 2 | K89: 2 | L89: 2 | M89: 0 | N89: 0 | O89: =COUNTIF($P$2:P89,P89) -> 86 | P89: =_xlfn.CONCAT(I89, J89, K89, IF(LEN(L89)=1,_xlfn.CONCAT(0,L89),L89), IF(LEN(M89)=1,_xlfn.CONCAT(0,M89),M89), IF(LEN(N89)=1,_xlfn.CONCAT(0,N89),N89)) -> 122020000 | Q89: =_xlfn.CONCAT(I89, J89, K89, IF(LEN(L89)=1,_xlfn.CONCAT(0,L89),L89), IF(LEN(M89)=1,_xlfn.CONCAT(0,M89),M89), IF(LEN(N89)=1,_xlfn.CONCAT(0,N89),N89), IF(LEN(O89)=1,_xlfn.CONCAT("000",O89),IF(LEN(O89)=2,_xlfn.CONCAT("00",O89),IF(LEN(O89)=3,_xlfn.CONCAT(0,O89),O89)))) -> 1220200000086 | R89: Помощь неба | S89: Все идет гладко, как запланировано | AZ89: 1 | BA89: 丙 | BG89: 1 | BJ89: 1
A90: 1 | B90: =_xlfn.CONCAT(C90,". ", D90,". ", E90,". ", F90,". ", G90,". ", H90) -> Общий расчет. Ци Мень. Анализ Дворца. Комбинации. Нет. Нет | C90: =IFERROR(VLOOKUP(I90,lvl_1[],2,FALSE),"Нет") -> Общий расчет | D90: =IFERROR(VLOOKUP(Rule!J90,lvl_2[],2,FALSE),"Нет") -> Ци Мень | E90: =IFERROR(VLOOKUP(Rule!K90,lvl_3[],2,FALSE),"Нет") -> Анализ Дворца | F90: =IFERROR(INDEX(lvl_4[],MATCH(L90,lvl_4[ID],0),MATCH(TEXT(K90,"##0"),lvl_4[#Headers],0)),"Нет") -> Комбинации | G90: =IFERROR(INDEX(lvl_5[],MATCH(M90,lvl_5[ID],0),MATCH(_xlfn.CONCAT(TEXT(K90,"##0"),"_",TEXT(L90,"##0")),lvl_5[#Headers],0)),"Нет") -> Нет | H90: =IFERROR(INDEX(lvl_6[],MATCH(N90,lvl_6[ID],0),MATCH(_xlfn.CONCAT(K90,"_",L90,"_",M90),lvl_6[#Headers],0)),"Нет") -> Нет | I90: 1 | J90: 2 | K90: 2 | L90: 2 | M90: 0 | N90: 0 | O90: =COUNTIF($P$2:P90,P90) -> 87 | P90: =_xlfn.CONCAT(I90, J90, K90, IF(LEN(L90)=1,_xlfn.CONCAT(0,L90),L90), IF(LEN(M90)=1,_xlfn.CONCAT(0,M90),M90), IF(LEN(N90)=1,_xlfn.CONCAT(0,N90),N90)) -> 122020000 | Q90: =_xlfn.CONCAT(I90, J90, K90, IF(LEN(L90)=1,_xlfn.CONCAT(0,L90),L90), IF(LEN(M90)=1,_xlfn.CONCAT(0,M90),M90), IF(LEN(N90)=1,_xlfn.CONCAT(0,N90),N90), IF(LEN(O90)=1,_xlfn.CONCAT("000",O90),IF(LEN(O90)=2,_xlfn.CONCAT("00",O90),IF(LEN(O90)=3,_xlfn.CONCAT(0,O90),O90)))) -> 1220200000087 | R90: Помощь неба | S90: Все идет гладко, как запланировано | AZ90: 1 | BA90: 乙 | BG90: 1 | BJ90: 1
A91: 1 | B91: =_xlfn.CONCAT(C91,". ", D91,". ", E91,". ", F91,". ", G91,". ", H91) -> Общий расчет. Ци Мень. Анализ Дворца. Комбинации. Нет. Нет | C91: =IFERROR(VLOOKUP(I91,lvl_1[],2,FALSE),"Нет") -> Общий расчет | D91: =IFERROR(VLOOKUP(Rule!J91,lvl_2[],2,FALSE),"Нет") -> Ци Мень | E91: =IFERROR(VLOOKUP(Rule!K91,lvl_3[],2,FALSE),"Нет") -> Анализ Дворца | F91: =IFERROR(INDEX(lvl_4[],MATCH(L91,lvl_4[ID],0),MATCH(TEXT(K91,"##0"),lvl_4[#Headers],0)),"Нет") -> Комбинации | G91: =IFERROR(INDEX(lvl_5[],MATCH(M91,lvl_5[ID],0),MATCH(_xlfn.CONCAT(TEXT(K91,"##0"),"_",TEXT(L91,"##0")),lvl_5[#Headers],0)),"Нет") -> Нет | H91: =IFERROR(INDEX(lvl_6[],MATCH(N91,lvl_6[ID],0),MATCH(_xlfn.CONCAT(K91,"_",L91,"_",M91),lvl_6[#Headers],0)),"Нет") -> Нет | I91: 1 | J91: 2 | K91: 2 | L91: 2 | M91: 0 | N91: 0 | O91: =COUNTIF($P$2:P91,P91) -> 88 | P91: =_xlfn.CONCAT(I91, J91, K91, IF(LEN(L91)=1,_xlfn.CONCAT(0,L91),L91), IF(LEN(M91)=1,_xlfn.CONCAT(0,M91),M91), IF(LEN(N91)=1,_xlfn.CONCAT(0,N91),N91)) -> 122020000 | Q91: =_xlfn.CONCAT(I91, J91, K91, IF(LEN(L91)=1,_xlfn.CONCAT(0,L91),L91), IF(LEN(M91)=1,_xlfn.CONCAT(0,M91),M91), IF(LEN(N91)=1,_xlfn.CONCAT(0,N91),N91), IF(LEN(O91)=1,_xlfn.CONCAT("000",O91),IF(LEN(O91)=2,_xlfn.CONCAT("00",O91),IF(LEN(O91)=3,_xlfn.CONCAT(0,O91),O91)))) -> 1220200000088 | R91: Наказание шести инструментов. Шесть инструментов ударяют и наказывают | S91: Максимально несчастливая ситуация. Все происходит под давлением. Не атаковать, не вступать в войну, не инициировать дела, иначе навлечешь на себя несчастья. В денежных делах затраты увеличатся вдвое и прибыль уменьшится вдвое | AW91: 2 | AY91: 庚 | BG91: -1 | BJ91: 1
A92: 1 | B92: =_xlfn.CONCAT(C92,". ", D92,". ", E92,". ", F92,". ", G92,". ", H92) -> Общий расчет. Ци Мень. Анализ Дворца. Комбинации. Нет. Нет | C92: =IFERROR(VLOOKUP(I92,lvl_1[],2,FALSE),"Нет") -> Общий расчет | D92: =IFERROR(VLOOKUP(Rule!J92,lvl_2[],2,FALSE),"Нет") -> Ци Мень | E92: =IFERROR(VLOOKUP(Rule!K92,lvl_3[],2,FALSE),"Нет") -> Анализ Дворца | F92: =IFERROR(INDEX(lvl_4[],MATCH(L92,lvl_4[ID],0),MATCH(TEXT(K92,"##0"),lvl_4[#Headers],0)),"Нет") -> Комбинации | G92: =IFERROR(INDEX(lvl_5[],MATCH(M92,lvl_5[ID],0),MATCH(_xlfn.CONCAT(TEXT(K92,"##0"),"_",TEXT(L92,"##0")),lvl_5[#Headers],0)),"Нет") -> Нет | H92: =IFERROR(INDEX(lvl_6[],MATCH(N92,lvl_6[ID],0),MATCH(_xlfn.CONCAT(K92,"_",L92,"_",M92),lvl_6[#Headers],0)),"Нет") -> Нет | I92: 1 | J92: 2 | K92: 2 | L92: 2 | M92: 0 | N92: 0 | O92: =COUNTIF($P$2:P92,P92) -> 89 | P92: =_xlfn.CONCAT(I92, J92, K92, IF(LEN(L92)=1,_xlfn.CONCAT(0,L92),L92), IF(LEN(M92)=1,_xlfn.CONCAT(0,M92),M92), IF(LEN(N92)=1,_xlfn.CONCAT(0,N92),N92)) -> 122020000 | Q92: =_xlfn.CONCAT(I92, J92, K92, IF(LEN(L92)=1,_xlfn.CONCAT(0,L92),L92), IF(LEN(M92)=1,_xlfn.CONCAT(0,M92),M92), IF(LEN(N92)=1,_xlfn.CONCAT(0,N92),N92), IF(LEN(O92)=1,_xlfn.CONCAT("000",O92),IF(LEN(O92)=2,_xlfn.CONCAT("00",O92),IF(LEN(O92)=3,_xlfn.CONCAT(0,O92),O92)))) -> 1220200000089 | R92: Наказание шести инструментов. Шесть инструментов ударяют и наказывают | S92: Максимально несчастливая ситуация. Все происходит под давлением. Не атаковать, не вступать в войну, не инициировать дела, иначе навлечешь на себя несчастья. В денежных делах затраты увеличатся вдвое и прибыль уменьшится вдвое | AW92: 8 | AY92: 癸 | BG92: -1 | BJ92: 1
A93: 1 | B93: =_xlfn.CONCAT(C93,". ", D93,". ", E93,". ", F93,". ", G93,". ", H93) -> Общий расчет. Ци Мень. Анализ Дворца. Комбинации. Нет. Нет | C93: =IFERROR(VLOOKUP(I93,lvl_1[],2,FALSE),"Нет") -> Общий расчет | D93: =IFERROR(VLOOKUP(Rule!J93,lvl_2[],2,FALSE),"Нет") -> Ци Мень | E93: =IFERROR(VLOOKUP(Rule!K93,lvl_3[],2,FALSE),"Нет") -> Анализ Дворца | F93: =IFERROR(INDEX(lvl_4[],MATCH(L93,lvl_4[ID],0),MATCH(TEXT(K93,"##0"),lvl_4[#Headers],0)),"Нет") -> Комбинации | G93: =IFERROR(INDEX(lvl_5[],MATCH(M93,lvl_5[ID],0),MATCH(_xlfn.CONCAT(TEXT(K93,"##0"),"_",TEXT(L93,"##0")),lvl_5[#Headers],0)),"Нет") -> Нет | H93: =IFERROR(INDEX(lvl_6[],MATCH(N93,lvl_6[ID],0),MATCH(_xlfn.CONCAT(K93,"_",L93,"_",M93),lvl_6[#Headers],0)),"Нет") -> Нет | I93: 1 | J93: 2 | K93: 2 | L93: 2 | M93: 0 | N93: 0 | O93: =COUNTIF($P$2:P93,P93) -> 90 | P93: =_xlfn.CONCAT(I93, J93, K93, IF(LEN(L93)=1,_xlfn.CONCAT(0,L93),L93), IF(LEN(M93)=1,_xlfn.CONCAT(0,M93),M93), IF(LEN(N93)=1,_xlfn.CONCAT(0,N93),N93)) -> 122020000 | Q93: =_xlfn.CONCAT(I93, J93, K93, IF(LEN(L93)=1,_xlfn.CONCAT(0,L93),L93), IF(LEN(M93)=1,_xlfn.CONCAT(0,M93),M93), IF(LEN(N93)=1,_xlfn.CONCAT(0,N93),N93), IF(LEN(O93)=1,_xlfn.CONCAT("000",O93),IF(LEN(O93)=2,_xlfn.CONCAT("00",O93),IF(LEN(O93)=3,_xlfn.CONCAT(0,O93),O93)))) -> 1220200000090 | R93: Наказание шести инструментов. Шесть инструментов ударяют и наказывают | S93: Максимально несчастливая ситуация. Все происходит под давлением. Не атаковать, не вступать в войну, не инициировать дела, иначе навлечешь на себя несчастья. В денежных делах затраты увеличатся вдвое и прибыль уменьшится вдвое | AW93: 8 | AY93: 己 | BG93: -1 | BJ93: 1
A94: 1 | B94: =_xlfn.CONCAT(C94,". ", D94,". ", E94,". ", F94,". ", G94,". ", H94) -> Общий расчет. Ци Мень. Анализ Дворца. Комбинации. Нет. Нет | C94: =IFERROR(VLOOKUP(I94,lvl_1[],2,FALSE),"Нет") -> Общий расчет | D94: =IFERROR(VLOOKUP(Rule!J94,lvl_2[],2,FALSE),"Нет") -> Ци Мень | E94: =IFERROR(VLOOKUP(Rule!K94,lvl_3[],2,FALSE),"Нет") -> Анализ Дворца | F94: =IFERROR(INDEX(lvl_4[],MATCH(L94,lvl_4[ID],0),MATCH(TEXT(K94,"##0"),lvl_4[#Headers],0)),"Нет") -> Комбинации | G94: =IFERROR(INDEX(lvl_5[],MATCH(M94,lvl_5[ID],0),MATCH(_xlfn.CONCAT(TEXT(K94,"##0"),"_",TEXT(L94,"##0")),lvl_5[#Headers],0)),"Нет") -> Нет | H94: =IFERROR(INDEX(lvl_6[],MATCH(N94,lvl_6[ID],0),MATCH(_xlfn.CONCAT(K94,"_",L94,"_",M94),lvl_6[#Headers],0)),"Нет") -> Нет | I94: 1 | J94: 2 | K94: 2 | L94: 2 | M94: 0 | N94: 0 | O94: =COUNTIF($P$2:P94,P94) -> 91 | P94: =_xlfn.CONCAT(I94, J94, K94, IF(LEN(L94)=1,_xlfn.CONCAT(0,L94),L94), IF(LEN(M94)=1,_xlfn.CONCAT(0,M94),M94), IF(LEN(N94)=1,_xlfn.CONCAT(0,N94),N94)) -> 122020000 | Q94: =_xlfn.CONCAT(I94, J94, K94, IF(LEN(L94)=1,_xlfn.CONCAT(0,L94),L94), IF(LEN(M94)=1,_xlfn.CONCAT(0,M94),M94), IF(LEN(N94)=1,_xlfn.CONCAT(0,N94),N94), IF(LEN(O94)=1,_xlfn.CONCAT("000",O94),IF(LEN(O94)=2,_xlfn.CONCAT("00",O94),IF(LEN(O94)=3,_xlfn.CONCAT(0,O94),O94)))) -> 1220200000091 | R94: Три мистика в могиле | S94: Во всех делах неудача, никакие замыслы не воплощаются. Беды не будет у того, кто не действует | AW94: 8 | AY94: 丁 | BG94: -1 | BJ94: 1 | BK94: 1
A95: 1 | B95: =_xlfn.CONCAT(C95,". ", D95,". ", E95,". ", F95,". ", G95,". ", H95) -> Общий расчет. Ци Мень. Анализ Дворца. Комбинации. Нет. Нет | C95: =IFERROR(VLOOKUP(I95,lvl_1[],2,FALSE),"Нет") -> Общий расчет | D95: =IFERROR(VLOOKUP(Rule!J95,lvl_2[],2,FALSE),"Нет") -> Ци Мень | E95: =IFERROR(VLOOKUP(Rule!K95,lvl_3[],2,FALSE),"Нет") -> Анализ Дворца | F95: =IFERROR(INDEX(lvl_4[],MATCH(L95,lvl_4[ID],0),MATCH(TEXT(K95,"##0"),lvl_4[#Headers],0)),"Нет") -> Комбинации | G95: =IFERROR(INDEX(lvl_5[],MATCH(M95,lvl_5[ID],0),MATCH(_xlfn.CONCAT(TEXT(K95,"##0"),"_",TEXT(L95,"##0")),lvl_5[#Headers],0)),"Нет") -> Нет | H95: =IFERROR(INDEX(lvl_6[],MATCH(N95,lvl_6[ID],0),MATCH(_xlfn.CONCAT(K95,"_",L95,"_",M95),lvl_6[#Headers],0)),"Нет") -> Нет | I95: 1 | J95: 2 | K95: 2 | L95: 2 | M95: 0 | N95: 0 | O95: =COUNTIF($P$2:P95,P95) -> 92 | P95: =_xlfn.CONCAT(I95, J95, K95, IF(LEN(L95)=1,_xlfn.CONCAT(0,L95),L95), IF(LEN(M95)=1,_xlfn.CONCAT(0,M95),M95), IF(LEN(N95)=1,_xlfn.CONCAT(0,N95),N95)) -> 122020000 | Q95: =_xlfn.CONCAT(I95, J95, K95, IF(LEN(L95)=1,_xlfn.CONCAT(0,L95),L95), IF(LEN(M95)=1,_xlfn.CONCAT(0,M95),M95), IF(LEN(N95)=1,_xlfn.CONCAT(0,N95),N95), IF(LEN(O95)=1,_xlfn.CONCAT("000",O95),IF(LEN(O95)=2,_xlfn.CONCAT("00",O95),IF(LEN(O95)=3,_xlfn.CONCAT(0,O95),O95)))) -> 1220200000092 | R95: Три мистика в могиле | S95: Во всех делах неудача, никакие замыслы не воплощаются. Беды не будет у того, кто не действует | AW95: 2 | AY95: 乙 | BG95: -1 | BJ95: 1 | BK95: 1
A96: 1 | B96: =_xlfn.CONCAT(C96,". ", D96,". ", E96,". ", F96,". ", G96,". ", H96) -> Общий расчет. Ци Мень. Анализ Дворца. Комбинации. Нет. Нет | C96: =IFERROR(VLOOKUP(I96,lvl_1[],2,FALSE),"Нет") -> Общий расчет | D96: =IFERROR(VLOOKUP(Rule!J96,lvl_2[],2,FALSE),"Нет") -> Ци Мень | E96: =IFERROR(VLOOKUP(Rule!K96,lvl_3[],2,FALSE),"Нет") -> Анализ Дворца | F96: =IFERROR(INDEX(lvl_4[],MATCH(L96,lvl_4[ID],0),MATCH(TEXT(K96,"##0"),lvl_4[#Headers],0)),"Нет") -> Комбинации | G96: =IFERROR(INDEX(lvl_5[],MATCH(M96,lvl_5[ID],0),MATCH(_xlfn.CONCAT(TEXT(K96,"##0"),"_",TEXT(L96,"##0")),lvl_5[#Headers],0)),"Нет") -> Нет | H96: =IFERROR(INDEX(lvl_6[],MATCH(N96,lvl_6[ID],0),MATCH(_xlfn.CONCAT(K96,"_",L96,"_",M96),lvl_6[#Headers],0)),"Нет") -> Нет | I96: 1 | J96: 2 | K96: 2 | L96: 2 | M96: 0 | N96: 0 | O96: =COUNTIF($P$2:P96,P96) -> 93 | P96: =_xlfn.CONCAT(I96, J96, K96, IF(LEN(L96)=1,_xlfn.CONCAT(0,L96),L96), IF(LEN(M96)=1,_xlfn.CONCAT(0,M96),M96), IF(LEN(N96)=1,_xlfn.CONCAT(0,N96),N96)) -> 122020000 | Q96: =_xlfn.CONCAT(I96, J96, K96, IF(LEN(L96)=1,_xlfn.CONCAT(0,L96),L96), IF(LEN(M96)=1,_xlfn.CONCAT(0,M96),M96), IF(LEN(N96)=1,_xlfn.CONCAT(0,N96),N96), IF(LEN(O96)=1,_xlfn.CONCAT("000",O96),IF(LEN(O96)=2,_xlfn.CONCAT("00",O96),IF(LEN(O96)=3,_xlfn.CONCAT(0,O96),O96)))) -> 1220200000093 | R96: Три мистика в могиле | S96: Во всех делах неудача, никакие замыслы не воплощаются. Беды не будет у того, кто не действует | AW96: 6 | AY96: 丙 | BG96: -1 | BJ96: 1 | BK96: 1
A97: 1 | B97: =_xlfn.CONCAT(C97,". ", D97,". ", E97,". ", F97,". ", G97,". ", H97) -> Общий расчет. Ци Мень. Анализ Дворца. Комбинации. Нет. Нет | C97: =IFERROR(VLOOKUP(I97,lvl_1[],2,FALSE),"Нет") -> Общий расчет | D97: =IFERROR(VLOOKUP(Rule!J97,lvl_2[],2,FALSE),"Нет") -> Ци Мень | E97: =IFERROR(VLOOKUP(Rule!K97,lvl_3[],2,FALSE),"Нет") -> Анализ Дворца | F97: =IFERROR(INDEX(lvl_4[],MATCH(L97,lvl_4[ID],0),MATCH(TEXT(K97,"##0"),lvl_4[#Headers],0)),"Нет") -> Комбинации | G97: =IFERROR(INDEX(lvl_5[],MATCH(M97,lvl_5[ID],0),MATCH(_xlfn.CONCAT(TEXT(K97,"##0"),"_",TEXT(L97,"##0")),lvl_5[#Headers],0)),"Нет") -> Нет | H97: =IFERROR(INDEX(lvl_6[],MATCH(N97,lvl_6[ID],0),MATCH(_xlfn.CONCAT(K97,"_",L97,"_",M97),lvl_6[#Headers],0)),"Нет") -> Нет | I97: 1 | J97: 2 | K97: 2 | L97: 2 | M97: 0 | N97: 0 | O97: =COUNTIF($P$2:P97,P97) -> 94 | P97: =_xlfn.CONCAT(I97, J97, K97, IF(LEN(L97)=1,_xlfn.CONCAT(0,L97),L97), IF(LEN(M97)=1,_xlfn.CONCAT(0,M97),M97), IF(LEN(N97)=1,_xlfn.CONCAT(0,N97),N97)) -> 122020000 | Q97: =_xlfn.CONCAT(I97, J97, K97, IF(LEN(L97)=1,_xlfn.CONCAT(0,L97),L97), IF(LEN(M97)=1,_xlfn.CONCAT(0,M97),M97), IF(LEN(N97)=1,_xlfn.CONCAT(0,N97),N97), IF(LEN(O97)=1,_xlfn.CONCAT("000",O97),IF(LEN(O97)=2,_xlfn.CONCAT("00",O97),IF(LEN(O97)=3,_xlfn.CONCAT(0,O97),O97)))) -> 1220200000094 | R97: Фу Инь восьми врат | S97: Люди пассивны. Сохранение тренда во всех процессах | AW97: 4 | BB97: 杜 | BG97: -1 | BJ97: 1
A98: 1 | B98: =_xlfn.CONCAT(C98,". ", D98,". ", E98,". ", F98,". ", G98,". ", H98) -> Общий расчет. Ци Мень. Анализ Дворца. Комбинации. Нет. Нет | C98: =IFERROR(VLOOKUP(I98,lvl_1[],2,FALSE),"Нет") -> Общий расчет | D98: =IFERROR(VLOOKUP(Rule!J98,lvl_2[],2,FALSE),"Нет") -> Ци Мень | E98: =IFERROR(VLOOKUP(Rule!K98,lvl_3[],2,FALSE),"Нет") -> Анализ Дворца | F98: =IFERROR(INDEX(lvl_4[],MATCH(L98,lvl_4[ID],0),MATCH(TEXT(K98,"##0"),lvl_4[#Headers],0)),"Нет") -> Комбинации | G98: =IFERROR(INDEX(lvl_5[],MATCH(M98,lvl_5[ID],0),MATCH(_xlfn.CONCAT(TEXT(K98,"##0"),"_",TEXT(L98,"##0")),lvl_5[#Headers],0)),"Нет") -> Нет | H98: =IFERROR(INDEX(lvl_6[],MATCH(N98,lvl_6[ID],0),MATCH(_xlfn.CONCAT(K98,"_",L98,"_",M98),lvl_6[#Headers],0)),"Нет") -> Нет | I98: 1 | J98: 2 | K98: 2 | L98: 2 | M98: 0 | N98: 0 | O98: =COUNTIF($P$2:P98,P98) -> 95 | P98: =_xlfn.CONCAT(I98, J98, K98, IF(LEN(L98)=1,_xlfn.CONCAT(0,L98),L98), IF(LEN(M98)=1,_xlfn.CONCAT(0,M98),M98), IF(LEN(N98)=1,_xlfn.CONCAT(0,N98),N98)) -> 122020000 | Q98: =_xlfn.CONCAT(I98, J98, K98, IF(LEN(L98)=1,_xlfn.CONCAT(0,L98),L98), IF(LEN(M98)=1,_xlfn.CONCAT(0,M98),M98), IF(LEN(N98)=1,_xlfn.CONCAT(0,N98),N98), IF(LEN(O98)=1,_xlfn.CONCAT("000",O98),IF(LEN(O98)=2,_xlfn.CONCAT("00",O98),IF(LEN(O98)=3,_xlfn.CONCAT(0,O98),O98)))) -> 1220200000095 | R98: Фу Инь восьми врат | S98: Люди пассивны. Сохранение тренда во всех процессах | AW98: 9 | BB98: 景 | BG98: -1 | BJ98: 1
A99: 1 | B99: =_xlfn.CONCAT(C99,". ", D99,". ", E99,". ", F99,". ", G99,". ", H99) -> Общий расчет. Ци Мень. Анализ Дворца. Комбинации. Нет. Нет | C99: =IFERROR(VLOOKUP(I99,lvl_1[],2,FALSE),"Нет") -> Общий расчет | D99: =IFERROR(VLOOKUP(Rule!J99,lvl_2[],2,FALSE),"Нет") -> Ци Мень | E99: =IFERROR(VLOOKUP(Rule!K99,lvl_3[],2,FALSE),"Нет") -> Анализ Дворца | F99: =IFERROR(INDEX(lvl_4[],MATCH(L99,lvl_4[ID],0),MATCH(TEXT(K99,"##0"),lvl_4[#Headers],0)),"Нет") -> Комбинации | G99: =IFERROR(INDEX(lvl_5[],MATCH(M99,lvl_5[ID],0),MATCH(_xlfn.CONCAT(TEXT(K99,"##0"),"_",TEXT(L99,"##0")),lvl_5[#Headers],0)),"Нет") -> Нет | H99: =IFERROR(INDEX(lvl_6[],MATCH(N99,lvl_6[ID],0),MATCH(_xlfn.CONCAT(K99,"_",L99,"_",M99),lvl_6[#Headers],0)),"Нет") -> Нет | I99: 1 | J99: 2 | K99: 2 | L99: 2 | M99: 0 | N99: 0 | O99: =COUNTIF($P$2:P99,P99) -> 96 | P99: =_xlfn.CONCAT(I99, J99, K99, IF(LEN(L99)=1,_xlfn.CONCAT(0,L99),L99), IF(LEN(M99)=1,_xlfn.CONCAT(0,M99),M99), IF(LEN(N99)=1,_xlfn.CONCAT(0,N99),N99)) -> 122020000 | Q99: =_xlfn.CONCAT(I99, J99, K99, IF(LEN(L99)=1,_xlfn.CONCAT(0,L99),L99), IF(LEN(M99)=1,_xlfn.CONCAT(0,M99),M99), IF(LEN(N99)=1,_xlfn.CONCAT(0,N99),N99), IF(LEN(O99)=1,_xlfn.CONCAT("000",O99),IF(LEN(O99)=2,_xlfn.CONCAT("00",O99),IF(LEN(O99)=3,_xlfn.CONCAT(0,O99),O99)))) -> 1220200000096 | R99: Фу Инь восьми врат | S99: Люди пассивны. Сохранение тренда во всех процессах | AW99: 2 | BB99: 死 | BG99: -1 | BJ99: 1
A100: 1 | B100: =_xlfn.CONCAT(C100,". ", D100,". ", E100,". ", F100,". ", G100,". ", H100) -> Общий расчет. Ци Мень. Анализ Дворца. Комбинации. Нет. Нет | C100: =IFERROR(VLOOKUP(I100,lvl_1[],2,FALSE),"Нет") -> Общий расчет | D100: =IFERROR(VLOOKUP(Rule!J100,lvl_2[],2,FALSE),"Нет") -> Ци Мень | E100: =IFERROR(VLOOKUP(Rule!K100,lvl_3[],2,FALSE),"Нет") -> Анализ Дворца | F100: =IFERROR(INDEX(lvl_4[],MATCH(L100,lvl_4[ID],0),MATCH(TEXT(K100,"##0"),lvl_4[#Headers],0)),"Нет") -> Комбинации | G100: =IFERROR(INDEX(lvl_5[],MATCH(M100,lvl_5[ID],0),MATCH(_xlfn.CONCAT(TEXT(K100,"##0"),"_",TEXT(L100,"##0")),lvl_5[#Headers],0)),"Нет") -> Нет | H100: =IFERROR(INDEX(lvl_6[],MATCH(N100,lvl_6[ID],0),MATCH(_xlfn.CONCAT(K100,"_",L100,"_",M100),lvl_6[#Headers],0)),"Нет") -> Нет | I100: 1 | J100: 2 | K100: 2 | L100: 2 | M100: 0 | N100: 0 | O100: =COUNTIF($P$2:P100,P100) -> 97 | P100: =_xlfn.CONCAT(I100, J100, K100, IF(LEN(L100)=1,_xlfn.CONCAT(0,L100),L100), IF(LEN(M100)=1,_xlfn.CONCAT(0,M100),M100), IF(LEN(N100)=1,_xlfn.CONCAT(0,N100),N100)) -> 122020000 | Q100: =_xlfn.CONCAT(I100, J100, K100, IF(LEN(L100)=1,_xlfn.CONCAT(0,L100),L100), IF(LEN(M100)=1,_xlfn.CONCAT(0,M100),M100), IF(LEN(N100)=1,_xlfn.CONCAT(0,N100),N100), IF(LEN(O100)=1,_xlfn.CONCAT("000",O100),IF(LEN(O100)=2,_xlfn.CONCAT("00",O100),IF(LEN(O100)=3,_xlfn.CONCAT(0,O100),O100)))) -> 1220200000097 | R100: Фу Инь восьми врат | S100: Люди пассивны. Сохранение тренда во всех процессах | AW100: 7 | BB100: 驚 | BG100: -1 | BJ100: 1
A101: 1 | B101: =_xlfn.CONCAT(C101,". ", D101,". ", E101,". ", F101,". ", G101,". ", H101) -> Общий расчет. Ци Мень. Анализ Дворца. Комбинации. Нет. Нет | C101: =IFERROR(VLOOKUP(I101,lvl_1[],2,FALSE),"Нет") -> Общий расчет | D101: =IFERROR(VLOOKUP(Rule!J101,lvl_2[],2,FALSE),"Нет") -> Ци Мень | E101: =IFERROR(VLOOKUP(Rule!K101,lvl_3[],2,FALSE),"Нет") -> Анализ Дворца | F101: =IFERROR(INDEX(lvl_4[],MATCH(L101,lvl_4[ID],0),MATCH(TEXT(K101,"##0"),lvl_4[#Headers],0)),"Нет") -> Комбинации | G101: =IFERROR(INDEX(lvl_5[],MATCH(M101,lvl_5[ID],0),MATCH(_xlfn.CONCAT(TEXT(K101,"##0"),"_",TEXT(L101,"##0")),lvl_5[#Headers],0)),"Нет") -> Нет | H101: =IFERROR(INDEX(lvl_6[],MATCH(N101,lvl_6[ID],0),MATCH(_xlfn.CONCAT(K101,"_",L101,"_",M101),lvl_6[#Headers],0)),"Нет") -> Нет | I101: 1 | J101: 2 | K101: 2 | L101: 2 | M101: 0 | N101: 0 | O101: =COUNTIF($P$2:P101,P101) -> 98 | P101: =_xlfn.CONCAT(I101, J101, K101, IF(LEN(L101)=1,_xlfn.CONCAT(0,L101),L101), IF(LEN(M101)=1,_xlfn.CONCAT(0,M101),M101), IF(LEN(N101)=1,_xlfn.CONCAT(0,N101),N101)) -> 122020000 | Q101: =_xlfn.CONCAT(I101, J101, K101, IF(LEN(L101)=1,_xlfn.CONCAT(0,L101),L101), IF(LEN(M101)=1,_xlfn.CONCAT(0,M101),M101), IF(LEN(N101)=1,_xlfn.CONCAT(0,N101),N101), IF(LEN(O101)=1,_xlfn.CONCAT("000",O101),IF(LEN(O101)=2,_xlfn.CONCAT("00",O101),IF(LEN(O101)=3,_xlfn.CONCAT(0,O101),O101)))) -> 1220200000098 | R101: Фу Инь восьми врат | S101: Люди пассивны. Сохранение тренда во всех процессах | AW101: 6 | BB101: 開 | BG101: -1 | BJ101: 1
A102: 1 | B102: =_xlfn.CONCAT(C102,". ", D102,". ", E102,". ", F102,". ", G102,". ", H102) -> Общий расчет. Ци Мень. Анализ Дворца. Комбинации. Нет. Нет | C102: =IFERROR(VLOOKUP(I102,lvl_1[],2,FALSE),"Нет") -> Общий расчет | D102: =IFERROR(VLOOKUP(Rule!J102,lvl_2[],2,FALSE),"Нет") -> Ци Мень | E102: =IFERROR(VLOOKUP(Rule!K102,lvl_3[],2,FALSE),"Нет") -> Анализ Дворца | F102: =IFERROR(INDEX(lvl_4[],MATCH(L102,lvl_4[ID],0),MATCH(TEXT(K102,"##0"),lvl_4[#Headers],0)),"Нет") -> Комбинации | G102: =IFERROR(INDEX(lvl_5[],MATCH(M102,lvl_5[ID],0),MATCH(_xlfn.CONCAT(TEXT(K102,"##0"),"_",TEXT(L102,"##0")),lvl_5[#Headers],0)),"Нет") -> Нет | H102: =IFERROR(INDEX(lvl_6[],MATCH(N102,lvl_6[ID],0),MATCH(_xlfn.CONCAT(K102,"_",L102,"_",M102),lvl_6[#Headers],0)),"Нет") -> Нет | I102: 1 | J102: 2 | K102: 2 | L102: 2 | M102: 0 | N102: 0 | O102: =COUNTIF($P$2:P102,P102) -> 99 | P102: =_xlfn.CONCAT(I102, J102, K102, IF(LEN(L102)=1,_xlfn.CONCAT(0,L102),L102), IF(LEN(M102)=1,_xlfn.CONCAT(0,M102),M102), IF(LEN(N102)=1,_xlfn.CONCAT(0,N102),N102)) -> 122020000 | Q102: =_xlfn.CONCAT(I102, J102, K102, IF(LEN(L102)=1,_xlfn.CONCAT(0,L102),L102), IF(LEN(M102)=1,_xlfn.CONCAT(0,M102),M102), IF(LEN(N102)=1,_xlfn.CONCAT(0,N102),N102), IF(LEN(O102)=1,_xlfn.CONCAT("000",O102),IF(LEN(O102)=2,_xlfn.CONCAT("00",O102),IF(LEN(O102)=3,_xlfn.CONCAT(0,O102),O102)))) -> 1220200000099 | R102: Фу Инь восьми врат | S102: Люди пассивны. Сохранение тренда во всех процессах | AW102: 1 | BB102: 休 | BG102: -1 | BJ102: 1
A103: 1 | B103: =_xlfn.CONCAT(C103,". ", D103,". ", E103,". ", F103,". ", G103,". ", H103) -> Общий расчет. Ци Мень. Анализ Дворца. Комбинации. Нет. Нет | C103: =IFERROR(VLOOKUP(I103,lvl_1[],2,FALSE),"Нет") -> Общий расчет | D103: =IFERROR(VLOOKUP(Rule!J103,lvl_2[],2,FALSE),"Нет") -> Ци Мень | E103: =IFERROR(VLOOKUP(Rule!K103,lvl_3[],2,FALSE),"Нет") -> Анализ Дворца | F103: =IFERROR(INDEX(lvl_4[],MATCH(L103,lvl_4[ID],0),MATCH(TEXT(K103,"##0"),lvl_4[#Headers],0)),"Нет") -> Комбинации | G103: =IFERROR(INDEX(lvl_5[],MATCH(M103,lvl_5[ID],0),MATCH(_xlfn.CONCAT(TEXT(K103,"##0"),"_",TEXT(L103,"##0")),lvl_5[#Headers],0)),"Нет") -> Нет | H103: =IFERROR(INDEX(lvl_6[],MATCH(N103,lvl_6[ID],0),MATCH(_xlfn.CONCAT(K103,"_",L103,"_",M103),lvl_6[#Headers],0)),"Нет") -> Нет | I103: 1 | J103: 2 | K103: 2 | L103: 2 | M103: 0 | N103: 0 | O103: =COUNTIF($P$2:P103,P103) -> 100 | P103: =_xlfn.CONCAT(I103, J103, K103, IF(LEN(L103)=1,_xlfn.CONCAT(0,L103),L103), IF(LEN(M103)=1,_xlfn.CONCAT(0,M103),M103), IF(LEN(N103)=1,_xlfn.CONCAT(0,N103),N103)) -> 122020000 | Q103: =_xlfn.CONCAT(I103, J103, K103, IF(LEN(L103)=1,_xlfn.CONCAT(0,L103),L103), IF(LEN(M103)=1,_xlfn.CONCAT(0,M103),M103), IF(LEN(N103)=1,_xlfn.CONCAT(0,N103),N103), IF(LEN(O103)=1,_xlfn.CONCAT("000",O103),IF(LEN(O103)=2,_xlfn.CONCAT("00",O103),IF(LEN(O103)=3,_xlfn.CONCAT(0,O103),O103)))) -> 1220200000100 | R103: Фу Инь восьми врат | S103: Люди пассивны. Сохранение тренда во всех процессах | AW103: 8 | BB103: 生 | BG103: -1 | BJ103: 1
A104: 1 | B104: =_xlfn.CONCAT(C104,". ", D104,". ", E104,". ", F104,". ", G104,". ", H104) -> Общий расчет. Ци Мень. Анализ Дворца. Комбинации. Нет. Нет | C104: =IFERROR(VLOOKUP(I104,lvl_1[],2,FALSE),"Нет") -> Общий расчет | D104: =IFERROR(VLOOKUP(Rule!J104,lvl_2[],2,FALSE),"Нет") -> Ци Мень | E104: =IFERROR(VLOOKUP(Rule!K104,lvl_3[],2,FALSE),"Нет") -> Анализ Дворца | F104: =IFERROR(INDEX(lvl_4[],MATCH(L104,lvl_4[ID],0),MATCH(TEXT(K104,"##0"),lvl_4[#Headers],0)),"Нет") -> Комбинации | G104: =IFERROR(INDEX(lvl_5[],MATCH(M104,lvl_5[ID],0),MATCH(_xlfn.CONCAT(TEXT(K104,"##0"),"_",TEXT(L104,"##0")),lvl_5[#Headers],0)),"Нет") -> Нет | H104: =IFERROR(INDEX(lvl_6[],MATCH(N104,lvl_6[ID],0),MATCH(_xlfn.CONCAT(K104,"_",L104,"_",M104),lvl_6[#Headers],0)),"Нет") -> Нет | I104: 1 | J104: 2 | K104: 2 | L104: 2 | M104: 0 | N104: 0 | O104: =COUNTIF($P$2:P104,P104) -> 101 | P104: =_xlfn.CONCAT(I104, J104, K104, IF(LEN(L104)=1,_xlfn.CONCAT(0,L104),L104), IF(LEN(M104)=1,_xlfn.CONCAT(0,M104),M104), IF(LEN(N104)=1,_xlfn.CONCAT(0,N104),N104)) -> 122020000 | Q104: =_xlfn.CONCAT(I104, J104, K104, IF(LEN(L104)=1,_xlfn.CONCAT(0,L104),L104), IF(LEN(M104)=1,_xlfn.CONCAT(0,M104),M104), IF(LEN(N104)=1,_xlfn.CONCAT(0,N104),N104), IF(LEN(O104)=1,_xlfn.CONCAT("000",O104),IF(LEN(O104)=2,_xlfn.CONCAT("00",O104),IF(LEN(O104)=3,_xlfn.CONCAT(0,O104),O104)))) -> 1220200000101 | R104: Фу Инь восьми врат | S104: Люди пассивны. Сохранение тренда во всех процессах | AW104: 3 | BB104: 傷 | BG104: -1 | BJ104: 1
A105: 1 | B105: =_xlfn.CONCAT(C105,". ", D105,". ", E105,". ", F105,". ", G105,". ", H105) -> Общий расчет. Ци Мень. Анализ Дворца. Комбинации. Нет. Нет | C105: =IFERROR(VLOOKUP(I105,lvl_1[],2,FALSE),"Нет") -> Общий расчет | D105: =IFERROR(VLOOKUP(Rule!J105,lvl_2[],2,FALSE),"Нет") -> Ци Мень | E105: =IFERROR(VLOOKUP(Rule!K105,lvl_3[],2,FALSE),"Нет") -> Анализ Дворца | F105: =IFERROR(INDEX(lvl_4[],MATCH(L105,lvl_4[ID],0),MATCH(TEXT(K105,"##0"),lvl_4[#Headers],0)),"Нет") -> Комбинации | G105: =IFERROR(INDEX(lvl_5[],MATCH(M105,lvl_5[ID],0),MATCH(_xlfn.CONCAT(TEXT(K105,"##0"),"_",TEXT(L105,"##0")),lvl_5[#Headers],0)),"Нет") -> Нет | H105: =IFERROR(INDEX(lvl_6[],MATCH(N105,lvl_6[ID],0),MATCH(_xlfn.CONCAT(K105,"_",L105,"_",M105),lvl_6[#Headers],0)),"Нет") -> Нет | I105: 1 | J105: 2 | K105: 2 | L105: 2 | M105: 0 | N105: 0 | O105: =COUNTIF($P$2:P105,P105) -> 102 | P105: =_xlfn.CONCAT(I105, J105, K105, IF(LEN(L105)=1,_xlfn.CONCAT(0,L105),L105), IF(LEN(M105)=1,_xlfn.CONCAT(0,M105),M105), IF(LEN(N105)=1,_xlfn.CONCAT(0,N105),N105)) -> 122020000 | Q105: =_xlfn.CONCAT(I105, J105, K105, IF(LEN(L105)=1,_xlfn.CONCAT(0,L105),L105), IF(LEN(M105)=1,_xlfn.CONCAT(0,M105),M105), IF(LEN(N105)=1,_xlfn.CONCAT(0,N105),N105), IF(LEN(O105)=1,_xlfn.CONCAT("000",O105),IF(LEN(O105)=2,_xlfn.CONCAT("00",O105),IF(LEN(O105)=3,_xlfn.CONCAT(0,O105),O105)))) -> 1220200000102 | R105: Фу Инь звездный | S105: Траурные одежды, потери родственников (на практике – застой в мыслях) | AW105: 4 | BD105: 辅 | BG105: -1 | BJ105: 1
A106: 1 | B106: =_xlfn.CONCAT(C106,". ", D106,". ", E106,". ", F106,". ", G106,". ", H106) -> Общий расчет. Ци Мень. Анализ Дворца. Комбинации. Нет. Нет | C106: =IFERROR(VLOOKUP(I106,lvl_1[],2,FALSE),"Нет") -> Общий расчет | D106: =IFERROR(VLOOKUP(Rule!J106,lvl_2[],2,FALSE),"Нет") -> Ци Мень | E106: =IFERROR(VLOOKUP(Rule!K106,lvl_3[],2,FALSE),"Нет") -> Анализ Дворца | F106: =IFERROR(INDEX(lvl_4[],MATCH(L106,lvl_4[ID],0),MATCH(TEXT(K106,"##0"),lvl_4[#Headers],0)),"Нет") -> Комбинации | G106: =IFERROR(INDEX(lvl_5[],MATCH(M106,lvl_5[ID],0),MATCH(_xlfn.CONCAT(TEXT(K106,"##0"),"_",TEXT(L106,"##0")),lvl_5[#Headers],0)),"Нет") -> Нет | H106: =IFERROR(INDEX(lvl_6[],MATCH(N106,lvl_6[ID],0),MATCH(_xlfn.CONCAT(K106,"_",L106,"_",M106),lvl_6[#Headers],0)),"Нет") -> Нет | I106: 1 | J106: 2 | K106: 2 | L106: 2 | M106: 0 | N106: 0 | O106: =COUNTIF($P$2:P106,P106) -> 103 | P106: =_xlfn.CONCAT(I106, J106, K106, IF(LEN(L106)=1,_xlfn.CONCAT(0,L106),L106), IF(LEN(M106)=1,_xlfn.CONCAT(0,M106),M106), IF(LEN(N106)=1,_xlfn.CONCAT(0,N106),N106)) -> 122020000 | Q106: =_xlfn.CONCAT(I106, J106, K106, IF(LEN(L106)=1,_xlfn.CONCAT(0,L106),L106), IF(LEN(M106)=1,_xlfn.CONCAT(0,M106),M106), IF(LEN(N106)=1,_xlfn.CONCAT(0,N106),N106), IF(LEN(O106)=1,_xlfn.CONCAT("000",O106),IF(LEN(O106)=2,_xlfn.CONCAT("00",O106),IF(LEN(O106)=3,_xlfn.CONCAT(0,O106),O106)))) -> 1220200000103 | R106: Фу Инь звездный | S106: Траурные одежды, потери родственников (на практике – застой в мыслях) | AW106: 9 | BD106: 英 | BG106: -1 | BJ106: 1
A107: 1 | B107: =_xlfn.CONCAT(C107,". ", D107,". ", E107,". ", F107,". ", G107,". ", H107) -> Общий расчет. Ци Мень. Анализ Дворца. Комбинации. Нет. Нет | C107: =IFERROR(VLOOKUP(I107,lvl_1[],2,FALSE),"Нет") -> Общий расчет | D107: =IFERROR(VLOOKUP(Rule!J107,lvl_2[],2,FALSE),"Нет") -> Ци Мень | E107: =IFERROR(VLOOKUP(Rule!K107,lvl_3[],2,FALSE),"Нет") -> Анализ Дворца | F107: =IFERROR(INDEX(lvl_4[],MATCH(L107,lvl_4[ID],0),MATCH(TEXT(K107,"##0"),lvl_4[#Headers],0)),"Нет") -> Комбинации | G107: =IFERROR(INDEX(lvl_5[],MATCH(M107,lvl_5[ID],0),MATCH(_xlfn.CONCAT(TEXT(K107,"##0"),"_",TEXT(L107,"##0")),lvl_5[#Headers],0)),"Нет") -> Нет | H107: =IFERROR(INDEX(lvl_6[],MATCH(N107,lvl_6[ID],0),MATCH(_xlfn.CONCAT(K107,"_",L107,"_",M107),lvl_6[#Headers],0)),"Нет") -> Нет | I107: 1 | J107: 2 | K107: 2 | L107: 2 | M107: 0 | N107: 0 | O107: =COUNTIF($P$2:P107,P107) -> 104 | P107: =_xlfn.CONCAT(I107, J107, K107, IF(LEN(L107)=1,_xlfn.CONCAT(0,L107),L107), IF(LEN(M107)=1,_xlfn.CONCAT(0,M107),M107), IF(LEN(N107)=1,_xlfn.CONCAT(0,N107),N107)) -> 122020000 | Q107: =_xlfn.CONCAT(I107, J107, K107, IF(LEN(L107)=1,_xlfn.CONCAT(0,L107),L107), IF(LEN(M107)=1,_xlfn.CONCAT(0,M107),M107), IF(LEN(N107)=1,_xlfn.CONCAT(0,N107),N107), IF(LEN(O107)=1,_xlfn.CONCAT("000",O107),IF(LEN(O107)=2,_xlfn.CONCAT("00",O107),IF(LEN(O107)=3,_xlfn.CONCAT(0,O107),O107)))) -> 1220200000104 | R107: Фу Инь звездный | S107: Траурные одежды, потери родственников (на практике – застой в мыслях) | AW107: 2 | BD107: 芮 | BG107: -1 | BJ107: 1
A108: 1 | B108: =_xlfn.CONCAT(C108,". ", D108,". ", E108,". ", F108,". ", G108,". ", H108) -> Общий расчет. Ци Мень. Анализ Дворца. Комбинации. Нет. Нет | C108: =IFERROR(VLOOKUP(I108,lvl_1[],2,FALSE),"Нет") -> Общий расчет | D108: =IFERROR(VLOOKUP(Rule!J108,lvl_2[],2,FALSE),"Нет") -> Ци Мень | E108: =IFERROR(VLOOKUP(Rule!K108,lvl_3[],2,FALSE),"Нет") -> Анализ Дворца | F108: =IFERROR(INDEX(lvl_4[],MATCH(L108,lvl_4[ID],0),MATCH(TEXT(K108,"##0"),lvl_4[#Headers],0)),"Нет") -> Комбинации | G108: =IFERROR(INDEX(lvl_5[],MATCH(M108,lvl_5[ID],0),MATCH(_xlfn.CONCAT(TEXT(K108,"##0"),"_",TEXT(L108,"##0")),lvl_5[#Headers],0)),"Нет") -> Нет | H108: =IFERROR(INDEX(lvl_6[],MATCH(N108,lvl_6[ID],0),MATCH(_xlfn.CONCAT(K108,"_",L108,"_",M108),lvl_6[#Headers],0)),"Нет") -> Нет | I108: 1 | J108: 2 | K108: 2 | L108: 2 | M108: 0 | N108: 0 | O108: =COUNTIF($P$2:P108,P108) -> 105 | P108: =_xlfn.CONCAT(I108, J108, K108, IF(LEN(L108)=1,_xlfn.CONCAT(0,L108),L108), IF(LEN(M108)=1,_xlfn.CONCAT(0,M108),M108), IF(LEN(N108)=1,_xlfn.CONCAT(0,N108),N108)) -> 122020000 | Q108: =_xlfn.CONCAT(I108, J108, K108, IF(LEN(L108)=1,_xlfn.CONCAT(0,L108),L108), IF(LEN(M108)=1,_xlfn.CONCAT(0,M108),M108), IF(LEN(N108)=1,_xlfn.CONCAT(0,N108),N108), IF(LEN(O108)=1,_xlfn.CONCAT("000",O108),IF(LEN(O108)=2,_xlfn.CONCAT("00",O108),IF(LEN(O108)=3,_xlfn.CONCAT(0,O108),O108)))) -> 1220200000105 | R108: Фу Инь звездный | S108: Траурные одежды, потери родственников (на практике – застой в мыслях) | AW108: 7 | BD108: 柱 | BG108: -1 | BJ108: 1
A109: 1 | B109: =_xlfn.CONCAT(C109,". ", D109,". ", E109,". ", F109,". ", G109,". ", H109) -> Общий расчет. Ци Мень. Анализ Дворца. Комбинации. Нет. Нет | C109: =IFERROR(VLOOKUP(I109,lvl_1[],2,FALSE),"Нет") -> Общий расчет | D109: =IFERROR(VLOOKUP(Rule!J109,lvl_2[],2,FALSE),"Нет") -> Ци Мень | E109: =IFERROR(VLOOKUP(Rule!K109,lvl_3[],2,FALSE),"Нет") -> Анализ Дворца | F109: =IFERROR(INDEX(lvl_4[],MATCH(L109,lvl_4[ID],0),MATCH(TEXT(K109,"##0"),lvl_4[#Headers],0)),"Нет") -> Комбинации | G109: =IFERROR(INDEX(lvl_5[],MATCH(M109,lvl_5[ID],0),MATCH(_xlfn.CONCAT(TEXT(K109,"##0"),"_",TEXT(L109,"##0")),lvl_5[#Headers],0)),"Нет") -> Нет | H109: =IFERROR(INDEX(lvl_6[],MATCH(N109,lvl_6[ID],0),MATCH(_xlfn.CONCAT(K109,"_",L109,"_",M109),lvl_6[#Headers],0)),"Нет") -> Нет | I109: 1 | J109: 2 | K109: 2 | L109: 2 | M109: 0 | N109: 0 | O109: =COUNTIF($P$2:P109,P109) -> 106 | P109: =_xlfn.CONCAT(I109, J109, K109, IF(LEN(L109)=1,_xlfn.CONCAT(0,L109),L109), IF(LEN(M109)=1,_xlfn.CONCAT(0,M109),M109), IF(LEN(N109)=1,_xlfn.CONCAT(0,N109),N109)) -> 122020000 | Q109: =_xlfn.CONCAT(I109, J109, K109, IF(LEN(L109)=1,_xlfn.CONCAT(0,L109),L109), IF(LEN(M109)=1,_xlfn.CONCAT(0,M109),M109), IF(LEN(N109)=1,_xlfn.CONCAT(0,N109),N109), IF(LEN(O109)=1,_xlfn.CONCAT("000",O109),IF(LEN(O109)=2,_xlfn.CONCAT("00",O109),IF(LEN(O109)=3,_xlfn.CONCAT(0,O109),O109)))) -> 1220200000106 | R109: Фу Инь звездный | S109: Траурные одежды, потери родственников (на практике – застой в мыслях) | AW109: 6 | BD109: 心 | BG109: -1 | BJ109: 1
A110: 1 | B110: =_xlfn.CONCAT(C110,". ", D110,". ", E110,". ", F110,". ", G110,". ", H110) -> Общий расчет. Ци Мень. Анализ Дворца. Комбинации. Нет. Нет | C110: =IFERROR(VLOOKUP(I110,lvl_1[],2,FALSE),"Нет") -> Общий расчет | D110: =IFERROR(VLOOKUP(Rule!J110,lvl_2[],2,FALSE),"Нет") -> Ци Мень | E110: =IFERROR(VLOOKUP(Rule!K110,lvl_3[],2,FALSE),"Нет") -> Анализ Дворца | F110: =IFERROR(INDEX(lvl_4[],MATCH(L110,lvl_4[ID],0),MATCH(TEXT(K110,"##0"),lvl_4[#Headers],0)),"Нет") -> Комбинации | G110: =IFERROR(INDEX(lvl_5[],MATCH(M110,lvl_5[ID],0),MATCH(_xlfn.CONCAT(TEXT(K110,"##0"),"_",TEXT(L110,"##0")),lvl_5[#Headers],0)),"Нет") -> Нет | H110: =IFERROR(INDEX(lvl_6[],MATCH(N110,lvl_6[ID],0),MATCH(_xlfn.CONCAT(K110,"_",L110,"_",M110),lvl_6[#Headers],0)),"Нет") -> Нет | I110: 1 | J110: 2 | K110: 2 | L110: 2 | M110: 0 | N110: 0 | O110: =COUNTIF($P$2:P110,P110) -> 107 | P110: =_xlfn.CONCAT(I110, J110, K110, IF(LEN(L110)=1,_xlfn.CONCAT(0,L110),L110), IF(LEN(M110)=1,_xlfn.CONCAT(0,M110),M110), IF(LEN(N110)=1,_xlfn.CONCAT(0,N110),N110)) -> 122020000 | Q110: =_xlfn.CONCAT(I110, J110, K110, IF(LEN(L110)=1,_xlfn.CONCAT(0,L110),L110), IF(LEN(M110)=1,_xlfn.CONCAT(0,M110),M110), IF(LEN(N110)=1,_xlfn.CONCAT(0,N110),N110), IF(LEN(O110)=1,_xlfn.CONCAT("000",O110),IF(LEN(O110)=2,_xlfn.CONCAT("00",O110),IF(LEN(O110)=3,_xlfn.CONCAT(0,O110),O110)))) -> 1220200000107 | R110: Фу Инь звездный | S110: Траурные одежды, потери родственников (на практике – застой в мыслях) | AW110: 1 | BD110: 蓬 | BG110: -1 | BJ110: 1
A111: 1 | B111: =_xlfn.CONCAT(C111,". ", D111,". ", E111,". ", F111,". ", G111,". ", H111) -> Общий расчет. Ци Мень. Анализ Дворца. Комбинации. Нет. Нет | C111: =IFERROR(VLOOKUP(I111,lvl_1[],2,FALSE),"Нет") -> Общий расчет | D111: =IFERROR(VLOOKUP(Rule!J111,lvl_2[],2,FALSE),"Нет") -> Ци Мень | E111: =IFERROR(VLOOKUP(Rule!K111,lvl_3[],2,FALSE),"Нет") -> Анализ Дворца | F111: =IFERROR(INDEX(lvl_4[],MATCH(L111,lvl_4[ID],0),MATCH(TEXT(K111,"##0"),lvl_4[#Headers],0)),"Нет") -> Комбинации | G111: =IFERROR(INDEX(lvl_5[],MATCH(M111,lvl_5[ID],0),MATCH(_xlfn.CONCAT(TEXT(K111,"##0"),"_",TEXT(L111,"##0")),lvl_5[#Headers],0)),"Нет") -> Нет | H111: =IFERROR(INDEX(lvl_6[],MATCH(N111,lvl_6[ID],0),MATCH(_xlfn.CONCAT(K111,"_",L111,"_",M111),lvl_6[#Headers],0)),"Нет") -> Нет | I111: 1 | J111: 2 | K111: 2 | L111: 2 | M111: 0 | N111: 0 | O111: =COUNTIF($P$2:P111,P111) -> 108 | P111: =_xlfn.CONCAT(I111, J111, K111, IF(LEN(L111)=1,_xlfn.CONCAT(0,L111),L111), IF(LEN(M111)=1,_xlfn.CONCAT(0,M111),M111), IF(LEN(N111)=1,_xlfn.CONCAT(0,N111),N111)) -> 122020000 | Q111: =_xlfn.CONCAT(I111, J111, K111, IF(LEN(L111)=1,_xlfn.CONCAT(0,L111),L111), IF(LEN(M111)=1,_xlfn.CONCAT(0,M111),M111), IF(LEN(N111)=1,_xlfn.CONCAT(0,N111),N111), IF(LEN(O111)=1,_xlfn.CONCAT("000",O111),IF(LEN(O111)=2,_xlfn.CONCAT("00",O111),IF(LEN(O111)=3,_xlfn.CONCAT(0,O111),O111)))) -> 1220200000108 | R111: Фу Инь звездный | S111: Траурные одежды, потери родственников (на практике – застой в мыслях) | AW111: 8 | BD111: 任 | BG111: -1 | BJ111: 1
A112: 1 | B112: =_xlfn.CONCAT(C112,". ", D112,". ", E112,". ", F112,". ", G112,". ", H112) -> Общий расчет. Ци Мень. Анализ Дворца. Комбинации. Нет. Нет | C112: =IFERROR(VLOOKUP(I112,lvl_1[],2,FALSE),"Нет") -> Общий расчет | D112: =IFERROR(VLOOKUP(Rule!J112,lvl_2[],2,FALSE),"Нет") -> Ци Мень | E112: =IFERROR(VLOOKUP(Rule!K112,lvl_3[],2,FALSE),"Нет") -> Анализ Дворца | F112: =IFERROR(INDEX(lvl_4[],MATCH(L112,lvl_4[ID],0),MATCH(TEXT(K112,"##0"),lvl_4[#Headers],0)),"Нет") -> Комбинации | G112: =IFERROR(INDEX(lvl_5[],MATCH(M112,lvl_5[ID],0),MATCH(_xlfn.CONCAT(TEXT(K112,"##0"),"_",TEXT(L112,"##0")),lvl_5[#Headers],0)),"Нет") -> Нет | H112: =IFERROR(INDEX(lvl_6[],MATCH(N112,lvl_6[ID],0),MATCH(_xlfn.CONCAT(K112,"_",L112,"_",M112),lvl_6[#Headers],0)),"Нет") -> Нет | I112: 1 | J112: 2 | K112: 2 | L112: 2 | M112: 0 | N112: 0 | O112: =COUNTIF($P$2:P112,P112) -> 109 | P112: =_xlfn.CONCAT(I112, J112, K112, IF(LEN(L112)=1,_xlfn.CONCAT(0,L112),L112), IF(LEN(M112)=1,_xlfn.CONCAT(0,M112),M112), IF(LEN(N112)=1,_xlfn.CONCAT(0,N112),N112)) -> 122020000 | Q112: =_xlfn.CONCAT(I112, J112, K112, IF(LEN(L112)=1,_xlfn.CONCAT(0,L112),L112), IF(LEN(M112)=1,_xlfn.CONCAT(0,M112),M112), IF(LEN(N112)=1,_xlfn.CONCAT(0,N112),N112), IF(LEN(O112)=1,_xlfn.CONCAT("000",O112),IF(LEN(O112)=2,_xlfn.CONCAT("00",O112),IF(LEN(O112)=3,_xlfn.CONCAT(0,O112),O112)))) -> 1220200000109 | R112: Фу Инь звездный | S112: Траурные одежды, потери родственников (на практике – застой в мыслях) | AW112: 3 | BD112: 冲 | BG112: -1 | BJ112: 1
A113: 1 | B113: =_xlfn.CONCAT(C113,". ", D113,". ", E113,". ", F113,". ", G113,". ", H113) -> Общий расчет. Ци Мень. Анализ Дворца. Комбинации. Нет. Нет | C113: =IFERROR(VLOOKUP(I113,lvl_1[],2,FALSE),"Нет") -> Общий расчет | D113: =IFERROR(VLOOKUP(Rule!J113,lvl_2[],2,FALSE),"Нет") -> Ци Мень | E113: =IFERROR(VLOOKUP(Rule!K113,lvl_3[],2,FALSE),"Нет") -> Анализ Дворца | F113: =IFERROR(INDEX(lvl_4[],MATCH(L113,lvl_4[ID],0),MATCH(TEXT(K113,"##0"),lvl_4[#Headers],0)),"Нет") -> Комбинации | G113: =IFERROR(INDEX(lvl_5[],MATCH(M113,lvl_5[ID],0),MATCH(_xlfn.CONCAT(TEXT(K113,"##0"),"_",TEXT(L113,"##0")),lvl_5[#Headers],0)),"Нет") -> Нет | H113: =IFERROR(INDEX(lvl_6[],MATCH(N113,lvl_6[ID],0),MATCH(_xlfn.CONCAT(K113,"_",L113,"_",M113),lvl_6[#Headers],0)),"Нет") -> Нет | I113: 1 | J113: 2 | K113: 2 | L113: 2 | M113: 0 | N113: 0 | O113: =COUNTIF($P$2:P113,P113) -> 110 | P113: =_xlfn.CONCAT(I113, J113, K113, IF(LEN(L113)=1,_xlfn.CONCAT(0,L113),L113), IF(LEN(M113)=1,_xlfn.CONCAT(0,M113),M113), IF(LEN(N113)=1,_xlfn.CONCAT(0,N113),N113)) -> 122020000 | Q113: =_xlfn.CONCAT(I113, J113, K113, IF(LEN(L113)=1,_xlfn.CONCAT(0,L113),L113), IF(LEN(M113)=1,_xlfn.CONCAT(0,M113),M113), IF(LEN(N113)=1,_xlfn.CONCAT(0,N113),N113), IF(LEN(O113)=1,_xlfn.CONCAT("000",O113),IF(LEN(O113)=2,_xlfn.CONCAT("00",O113),IF(LEN(O113)=3,_xlfn.CONCAT(0,O113),O113)))) -> 1220200000110 | R113: Фу Инь генеральский | S113: Все происходит очень медленно. Сохранение тренда | AY113: 甲 | BA113: 甲 | BG113: -1 | BJ113: 1
A114: 1 | B114: =_xlfn.CONCAT(C114,". ", D114,". ", E114,". ", F114,". ", G114,". ", H114) -> Общий расчет. Ци Мень. Анализ Дворца. Комбинации. Нет. Нет | C114: =IFERROR(VLOOKUP(I114,lvl_1[],2,FALSE),"Нет") -> Общий расчет | D114: =IFERROR(VLOOKUP(Rule!J114,lvl_2[],2,FALSE),"Нет") -> Ци Мень | E114: =IFERROR(VLOOKUP(Rule!K114,lvl_3[],2,FALSE),"Нет") -> Анализ Дворца | F114: =IFERROR(INDEX(lvl_4[],MATCH(L114,lvl_4[ID],0),MATCH(TEXT(K114,"##0"),lvl_4[#Headers],0)),"Нет") -> Комбинации | G114: =IFERROR(INDEX(lvl_5[],MATCH(M114,lvl_5[ID],0),MATCH(_xlfn.CONCAT(TEXT(K114,"##0"),"_",TEXT(L114,"##0")),lvl_5[#Headers],0)),"Нет") -> Нет | H114: =IFERROR(INDEX(lvl_6[],MATCH(N114,lvl_6[ID],0),MATCH(_xlfn.CONCAT(K114,"_",L114,"_",M114),lvl_6[#Headers],0)),"Нет") -> Нет | I114: 1 | J114: 2 | K114: 2 | L114: 2 | M114: 0 | N114: 0 | O114: =COUNTIF($P$2:P114,P114) -> 111 | P114: =_xlfn.CONCAT(I114, J114, K114, IF(LEN(L114)=1,_xlfn.CONCAT(0,L114),L114), IF(LEN(M114)=1,_xlfn.CONCAT(0,M114),M114), IF(LEN(N114)=1,_xlfn.CONCAT(0,N114),N114)) -> 122020000 | Q114: =_xlfn.CONCAT(I114, J114, K114, IF(LEN(L114)=1,_xlfn.CONCAT(0,L114),L114), IF(LEN(M114)=1,_xlfn.CONCAT(0,M114),M114), IF(LEN(N114)=1,_xlfn.CONCAT(0,N114),N114), IF(LEN(O114)=1,_xlfn.CONCAT("000",O114),IF(LEN(O114)=2,_xlfn.CONCAT("00",O114),IF(LEN(O114)=3,_xlfn.CONCAT(0,O114),O114)))) -> 1220200000111 | R114: Фу Инь генеральский | S114: Все происходит очень медленно. Сохранение тренда | AY114: 乙 | BA114: 乙 | BG114: -1 | BJ114: 1
A115: 1 | B115: =_xlfn.CONCAT(C115,". ", D115,". ", E115,". ", F115,". ", G115,". ", H115) -> Общий расчет. Ци Мень. Анализ Дворца. Комбинации. Нет. Нет | C115: =IFERROR(VLOOKUP(I115,lvl_1[],2,FALSE),"Нет") -> Общий расчет | D115: =IFERROR(VLOOKUP(Rule!J115,lvl_2[],2,FALSE),"Нет") -> Ци Мень | E115: =IFERROR(VLOOKUP(Rule!K115,lvl_3[],2,FALSE),"Нет") -> Анализ Дворца | F115: =IFERROR(INDEX(lvl_4[],MATCH(L115,lvl_4[ID],0),MATCH(TEXT(K115,"##0"),lvl_4[#Headers],0)),"Нет") -> Комбинации | G115: =IFERROR(INDEX(lvl_5[],MATCH(M115,lvl_5[ID],0),MATCH(_xlfn.CONCAT(TEXT(K115,"##0"),"_",TEXT(L115,"##0")),lvl_5[#Headers],0)),"Нет") -> Нет | H115: =IFERROR(INDEX(lvl_6[],MATCH(N115,lvl_6[ID],0),MATCH(_xlfn.CONCAT(K115,"_",L115,"_",M115),lvl_6[#Headers],0)),"Нет") -> Нет | I115: 1 | J115: 2 | K115: 2 | L115: 2 | M115: 0 | N115: 0 | O115: =COUNTIF($P$2:P115,P115) -> 112 | P115: =_xlfn.CONCAT(I115, J115, K115, IF(LEN(L115)=1,_xlfn.CONCAT(0,L115),L115), IF(LEN(M115)=1,_xlfn.CONCAT(0,M115),M115), IF(LEN(N115)=1,_xlfn.CONCAT(0,N115),N115)) -> 122020000 | Q115: =_xlfn.CONCAT(I115, J115, K115, IF(LEN(L115)=1,_xlfn.CONCAT(0,L115),L115), IF(LEN(M115)=1,_xlfn.CONCAT(0,M115),M115), IF(LEN(N115)=1,_xlfn.CONCAT(0,N115),N115), IF(LEN(O115)=1,_xlfn.CONCAT("000",O115),IF(LEN(O115)=2,_xlfn.CONCAT("00",O115),IF(LEN(O115)=3,_xlfn.CONCAT(0,O115),O115)))) -> 1220200000112 | R115: Фу Инь генеральский | S115: Все происходит очень медленно. Сохранение тренда | AY115: 丙 | BA115: 丙 | BG115: -1 | BJ115: 1
A116: 1 | B116: =_xlfn.CONCAT(C116,". ", D116,". ", E116,". ", F116,". ", G116,". ", H116) -> Общий расчет. Ци Мень. Анализ Дворца. Комбинации. Нет. Нет | C116: =IFERROR(VLOOKUP(I116,lvl_1[],2,FALSE),"Нет") -> Общий расчет | D116: =IFERROR(VLOOKUP(Rule!J116,lvl_2[],2,FALSE),"Нет") -> Ци Мень | E116: =IFERROR(VLOOKUP(Rule!K116,lvl_3[],2,FALSE),"Нет") -> Анализ Дворца | F116: =IFERROR(INDEX(lvl_4[],MATCH(L116,lvl_4[ID],0),MATCH(TEXT(K116,"##0"),lvl_4[#Headers],0)),"Нет") -> Комбинации | G116: =IFERROR(INDEX(lvl_5[],MATCH(M116,lvl_5[ID],0),MATCH(_xlfn.CONCAT(TEXT(K116,"##0"),"_",TEXT(L116,"##0")),lvl_5[#Headers],0)),"Нет") -> Нет | H116: =IFERROR(INDEX(lvl_6[],MATCH(N116,lvl_6[ID],0),MATCH(_xlfn.CONCAT(K116,"_",L116,"_",M116),lvl_6[#Headers],0)),"Нет") -> Нет | I116: 1 | J116: 2 | K116: 2 | L116: 2 | M116: 0 | N116: 0 | O116: =COUNTIF($P$2:P116,P116) -> 113 | P116: =_xlfn.CONCAT(I116, J116, K116, IF(LEN(L116)=1,_xlfn.CONCAT(0,L116),L116), IF(LEN(M116)=1,_xlfn.CONCAT(0,M116),M116), IF(LEN(N116)=1,_xlfn.CONCAT(0,N116),N116)) -> 122020000 | Q116: =_xlfn.CONCAT(I116, J116, K116, IF(LEN(L116)=1,_xlfn.CONCAT(0,L116),L116), IF(LEN(M116)=1,_xlfn.CONCAT(0,M116),M116), IF(LEN(N116)=1,_xlfn.CONCAT(0,N116),N116), IF(LEN(O116)=1,_xlfn.CONCAT("000",O116),IF(LEN(O116)=2,_xlfn.CONCAT("00",O116),IF(LEN(O116)=3,_xlfn.CONCAT(0,O116),O116)))) -> 1220200000113 | R116: Фу Инь генеральский | S116: Все происходит очень медленно. Сохранение тренда | AY116: 丁 | BA116: 丁 | BG116: -1 | BJ116: 1
A117: 1 | B117: =_xlfn.CONCAT(C117,". ", D117,". ", E117,". ", F117,". ", G117,". ", H117) -> Общий расчет. Ци Мень. Анализ Дворца. Комбинации. Нет. Нет | C117: =IFERROR(VLOOKUP(I117,lvl_1[],2,FALSE),"Нет") -> Общий расчет | D117: =IFERROR(VLOOKUP(Rule!J117,lvl_2[],2,FALSE),"Нет") -> Ци Мень | E117: =IFERROR(VLOOKUP(Rule!K117,lvl_3[],2,FALSE),"Нет") -> Анализ Дворца | F117: =IFERROR(INDEX(lvl_4[],MATCH(L117,lvl_4[ID],0),MATCH(TEXT(K117,"##0"),lvl_4[#Headers],0)),"Нет") -> Комбинации | G117: =IFERROR(INDEX(lvl_5[],MATCH(M117,lvl_5[ID],0),MATCH(_xlfn.CONCAT(TEXT(K117,"##0"),"_",TEXT(L117,"##0")),lvl_5[#Headers],0)),"Нет") -> Нет | H117: =IFERROR(INDEX(lvl_6[],MATCH(N117,lvl_6[ID],0),MATCH(_xlfn.CONCAT(K117,"_",L117,"_",M117),lvl_6[#Headers],0)),"Нет") -> Нет | I117: 1 | J117: 2 | K117: 2 | L117: 2 | M117: 0 | N117: 0 | O117: =COUNTIF($P$2:P117,P117) -> 114 | P117: =_xlfn.CONCAT(I117, J117, K117, IF(LEN(L117)=1,_xlfn.CONCAT(0,L117),L117), IF(LEN(M117)=1,_xlfn.CONCAT(0,M117),M117), IF(LEN(N117)=1,_xlfn.CONCAT(0,N117),N117)) -> 122020000 | Q117: =_xlfn.CONCAT(I117, J117, K117, IF(LEN(L117)=1,_xlfn.CONCAT(0,L117),L117), IF(LEN(M117)=1,_xlfn.CONCAT(0,M117),M117), IF(LEN(N117)=1,_xlfn.CONCAT(0,N117),N117), IF(LEN(O117)=1,_xlfn.CONCAT("000",O117),IF(LEN(O117)=2,_xlfn.CONCAT("00",O117),IF(LEN(O117)=3,_xlfn.CONCAT(0,O117),O117)))) -> 1220200000114 | R117: Фу Инь генеральский | S117: Все происходит очень медленно. Сохранение тренда | AY117: 戊 | BA117: 戊 | BG117: -1 | BJ117: 1
A118: 1 | B118: =_xlfn.CONCAT(C118,". ", D118,". ", E118,". ", F118,". ", G118,". ", H118) -> Общий расчет. Ци Мень. Анализ Дворца. Комбинации. Нет. Нет | C118: =IFERROR(VLOOKUP(I118,lvl_1[],2,FALSE),"Нет") -> Общий расчет | D118: =IFERROR(VLOOKUP(Rule!J118,lvl_2[],2,FALSE),"Нет") -> Ци Мень | E118: =IFERROR(VLOOKUP(Rule!K118,lvl_3[],2,FALSE),"Нет") -> Анализ Дворца | F118: =IFERROR(INDEX(lvl_4[],MATCH(L118,lvl_4[ID],0),MATCH(TEXT(K118,"##0"),lvl_4[#Headers],0)),"Нет") -> Комбинации | G118: =IFERROR(INDEX(lvl_5[],MATCH(M118,lvl_5[ID],0),MATCH(_xlfn.CONCAT(TEXT(K118,"##0"),"_",TEXT(L118,"##0")),lvl_5[#Headers],0)),"Нет") -> Нет | H118: =IFERROR(INDEX(lvl_6[],MATCH(N118,lvl_6[ID],0),MATCH(_xlfn.CONCAT(K118,"_",L118,"_",M118),lvl_6[#Headers],0)),"Нет") -> Нет | I118: 1 | J118: 2 | K118: 2 | L118: 2 | M118: 0 | N118: 0 | O118: =COUNTIF($P$2:P118,P118) -> 115 | P118: =_xlfn.CONCAT(I118, J118, K118, IF(LEN(L118)=1,_xlfn.CONCAT(0,L118),L118), IF(LEN(M118)=1,_xlfn.CONCAT(0,M118),M118), IF(LEN(N118)=1,_xlfn.CONCAT(0,N118),N118)) -> 122020000 | Q118: =_xlfn.CONCAT(I118, J118, K118, IF(LEN(L118)=1,_xlfn.CONCAT(0,L118),L118), IF(LEN(M118)=1,_xlfn.CONCAT(0,M118),M118), IF(LEN(N118)=1,_xlfn.CONCAT(0,N118),N118), IF(LEN(O118)=1,_xlfn.CONCAT("000",O118),IF(LEN(O118)=2,_xlfn.CONCAT("00",O118),IF(LEN(O118)=3,_xlfn.CONCAT(0,O118),O118)))) -> 1220200000115 | R118: Фу Инь генеральский | S118: Все происходит очень медленно. Сохранение тренда | AY118: 己 | BA118: 己 | BG118: -1 | BJ118: 1
A119: 1 | B119: =_xlfn.CONCAT(C119,". ", D119,". ", E119,". ", F119,". ", G119,". ", H119) -> Общий расчет. Ци Мень. Анализ Дворца. Комбинации. Нет. Нет | C119: =IFERROR(VLOOKUP(I119,lvl_1[],2,FALSE),"Нет") -> Общий расчет | D119: =IFERROR(VLOOKUP(Rule!J119,lvl_2[],2,FALSE),"Нет") -> Ци Мень | E119: =IFERROR(VLOOKUP(Rule!K119,lvl_3[],2,FALSE),"Нет") -> Анализ Дворца | F119: =IFERROR(INDEX(lvl_4[],MATCH(L119,lvl_4[ID],0),MATCH(TEXT(K119,"##0"),lvl_4[#Headers],0)),"Нет") -> Комбинации | G119: =IFERROR(INDEX(lvl_5[],MATCH(M119,lvl_5[ID],0),MATCH(_xlfn.CONCAT(TEXT(K119,"##0"),"_",TEXT(L119,"##0")),lvl_5[#Headers],0)),"Нет") -> Нет | H119: =IFERROR(INDEX(lvl_6[],MATCH(N119,lvl_6[ID],0),MATCH(_xlfn.CONCAT(K119,"_",L119,"_",M119),lvl_6[#Headers],0)),"Нет") -> Нет | I119: 1 | J119: 2 | K119: 2 | L119: 2 | M119: 0 | N119: 0 | O119: =COUNTIF($P$2:P119,P119) -> 116 | P119: =_xlfn.CONCAT(I119, J119, K119, IF(LEN(L119)=1,_xlfn.CONCAT(0,L119),L119), IF(LEN(M119)=1,_xlfn.CONCAT(0,M119),M119), IF(LEN(N119)=1,_xlfn.CONCAT(0,N119),N119)) -> 122020000 | Q119: =_xlfn.CONCAT(I119, J119, K119, IF(LEN(L119)=1,_xlfn.CONCAT(0,L119),L119), IF(LEN(M119)=1,_xlfn.CONCAT(0,M119),M119), IF(LEN(N119)=1,_xlfn.CONCAT(0,N119),N119), IF(LEN(O119)=1,_xlfn.CONCAT("000",O119),IF(LEN(O119)=2,_xlfn.CONCAT("00",O119),IF(LEN(O119)=3,_xlfn.CONCAT(0,O119),O119)))) -> 1220200000116 | R119: Фу Инь генеральский | S119: Все происходит очень медленно. Сохранение тренда | AY119: 庚 | BA119: 庚 | BG119: -1 | BJ119: 1
A120: 1 | B120: =_xlfn.CONCAT(C120,". ", D120,". ", E120,". ", F120,". ", G120,". ", H120) -> Общий расчет. Ци Мень. Анализ Дворца. Комбинации. Нет. Нет | C120: =IFERROR(VLOOKUP(I120,lvl_1[],2,FALSE),"Нет") -> Общий расчет | D120: =IFERROR(VLOOKUP(Rule!J120,lvl_2[],2,FALSE),"Нет") -> Ци Мень | E120: =IFERROR(VLOOKUP(Rule!K120,lvl_3[],2,FALSE),"Нет") -> Анализ Дворца | F120: =IFERROR(INDEX(lvl_4[],MATCH(L120,lvl_4[ID],0),MATCH(TEXT(K120,"##0"),lvl_4[#Headers],0)),"Нет") -> Комбинации | G120: =IFERROR(INDEX(lvl_5[],MATCH(M120,lvl_5[ID],0),MATCH(_xlfn.CONCAT(TEXT(K120,"##0"),"_",TEXT(L120,"##0")),lvl_5[#Headers],0)),"Нет") -> Нет | H120: =IFERROR(INDEX(lvl_6[],MATCH(N120,lvl_6[ID],0),MATCH(_xlfn.CONCAT(K120,"_",L120,"_",M120),lvl_6[#Headers],0)),"Нет") -> Нет | I120: 1 | J120: 2 | K120: 2 | L120: 2 | M120: 0 | N120: 0 | O120: =COUNTIF($P$2:P120,P120) -> 117 | P120: =_xlfn.CONCAT(I120, J120, K120, IF(LEN(L120)=1,_xlfn.CONCAT(0,L120),L120), IF(LEN(M120)=1,_xlfn.CONCAT(0,M120),M120), IF(LEN(N120)=1,_xlfn.CONCAT(0,N120),N120)) -> 122020000 | Q120: =_xlfn.CONCAT(I120, J120, K120, IF(LEN(L120)=1,_xlfn.CONCAT(0,L120),L120), IF(LEN(M120)=1,_xlfn.CONCAT(0,M120),M120), IF(LEN(N120)=1,_xlfn.CONCAT(0,N120),N120), IF(LEN(O120)=1,_xlfn.CONCAT("000",O120),IF(LEN(O120)=2,_xlfn.CONCAT("00",O120),IF(LEN(O120)=3,_xlfn.CONCAT(0,O120),O120)))) -> 1220200000117 | R120: Фу Инь генеральский | S120: Все происходит очень медленно. Сохранение тренда | AY120: 辛 | BA120: 辛 | BG120: -1 | BJ120: 1
A121: 1 | B121: =_xlfn.CONCAT(C121,". ", D121,". ", E121,". ", F121,". ", G121,". ", H121) -> Общий расчет. Ци Мень. Анализ Дворца. Комбинации. Нет. Нет | C121: =IFERROR(VLOOKUP(I121,lvl_1[],2,FALSE),"Нет") -> Общий расчет | D121: =IFERROR(VLOOKUP(Rule!J121,lvl_2[],2,FALSE),"Нет") -> Ци Мень | E121: =IFERROR(VLOOKUP(Rule!K121,lvl_3[],2,FALSE),"Нет") -> Анализ Дворца | F121: =IFERROR(INDEX(lvl_4[],MATCH(L121,lvl_4[ID],0),MATCH(TEXT(K121,"##0"),lvl_4[#Headers],0)),"Нет") -> Комбинации | G121: =IFERROR(INDEX(lvl_5[],MATCH(M121,lvl_5[ID],0),MATCH(_xlfn.CONCAT(TEXT(K121,"##0"),"_",TEXT(L121,"##0")),lvl_5[#Headers],0)),"Нет") -> Нет | H121: =IFERROR(INDEX(lvl_6[],MATCH(N121,lvl_6[ID],0),MATCH(_xlfn.CONCAT(K121,"_",L121,"_",M121),lvl_6[#Headers],0)),"Нет") -> Нет | I121: 1 | J121: 2 | K121: 2 | L121: 2 | M121: 0 | N121: 0 | O121: =COUNTIF($P$2:P121,P121) -> 118 | P121: =_xlfn.CONCAT(I121, J121, K121, IF(LEN(L121)=1,_xlfn.CONCAT(0,L121),L121), IF(LEN(M121)=1,_xlfn.CONCAT(0,M121),M121), IF(LEN(N121)=1,_xlfn.CONCAT(0,N121),N121)) -> 122020000 | Q121: =_xlfn.CONCAT(I121, J121, K121, IF(LEN(L121)=1,_xlfn.CONCAT(0,L121),L121), IF(LEN(M121)=1,_xlfn.CONCAT(0,M121),M121), IF(LEN(N121)=1,_xlfn.CONCAT(0,N121),N121), IF(LEN(O121)=1,_xlfn.CONCAT("000",O121),IF(LEN(O121)=2,_xlfn.CONCAT("00",O121),IF(LEN(O121)=3,_xlfn.CONCAT(0,O121),O121)))) -> 1220200000118 | R121: Фу Инь генеральский | S121: Все происходит очень медленно. Сохранение тренда | AY121: 壬 | BA121: 壬 | BG121: -1 | BJ121: 1
A122: 1 | B122: =_xlfn.CONCAT(C122,". ", D122,". ", E122,". ", F122,". ", G122,". ", H122) -> Общий расчет. Ци Мень. Анализ Дворца. Комбинации. Нет. Нет | C122: =IFERROR(VLOOKUP(I122,lvl_1[],2,FALSE),"Нет") -> Общий расчет | D122: =IFERROR(VLOOKUP(Rule!J122,lvl_2[],2,FALSE),"Нет") -> Ци Мень | E122: =IFERROR(VLOOKUP(Rule!K122,lvl_3[],2,FALSE),"Нет") -> Анализ Дворца | F122: =IFERROR(INDEX(lvl_4[],MATCH(L122,lvl_4[ID],0),MATCH(TEXT(K122,"##0"),lvl_4[#Headers],0)),"Нет") -> Комбинации | G122: =IFERROR(INDEX(lvl_5[],MATCH(M122,lvl_5[ID],0),MATCH(_xlfn.CONCAT(TEXT(K122,"##0"),"_",TEXT(L122,"##0")),lvl_5[#Headers],0)),"Нет") -> Нет | H122: =IFERROR(INDEX(lvl_6[],MATCH(N122,lvl_6[ID],0),MATCH(_xlfn.CONCAT(K122,"_",L122,"_",M122),lvl_6[#Headers],0)),"Нет") -> Нет | I122: 1 | J122: 2 | K122: 2 | L122: 2 | M122: 0 | N122: 0 | O122: =COUNTIF($P$2:P122,P122) -> 119 | P122: =_xlfn.CONCAT(I122, J122, K122, IF(LEN(L122)=1,_xlfn.CONCAT(0,L122),L122), IF(LEN(M122)=1,_xlfn.CONCAT(0,M122),M122), IF(LEN(N122)=1,_xlfn.CONCAT(0,N122),N122)) -> 122020000 | Q122: =_xlfn.CONCAT(I122, J122, K122, IF(LEN(L122)=1,_xlfn.CONCAT(0,L122),L122), IF(LEN(M122)=1,_xlfn.CONCAT(0,M122),M122), IF(LEN(N122)=1,_xlfn.CONCAT(0,N122),N122), IF(LEN(O122)=1,_xlfn.CONCAT("000",O122),IF(LEN(O122)=2,_xlfn.CONCAT("00",O122),IF(LEN(O122)=3,_xlfn.CONCAT(0,O122),O122)))) -> 1220200000119 | R122: Фу Инь генеральский | S122: Все происходит очень медленно. Сохранение тренда | AY122: 癸 | BA122: 癸 | BG122: -1 | BJ122: 1
A123: 1 | B123: =_xlfn.CONCAT(C123,". ", D123,". ", E123,". ", F123,". ", G123,". ", H123) -> Общий расчет. Ци Мень. Анализ Дворца. Комбинации. Нет. Нет | C123: =IFERROR(VLOOKUP(I123,lvl_1[],2,FALSE),"Нет") -> Общий расчет | D123: =IFERROR(VLOOKUP(Rule!J123,lvl_2[],2,FALSE),"Нет") -> Ци Мень | E123: =IFERROR(VLOOKUP(Rule!K123,lvl_3[],2,FALSE),"Нет") -> Анализ Дворца | F123: =IFERROR(INDEX(lvl_4[],MATCH(L123,lvl_4[ID],0),MATCH(TEXT(K123,"##0"),lvl_4[#Headers],0)),"Нет") -> Комбинации | G123: =IFERROR(INDEX(lvl_5[],MATCH(M123,lvl_5[ID],0),MATCH(_xlfn.CONCAT(TEXT(K123,"##0"),"_",TEXT(L123,"##0")),lvl_5[#Headers],0)),"Нет") -> Нет | H123: =IFERROR(INDEX(lvl_6[],MATCH(N123,lvl_6[ID],0),MATCH(_xlfn.CONCAT(K123,"_",L123,"_",M123),lvl_6[#Headers],0)),"Нет") -> Нет | I123: 1 | J123: 2 | K123: 2 | L123: 2 | M123: 0 | N123: 0 | O123: =COUNTIF($P$2:P123,P123) -> 120 | P123: =_xlfn.CONCAT(I123, J123, K123, IF(LEN(L123)=1,_xlfn.CONCAT(0,L123),L123), IF(LEN(M123)=1,_xlfn.CONCAT(0,M123),M123), IF(LEN(N123)=1,_xlfn.CONCAT(0,N123),N123)) -> 122020000 | Q123: =_xlfn.CONCAT(I123, J123, K123, IF(LEN(L123)=1,_xlfn.CONCAT(0,L123),L123), IF(LEN(M123)=1,_xlfn.CONCAT(0,M123),M123), IF(LEN(N123)=1,_xlfn.CONCAT(0,N123),N123), IF(LEN(O123)=1,_xlfn.CONCAT("000",O123),IF(LEN(O123)=2,_xlfn.CONCAT("00",O123),IF(LEN(O123)=3,_xlfn.CONCAT(0,O123),O123)))) -> 1220200000120 | R123: Фан Инь восьми врат | S123: Действия людей неуместны и не встречают поддержки | AW123: 4 | BB123: 開 | BG123: -1 | BJ123: 1
A124: 1 | B124: =_xlfn.CONCAT(C124,". ", D124,". ", E124,". ", F124,". ", G124,". ", H124) -> Общий расчет. Ци Мень. Анализ Дворца. Комбинации. Нет. Нет | C124: =IFERROR(VLOOKUP(I124,lvl_1[],2,FALSE),"Нет") -> Общий расчет | D124: =IFERROR(VLOOKUP(Rule!J124,lvl_2[],2,FALSE),"Нет") -> Ци Мень | E124: =IFERROR(VLOOKUP(Rule!K124,lvl_3[],2,FALSE),"Нет") -> Анализ Дворца | F124: =IFERROR(INDEX(lvl_4[],MATCH(L124,lvl_4[ID],0),MATCH(TEXT(K124,"##0"),lvl_4[#Headers],0)),"Нет") -> Комбинации | G124: =IFERROR(INDEX(lvl_5[],MATCH(M124,lvl_5[ID],0),MATCH(_xlfn.CONCAT(TEXT(K124,"##0"),"_",TEXT(L124,"##0")),lvl_5[#Headers],0)),"Нет") -> Нет | H124: =IFERROR(INDEX(lvl_6[],MATCH(N124,lvl_6[ID],0),MATCH(_xlfn.CONCAT(K124,"_",L124,"_",M124),lvl_6[#Headers],0)),"Нет") -> Нет | I124: 1 | J124: 2 | K124: 2 | L124: 2 | M124: 0 | N124: 0 | O124: =COUNTIF($P$2:P124,P124) -> 121 | P124: =_xlfn.CONCAT(I124, J124, K124, IF(LEN(L124)=1,_xlfn.CONCAT(0,L124),L124), IF(LEN(M124)=1,_xlfn.CONCAT(0,M124),M124), IF(LEN(N124)=1,_xlfn.CONCAT(0,N124),N124)) -> 122020000 | Q124: =_xlfn.CONCAT(I124, J124, K124, IF(LEN(L124)=1,_xlfn.CONCAT(0,L124),L124), IF(LEN(M124)=1,_xlfn.CONCAT(0,M124),M124), IF(LEN(N124)=1,_xlfn.CONCAT(0,N124),N124), IF(LEN(O124)=1,_xlfn.CONCAT("000",O124),IF(LEN(O124)=2,_xlfn.CONCAT("00",O124),IF(LEN(O124)=3,_xlfn.CONCAT(0,O124),O124)))) -> 1220200000121 | R124: Фан Инь восьми врат | S124: Действия людей неуместны и не встречают поддержки | AW124: 9 | BB124: 休 | BG124: -1 | BJ124: 1
A125: 1 | B125: =_xlfn.CONCAT(C125,". ", D125,". ", E125,". ", F125,". ", G125,". ", H125) -> Общий расчет. Ци Мень. Анализ Дворца. Комбинации. Нет. Нет | C125: =IFERROR(VLOOKUP(I125,lvl_1[],2,FALSE),"Нет") -> Общий расчет | D125: =IFERROR(VLOOKUP(Rule!J125,lvl_2[],2,FALSE),"Нет") -> Ци Мень | E125: =IFERROR(VLOOKUP(Rule!K125,lvl_3[],2,FALSE),"Нет") -> Анализ Дворца | F125: =IFERROR(INDEX(lvl_4[],MATCH(L125,lvl_4[ID],0),MATCH(TEXT(K125,"##0"),lvl_4[#Headers],0)),"Нет") -> Комбинации | G125: =IFERROR(INDEX(lvl_5[],MATCH(M125,lvl_5[ID],0),MATCH(_xlfn.CONCAT(TEXT(K125,"##0"),"_",TEXT(L125,"##0")),lvl_5[#Headers],0)),"Нет") -> Нет | H125: =IFERROR(INDEX(lvl_6[],MATCH(N125,lvl_6[ID],0),MATCH(_xlfn.CONCAT(K125,"_",L125,"_",M125),lvl_6[#Headers],0)),"Нет") -> Нет | I125: 1 | J125: 2 | K125: 2 | L125: 2 | M125: 0 | N125: 0 | O125: =COUNTIF($P$2:P125,P125) -> 122 | P125: =_xlfn.CONCAT(I125, J125, K125, IF(LEN(L125)=1,_xlfn.CONCAT(0,L125),L125), IF(LEN(M125)=1,_xlfn.CONCAT(0,M125),M125), IF(LEN(N125)=1,_xlfn.CONCAT(0,N125),N125)) -> 122020000 | Q125: =_xlfn.CONCAT(I125, J125, K125, IF(LEN(L125)=1,_xlfn.CONCAT(0,L125),L125), IF(LEN(M125)=1,_xlfn.CONCAT(0,M125),M125), IF(LEN(N125)=1,_xlfn.CONCAT(0,N125),N125), IF(LEN(O125)=1,_xlfn.CONCAT("000",O125),IF(LEN(O125)=2,_xlfn.CONCAT("00",O125),IF(LEN(O125)=3,_xlfn.CONCAT(0,O125),O125)))) -> 1220200000122 | R125: Фан Инь восьми врат | S125: Действия людей неуместны и не встречают поддержки | AW125: 2 | BB125: 生 | BG125: -1 | BJ125: 1
A126: 1 | B126: =_xlfn.CONCAT(C126,". ", D126,". ", E126,". ", F126,". ", G126,". ", H126) -> Общий расчет. Ци Мень. Анализ Дворца. Комбинации. Нет. Нет | C126: =IFERROR(VLOOKUP(I126,lvl_1[],2,FALSE),"Нет") -> Общий расчет | D126: =IFERROR(VLOOKUP(Rule!J126,lvl_2[],2,FALSE),"Нет") -> Ци Мень | E126: =IFERROR(VLOOKUP(Rule!K126,lvl_3[],2,FALSE),"Нет") -> Анализ Дворца | F126: =IFERROR(INDEX(lvl_4[],MATCH(L126,lvl_4[ID],0),MATCH(TEXT(K126,"##0"),lvl_4[#Headers],0)),"Нет") -> Комбинации | G126: =IFERROR(INDEX(lvl_5[],MATCH(M126,lvl_5[ID],0),MATCH(_xlfn.CONCAT(TEXT(K126,"##0"),"_",TEXT(L126,"##0")),lvl_5[#Headers],0)),"Нет") -> Нет | H126: =IFERROR(INDEX(lvl_6[],MATCH(N126,lvl_6[ID],0),MATCH(_xlfn.CONCAT(K126,"_",L126,"_",M126),lvl_6[#Headers],0)),"Нет") -> Нет | I126: 1 | J126: 2 | K126: 2 | L126: 2 | M126: 0 | N126: 0 | O126: =COUNTIF($P$2:P126,P126) -> 123 | P126: =_xlfn.CONCAT(I126, J126, K126, IF(LEN(L126)=1,_xlfn.CONCAT(0,L126),L126), IF(LEN(M126)=1,_xlfn.CONCAT(0,M126),M126), IF(LEN(N126)=1,_xlfn.CONCAT(0,N126),N126)) -> 122020000 | Q126: =_xlfn.CONCAT(I126, J126, K126, IF(LEN(L126)=1,_xlfn.CONCAT(0,L126),L126), IF(LEN(M126)=1,_xlfn.CONCAT(0,M126),M126), IF(LEN(N126)=1,_xlfn.CONCAT(0,N126),N126), IF(LEN(O126)=1,_xlfn.CONCAT("000",O126),IF(LEN(O126)=2,_xlfn.CONCAT("00",O126),IF(LEN(O126)=3,_xlfn.CONCAT(0,O126),O126)))) -> 1220200000123 | R126: Фан Инь восьми врат | S126: Действия людей неуместны и не встречают поддержки | AW126: 7 | BB126: 傷 | BG126: -1 | BJ126: 1
A127: 1 | B127: =_xlfn.CONCAT(C127,". ", D127,". ", E127,". ", F127,". ", G127,". ", H127) -> Общий расчет. Ци Мень. Анализ Дворца. Комбинации. Нет. Нет | C127: =IFERROR(VLOOKUP(I127,lvl_1[],2,FALSE),"Нет") -> Общий расчет | D127: =IFERROR(VLOOKUP(Rule!J127,lvl_2[],2,FALSE),"Нет") -> Ци Мень | E127: =IFERROR(VLOOKUP(Rule!K127,lvl_3[],2,FALSE),"Нет") -> Анализ Дворца | F127: =IFERROR(INDEX(lvl_4[],MATCH(L127,lvl_4[ID],0),MATCH(TEXT(K127,"##0"),lvl_4[#Headers],0)),"Нет") -> Комбинации | G127: =IFERROR(INDEX(lvl_5[],MATCH(M127,lvl_5[ID],0),MATCH(_xlfn.CONCAT(TEXT(K127,"##0"),"_",TEXT(L127,"##0")),lvl_5[#Headers],0)),"Нет") -> Нет | H127: =IFERROR(INDEX(lvl_6[],MATCH(N127,lvl_6[ID],0),MATCH(_xlfn.CONCAT(K127,"_",L127,"_",M127),lvl_6[#Headers],0)),"Нет") -> Нет | I127: 1 | J127: 2 | K127: 2 | L127: 2 | M127: 0 | N127: 0 | O127: =COUNTIF($P$2:P127,P127) -> 124 | P127: =_xlfn.CONCAT(I127, J127, K127, IF(LEN(L127)=1,_xlfn.CONCAT(0,L127),L127), IF(LEN(M127)=1,_xlfn.CONCAT(0,M127),M127), IF(LEN(N127)=1,_xlfn.CONCAT(0,N127),N127)) -> 122020000 | Q127: =_xlfn.CONCAT(I127, J127, K127, IF(LEN(L127)=1,_xlfn.CONCAT(0,L127),L127), IF(LEN(M127)=1,_xlfn.CONCAT(0,M127),M127), IF(LEN(N127)=1,_xlfn.CONCAT(0,N127),N127), IF(LEN(O127)=1,_xlfn.CONCAT("000",O127),IF(LEN(O127)=2,_xlfn.CONCAT("00",O127),IF(LEN(O127)=3,_xlfn.CONCAT(0,O127),O127)))) -> 1220200000124 | R127: Фан Инь восьми врат | S127: Действия людей неуместны и не встречают поддержки | AW127: 6 | BB127: 杜 | BG127: -1 | BJ127: 1
A128: 1 | B128: =_xlfn.CONCAT(C128,". ", D128,". ", E128,". ", F128,". ", G128,". ", H128) -> Общий расчет. Ци Мень. Анализ Дворца. Комбинации. Нет. Нет | C128: =IFERROR(VLOOKUP(I128,lvl_1[],2,FALSE),"Нет") -> Общий расчет | D128: =IFERROR(VLOOKUP(Rule!J128,lvl_2[],2,FALSE),"Нет") -> Ци Мень | E128: =IFERROR(VLOOKUP(Rule!K128,lvl_3[],2,FALSE),"Нет") -> Анализ Дворца | F128: =IFERROR(INDEX(lvl_4[],MATCH(L128,lvl_4[ID],0),MATCH(TEXT(K128,"##0"),lvl_4[#Headers],0)),"Нет") -> Комбинации | G128: =IFERROR(INDEX(lvl_5[],MATCH(M128,lvl_5[ID],0),MATCH(_xlfn.CONCAT(TEXT(K128,"##0"),"_",TEXT(L128,"##0")),lvl_5[#Headers],0)),"Нет") -> Нет | H128: =IFERROR(INDEX(lvl_6[],MATCH(N128,lvl_6[ID],0),MATCH(_xlfn.CONCAT(K128,"_",L128,"_",M128),lvl_6[#Headers],0)),"Нет") -> Нет | I128: 1 | J128: 2 | K128: 2 | L128: 2 | M128: 0 | N128: 0 | O128: =COUNTIF($P$2:P128,P128) -> 125 | P128: =_xlfn.CONCAT(I128, J128, K128, IF(LEN(L128)=1,_xlfn.CONCAT(0,L128),L128), IF(LEN(M128)=1,_xlfn.CONCAT(0,M128),M128), IF(LEN(N128)=1,_xlfn.CONCAT(0,N128),N128)) -> 122020000 | Q128: =_xlfn.CONCAT(I128, J128, K128, IF(LEN(L128)=1,_xlfn.CONCAT(0,L128),L128), IF(LEN(M128)=1,_xlfn.CONCAT(0,M128),M128), IF(LEN(N128)=1,_xlfn.CONCAT(0,N128),N128), IF(LEN(O128)=1,_xlfn.CONCAT("000",O128),IF(LEN(O128)=2,_xlfn.CONCAT("00",O128),IF(LEN(O128)=3,_xlfn.CONCAT(0,O128),O128)))) -> 1220200000125 | R128: Фан Инь восьми врат | S128: Действия людей неуместны и не встречают поддержки | AW128: 1 | BB128: 景 | BG128: -1 | BJ128: 1
A129: 1 | B129: =_xlfn.CONCAT(C129,". ", D129,". ", E129,". ", F129,". ", G129,". ", H129) -> Общий расчет. Ци Мень. Анализ Дворца. Комбинации. Нет. Нет | C129: =IFERROR(VLOOKUP(I129,lvl_1[],2,FALSE),"Нет") -> Общий расчет | D129: =IFERROR(VLOOKUP(Rule!J129,lvl_2[],2,FALSE),"Нет") -> Ци Мень | E129: =IFERROR(VLOOKUP(Rule!K129,lvl_3[],2,FALSE),"Нет") -> Анализ Дворца | F129: =IFERROR(INDEX(lvl_4[],MATCH(L129,lvl_4[ID],0),MATCH(TEXT(K129,"##0"),lvl_4[#Headers],0)),"Нет") -> Комбинации | G129: =IFERROR(INDEX(lvl_5[],MATCH(M129,lvl_5[ID],0),MATCH(_xlfn.CONCAT(TEXT(K129,"##0"),"_",TEXT(L129,"##0")),lvl_5[#Headers],0)),"Нет") -> Нет | H129: =IFERROR(INDEX(lvl_6[],MATCH(N129,lvl_6[ID],0),MATCH(_xlfn.CONCAT(K129,"_",L129,"_",M129),lvl_6[#Headers],0)),"Нет") -> Нет | I129: 1 | J129: 2 | K129: 2 | L129: 2 | M129: 0 | N129: 0 | O129: =COUNTIF($P$2:P129,P129) -> 126 | P129: =_xlfn.CONCAT(I129, J129, K129, IF(LEN(L129)=1,_xlfn.CONCAT(0,L129),L129), IF(LEN(M129)=1,_xlfn.CONCAT(0,M129),M129), IF(LEN(N129)=1,_xlfn.CONCAT(0,N129),N129)) -> 122020000 | Q129: =_xlfn.CONCAT(I129, J129, K129, IF(LEN(L129)=1,_xlfn.CONCAT(0,L129),L129), IF(LEN(M129)=1,_xlfn.CONCAT(0,M129),M129), IF(LEN(N129)=1,_xlfn.CONCAT(0,N129),N129), IF(LEN(O129)=1,_xlfn.CONCAT("000",O129),IF(LEN(O129)=2,_xlfn.CONCAT("00",O129),IF(LEN(O129)=3,_xlfn.CONCAT(0,O129),O129)))) -> 1220200000126 | R129: Фан Инь восьми врат | S129: Действия людей неуместны и не встречают поддержки | AW129: 8 | BB129: 死 | BG129: -1 | BJ129: 1
A130: 1 | B130: =_xlfn.CONCAT(C130,". ", D130,". ", E130,". ", F130,". ", G130,". ", H130) -> Общий расчет. Ци Мень. Анализ Дворца. Комбинации. Нет. Нет | C130: =IFERROR(VLOOKUP(I130,lvl_1[],2,FALSE),"Нет") -> Общий расчет | D130: =IFERROR(VLOOKUP(Rule!J130,lvl_2[],2,FALSE),"Нет") -> Ци Мень | E130: =IFERROR(VLOOKUP(Rule!K130,lvl_3[],2,FALSE),"Нет") -> Анализ Дворца | F130: =IFERROR(INDEX(lvl_4[],MATCH(L130,lvl_4[ID],0),MATCH(TEXT(K130,"##0"),lvl_4[#Headers],0)),"Нет") -> Комбинации | G130: =IFERROR(INDEX(lvl_5[],MATCH(M130,lvl_5[ID],0),MATCH(_xlfn.CONCAT(TEXT(K130,"##0"),"_",TEXT(L130,"##0")),lvl_5[#Headers],0)),"Нет") -> Нет | H130: =IFERROR(INDEX(lvl_6[],MATCH(N130,lvl_6[ID],0),MATCH(_xlfn.CONCAT(K130,"_",L130,"_",M130),lvl_6[#Headers],0)),"Нет") -> Нет | I130: 1 | J130: 2 | K130: 2 | L130: 2 | M130: 0 | N130: 0 | O130: =COUNTIF($P$2:P130,P130) -> 127 | P130: =_xlfn.CONCAT(I130, J130, K130, IF(LEN(L130)=1,_xlfn.CONCAT(0,L130),L130), IF(LEN(M130)=1,_xlfn.CONCAT(0,M130),M130), IF(LEN(N130)=1,_xlfn.CONCAT(0,N130),N130)) -> 122020000 | Q130: =_xlfn.CONCAT(I130, J130, K130, IF(LEN(L130)=1,_xlfn.CONCAT(0,L130),L130), IF(LEN(M130)=1,_xlfn.CONCAT(0,M130),M130), IF(LEN(N130)=1,_xlfn.CONCAT(0,N130),N130), IF(LEN(O130)=1,_xlfn.CONCAT("000",O130),IF(LEN(O130)=2,_xlfn.CONCAT("00",O130),IF(LEN(O130)=3,_xlfn.CONCAT(0,O130),O130)))) -> 1220200000127 | R130: Фан Инь восьми врат | S130: Действия людей неуместны и не встречают поддержки | AW130: 3 | BB130: 驚 | BG130: -1 | BJ130: 1
A131: 1 | B131: =_xlfn.CONCAT(C131,". ", D131,". ", E131,". ", F131,". ", G131,". ", H131) -> Общий расчет. Ци Мень. Анализ Дворца. Комбинации. Нет. Нет | C131: =IFERROR(VLOOKUP(I131,lvl_1[],2,FALSE),"Нет") -> Общий расчет | D131: =IFERROR(VLOOKUP(Rule!J131,lvl_2[],2,FALSE),"Нет") -> Ци Мень | E131: =IFERROR(VLOOKUP(Rule!K131,lvl_3[],2,FALSE),"Нет") -> Анализ Дворца | F131: =IFERROR(INDEX(lvl_4[],MATCH(L131,lvl_4[ID],0),MATCH(TEXT(K131,"##0"),lvl_4[#Headers],0)),"Нет") -> Комбинации | G131: =IFERROR(INDEX(lvl_5[],MATCH(M131,lvl_5[ID],0),MATCH(_xlfn.CONCAT(TEXT(K131,"##0"),"_",TEXT(L131,"##0")),lvl_5[#Headers],0)),"Нет") -> Нет | H131: =IFERROR(INDEX(lvl_6[],MATCH(N131,lvl_6[ID],0),MATCH(_xlfn.CONCAT(K131,"_",L131,"_",M131),lvl_6[#Headers],0)),"Нет") -> Нет | I131: 1 | J131: 2 | K131: 2 | L131: 2 | M131: 0 | N131: 0 | O131: =COUNTIF($P$2:P131,P131) -> 128 | P131: =_xlfn.CONCAT(I131, J131, K131, IF(LEN(L131)=1,_xlfn.CONCAT(0,L131),L131), IF(LEN(M131)=1,_xlfn.CONCAT(0,M131),M131), IF(LEN(N131)=1,_xlfn.CONCAT(0,N131),N131)) -> 122020000 | Q131: =_xlfn.CONCAT(I131, J131, K131, IF(LEN(L131)=1,_xlfn.CONCAT(0,L131),L131), IF(LEN(M131)=1,_xlfn.CONCAT(0,M131),M131), IF(LEN(N131)=1,_xlfn.CONCAT(0,N131),N131), IF(LEN(O131)=1,_xlfn.CONCAT("000",O131),IF(LEN(O131)=2,_xlfn.CONCAT("00",O131),IF(LEN(O131)=3,_xlfn.CONCAT(0,O131),O131)))) -> 1220200000128 | R131: Фан Инь звездный | S131: Мысли людей неуместны | AW131: 4 | BD131: 心 | BG131: -1 | BJ131: 1
A132: 1 | B132: =_xlfn.CONCAT(C132,". ", D132,". ", E132,". ", F132,". ", G132,". ", H132) -> Общий расчет. Ци Мень. Анализ Дворца. Комбинации. Нет. Нет | C132: =IFERROR(VLOOKUP(I132,lvl_1[],2,FALSE),"Нет") -> Общий расчет | D132: =IFERROR(VLOOKUP(Rule!J132,lvl_2[],2,FALSE),"Нет") -> Ци Мень | E132: =IFERROR(VLOOKUP(Rule!K132,lvl_3[],2,FALSE),"Нет") -> Анализ Дворца | F132: =IFERROR(INDEX(lvl_4[],MATCH(L132,lvl_4[ID],0),MATCH(TEXT(K132,"##0"),lvl_4[#Headers],0)),"Нет") -> Комбинации | G132: =IFERROR(INDEX(lvl_5[],MATCH(M132,lvl_5[ID],0),MATCH(_xlfn.CONCAT(TEXT(K132,"##0"),"_",TEXT(L132,"##0")),lvl_5[#Headers],0)),"Нет") -> Нет | H132: =IFERROR(INDEX(lvl_6[],MATCH(N132,lvl_6[ID],0),MATCH(_xlfn.CONCAT(K132,"_",L132,"_",M132),lvl_6[#Headers],0)),"Нет") -> Нет | I132: 1 | J132: 2 | K132: 2 | L132: 2 | M132: 0 | N132: 0 | O132: =COUNTIF($P$2:P132,P132) -> 129 | P132: =_xlfn.CONCAT(I132, J132, K132, IF(LEN(L132)=1,_xlfn.CONCAT(0,L132),L132), IF(LEN(M132)=1,_xlfn.CONCAT(0,M132),M132), IF(LEN(N132)=1,_xlfn.CONCAT(0,N132),N132)) -> 122020000 | Q132: =_xlfn.CONCAT(I132, J132, K132, IF(LEN(L132)=1,_xlfn.CONCAT(0,L132),L132), IF(LEN(M132)=1,_xlfn.CONCAT(0,M132),M132), IF(LEN(N132)=1,_xlfn.CONCAT(0,N132),N132), IF(LEN(O132)=1,_xlfn.CONCAT("000",O132),IF(LEN(O132)=2,_xlfn.CONCAT("00",O132),IF(LEN(O132)=3,_xlfn.CONCAT(0,O132),O132)))) -> 1220200000129 | R132: Фан Инь звездный | S132: Мысли людей неуместны | AW132: 9 | BD132: 蓬 | BG132: -1 | BJ132: 1
A133: 1 | B133: =_xlfn.CONCAT(C133,". ", D133,". ", E133,". ", F133,". ", G133,". ", H133) -> Общий расчет. Ци Мень. Анализ Дворца. Комбинации. Нет. Нет | C133: =IFERROR(VLOOKUP(I133,lvl_1[],2,FALSE),"Нет") -> Общий расчет | D133: =IFERROR(VLOOKUP(Rule!J133,lvl_2[],2,FALSE),"Нет") -> Ци Мень | E133: =IFERROR(VLOOKUP(Rule!K133,lvl_3[],2,FALSE),"Нет") -> Анализ Дворца | F133: =IFERROR(INDEX(lvl_4[],MATCH(L133,lvl_4[ID],0),MATCH(TEXT(K133,"##0"),lvl_4[#Headers],0)),"Нет") -> Комбинации | G133: =IFERROR(INDEX(lvl_5[],MATCH(M133,lvl_5[ID],0),MATCH(_xlfn.CONCAT(TEXT(K133,"##0"),"_",TEXT(L133,"##0")),lvl_5[#Headers],0)),"Нет") -> Нет | H133: =IFERROR(INDEX(lvl_6[],MATCH(N133,lvl_6[ID],0),MATCH(_xlfn.CONCAT(K133,"_",L133,"_",M133),lvl_6[#Headers],0)),"Нет") -> Нет | I133: 1 | J133: 2 | K133: 2 | L133: 2 | M133: 0 | N133: 0 | O133: =COUNTIF($P$2:P133,P133) -> 130 | P133: =_xlfn.CONCAT(I133, J133, K133, IF(LEN(L133)=1,_xlfn.CONCAT(0,L133),L133), IF(LEN(M133)=1,_xlfn.CONCAT(0,M133),M133), IF(LEN(N133)=1,_xlfn.CONCAT(0,N133),N133)) -> 122020000 | Q133: =_xlfn.CONCAT(I133, J133, K133, IF(LEN(L133)=1,_xlfn.CONCAT(0,L133),L133), IF(LEN(M133)=1,_xlfn.CONCAT(0,M133),M133), IF(LEN(N133)=1,_xlfn.CONCAT(0,N133),N133), IF(LEN(O133)=1,_xlfn.CONCAT("000",O133),IF(LEN(O133)=2,_xlfn.CONCAT("00",O133),IF(LEN(O133)=3,_xlfn.CONCAT(0,O133),O133)))) -> 1220200000130 | R133: Фан Инь звездный | S133: Мысли людей неуместны | AW133: 2 | BD133: 任 | BG133: -1 | BJ133: 1
...

Sheet Settings
B1: Column | C1: Flag | J1: 1. A | K1: =SEARCH(".",J1,1) -> 2 | L1: =K1+1 -> 3 | M1: =MID(J1,L1,LEN(J1)-L1) -> A | N1: A
A2: в базу | B2: A | C2: 1 | J2: 2. B | K2: =SEARCH(".",J2,1) -> 2 | L2: =K2+1 -> 3 | M2: =MID(J2,L2,LEN(J2)-L2) -> B | N2: B
A3: Описание | B3: B | C3: 1 | J3: 3. C | K3: =SEARCH(".",J3,1) -> 2 | L3: =K3+1 -> 3 | M3: =MID(J3,L3,LEN(J3)-L3) -> C | N3: C
A4: lvl_1_nm | B4: C | C4: 1 | J4: 4. D | K4: =SEARCH(".",J4,1) -> 2 | L4: =K4+1 -> 3 | M4: =MID(J4,L4,LEN(J4)-L4) -> D | N4: D
A5: lvl_2_nm | B5: D | C5: 1 | J5: 5. E | K5: =SEARCH(".",J5,1) -> 2 | L5: =K5+1 -> 3 | M5: =MID(J5,L5,LEN(J5)-L5) -> E | N5: E
A6: lvl_3_nm | B6: E | C6: 1 | J6: 6. F | K6: =SEARCH(".",J6,1) -> 2 | L6: =K6+1 -> 3 | M6: =MID(J6,L6,LEN(J6)-L6) -> F | N6: F
A7: lvl_4_nm | B7: F | C7: 1 | J7: 7. G | K7: =SEARCH(".",J7,1) -> 2 | L7: =K7+1 -> 3 | M7: =MID(J7,L7,LEN(J7)-L7) -> G | N7: G
A8: lvl_5_nm | B8: G | C8: 1 | J8: 8. H | K8: =SEARCH(".",J8,1) -> 2 | L8: =K8+1 -> 3 | M8: =MID(J8,L8,LEN(J8)-L8) -> H | N8: H
A9: lvl_6_nm | B9: H | C9: 1 | J9: 9. I | K9: =SEARCH(".",J9,1) -> 2 | L9: =K9+1 -> 3 | M9: =MID(J9,L9,LEN(J9)-L9) -> I | N9: I
A10: lvl_1 | B10: I | C10: 1 | J10: 10. J | K10: =SEARCH(".",J10,1) -> 3 | L10: =K10+1 -> 4 | M10: =MID(J10,L10,LEN(J10)-L10) -> J | N10: J
A11: lvl_2 | B11: J | C11: 1 | J11: 11. K | K11: =SEARCH(".",J11,1) -> 3 | L11: =K11+1 -> 4 | M11: =MID(J11,L11,LEN(J11)-L11) -> K | N11: K
A12: lvl_3 | B12: K | C12: 1 | J12: 12. L | K12: =SEARCH(".",J12,1) -> 3 | L12: =K12+1 -> 4 | M12: =MID(J12,L12,LEN(J12)-L12) -> L | N12: L
A13: lvl_4 | B13: L | C13: 1 | J13: 13. M | K13: =SEARCH(".",J13,1) -> 3 | L13: =K13+1 -> 4 | M13: =MID(J13,L13,LEN(J13)-L13) -> M | N13: M
... A68: date_analyze_stop_factor | B68: BO | C68: 1 | J68: 68. BP | K68: =SEARCH(".",J68,1) -> 3 | L68: =K68+1 -> 4 | M68: =MID(J68,L68,LEN(J68)-L68) -> BP | N68: BP
J69: 69. BQ | K69: =SEARCH(".",J69,1) -> 3 | L69: =K69+1 -> 4 | M69: =MID(J69,L69,LEN(J69)-L69) -> BQ | N69: BQ
J70: 70. BR | K70: =SEARCH(".",J70,1) -> 3 | L70: =K70+1 -> 4 | M70: =MID(J70,L70,LEN(J70)-L70) -> BR | N70: BR
J72: Если вам нужно больше названий или таблица за пределами 70 столбцов, просто дайте мне знать!

Sheet Справочник
A1: lvl_1 | B1: lvl_2 | C1: lvl_3 | D1: lvl_4 | M1: lvl_1 | P1: lvl_2 | S1: lvl_3 | V1: lvl_4 | AA1: lvl_5 | AK1: lvl_6
A2: 0 | B2: 2 | C2: 2 | D2: 1 | M2: ID | N2: NM | P2: ID | Q2: NM | S2: ID | T2: NM | W2: Анализ даты | X2: Анализ Дворца | Y2: Активация | AB2: Персональные настройки | AC2: Структура | AD2: Совпадение направлений | AE2: СКДГ | AG2: Операторы | AH2: Совпадение направлений | AI2: Пустота | AJ2: Желтая 5 | AM2: Полное столкновение | AQ2: НС | AR2: ЗВ | AS2: Ворота | AT2: Дворец | AU2: Дух | AV2: Звезда
M3: 1 | N3: Общий расчет | P3: 1 | Q3: Баз ци | S3: 1 | T3: Анализ даты | V3: ID | W3: 1 | X3: 2 | Y3: 3 | AA3: ID | AB3: 2_0 | AC3: 2_1 | AD3: 2_6 | AE3: 1_4 | AF3: 1_5 | AG3: 2_3 | AH3: 2_62 | AI3: 2_8 | AJ3: 2_9 | AL3: ID | AM3: 1_4_1 | AN3: 1_4_2 | AO3: 1_4_3 | AP3: 1_5_1 | AQ3: 2_1_1 | AR3: 2_1_2 | AS3: 2_3_1 | AT3: 2_3_2 | AU3: 2_3_3 | AV3: 2_3_4
M4: 2 | N4: Индивидуальный расчет | P4: 2 | Q4: Ци Мень | S4: 2 | T4: Анализ Дворца | V4: 0 | W4: Персональные настройки | X4: Персональные настройки | AA4: 0 | AC4: Благоприятность | AE4: Нет | AL4: 1 | AM4: Год и месяц | AP4: Братство | AQ4: НС. Фаза Ци | AR4: ЗВ. Фаза Ци | AS4: Ворота. Благоприятность | AT4: Дворец. Благоприятность | AU4: Дух. Благоприятность | AV4: Звезда. Благоприятность
P5: 3 | Q5: Фэн Шуй | S5: 3 | T5: Активация | V5: 1 | W5: Фаза Ци | X5: Структуры | Y5: Летящие звезды | AA5: 1 | AB5: Структуры | AC5: НС | AD5: Час = День | AE5: Полное столкновение | AF5: 10 Божеств | AG5: Ворота | AH5: Год | AI5: По году | AJ5: По году | AL5: 2 | AM5: Год и день | AP5: Грабитель богатства | AQ5: НС. Отношение со дворцом | AR5: ЗВ. Отношение со дворцом | AS5: Ворота. Сила ворот по сезону (своевременность) | AT5: Дворец. Отношение элемента оператора к элементу дворца | AU5: Дух. Отношение элемента оператора к элементу дворца | AV5: Звезда. Отношение элемента оператора к элементу дворца
P6: 4 | Q6: Анализ даты | S6: 4 | T6: Манифестация | V6: 2 | W6: Столкновения ЗВ | X6: Комбинации | AA6: 2 | AB6: Комбинации | AC6: ЗВ | AD6: Час = День = Месяц | AE6: Период | AF6: Звезда Генерала | AG6: Дворец | AH6: Месяц | AI6: По месяцу | AJ6: По месяцу | AL6: 3 | AM6: Год и час | AP6: Дух наслаждения | AQ6: НС. Элемент в сезоне | AR6: ЗВ. Элемент в сезоне | AS6: Ворота. Сила ворот по Дворцу | AT6: Дворец. Сила дворца в сезоне (своевременность) | AU6: Дух. Отношение элемента оператора к элементу сезона | AV6: Звезда. Сила дворца в сезоне (своевременность)
V7: 3 | W7: Преодоление НС | X7: Операторы | AA7: 3 | AB7: Операторы | AD7: Час = День = Месяц = Год | AE7: Элемент | AF7: Цветущий балдахин | AG7: Дух | AH7: День | AI7: По дню | AL7: 4 | AM7: Месяц и день | AP7: Ранение чиновника (Нападение на власть) | AS7: Ворота. Сила благоприятных Ворот в разных дворцах с учетом сезона
V8: 4 | W8: СКДГ | X8: Фаза Ци | AA8: 4 | AB8: Символические звезды | AE8: Хорошее время | AF8: Почтовая лошадь | AG8: Звезда | AI8: По Часу | AL8: 5 | AM8: Месяц и час | AP8: Склонность к богатству (Косое богатство)
V9: 5 | W9: Символические звезды | X9: Взаимодействия Дворцов | AA9: 5 | AE9: Идеальное время | AF9: Демон уничтожения | AL9: 6 | AM9: День и час | AP9: Прямое богатство
V10: 6 | X10: Совпадение направлений | AA10: 6 | AF10: Демон грабежа | AL10: 7 | AP10: Убийство 7й позиции (Неправильный чиновник_
V11: 7 | X11: Символические звезды | AA11: 7 | AF11: Цветок романтики / Цветок персика | AL11: 8 | AP11: Правильный чиновник (Правильная власть)
V12: 8 | X12: Пустота | AA12: 8 | AF12: Звезда Бедствий | AL12: 9 | AP12: Косая печать (Дух Совы)
V13: 9 | X13: Желтая пятерка | AA13: 9 | AF13: Небесный доктор / медик | AL13: 10 | AP13: Правильная печать
V14: 10 | AA14: 10 | AF14: Красный луань, Красный феникс, Волшебник Любви
V15: 11 | AA15: 11 | AF15: Одинокая планета, Приют одиночества (для Женщин)
V16: 99 | W16: Нет | X16: Нет | Y16: Нет | AA16: 12 | AF16: Одинокая планета, Приют одиночества (для мужчин)
AA17: 13 | AF17: Небесная благодать
AA18: 14 | AF18: Лунная добродетель
AA19: 15 | AF19: Благородный небесной единицы (Благородный человек)
AA20: 16 | AF20: Благородный Тайцзи
AA21: 17 | AF21: Звезда академика
AA22: 18 | AF22: Овечий нож (Демон убиения овец)
AA23: 19 | AF23: Вознаграждение 10 Небесных стволов (Процветание)
AA24: 20 | AF24: Демон красоты
AA25: 21 | AF25: Золотая карета
AA26: 22 | AF26: Куйгант
AA27: 23 | AF27: Ошибка Инь-Ян
AA28: 24 | AF28: Сети небес и земли
... AA37: 33 | AF37: Месячная добродетель
AA38: 34
AA39: 35
AA40: 36
AA41: 37
AA42: 38
AA43: 39
AA44: 40
AA45: 41
AA46: 42
AA47: 43
AA48: 44
AA49: 45

Sheet Лист1
A1: id_group | B1: system | C1: sky_earth | D1: combination | E1: nm | F1: coef | G1: stop | I1: 申 | J1: 巳 | K1: 寅 | M1: =_xlfn.CONCAT(I1,J1) -> 申巳 | P1: =_xlfn.CONCAT(I1,J1,K1,) -> 申巳寅 | R1: Нужно отдельно подумать над пустотой
A2: 1 | B2: bazci | C2: sky | D2: 甲己 | E2: Комбинация НС. Земля | F2: 0.75 | M2: =_xlfn.CONCAT(J1,I1) -> 巳申 | P2: =_xlfn.CONCAT(I1,K1,J1) -> 申寅巳 | R2: Нужно подумать над реализацией проверки прямых столкновений
A3: 1 | B3: bazci | C3: sky | D3: 己甲 | E3: Комбинация НС. Земля | F3: 0.75 | P3: =_xlfn.CONCAT(J1,I1,K1) -> 巳申寅
A4: 1 | B4: bazci | C4: sky | D4: 乙庚 | E4: Комбинация НС. Металл | F4: 0.75 | P4: =_xlfn.CONCAT(J1,K1,I1) -> 巳寅申
A5: 1 | B5: bazci | C5: sky | D5: 庚乙 | E5: Комбинация НС. Металл | F5: 0.75 | P5: =_xlfn.CONCAT(K1,I1,J1) -> 寅申巳
A6: 1 | B6: bazci | C6: sky | D6: 丙辛 | E6: Комбинация НС. Вода | F6: 0.75 | P6: =_xlfn.CONCAT(K1,J1,I1) -> 寅巳申
A7: 1 | B7: bazci | C7: sky | D7: 辛丙 | E7: Комбинация НС. Вода | F7: 0.75
A8: 1 | B8: bazci | C8: sky | D8: 丁壬 | E8: Комбинация НС. Дерево | F8: 0.75
A9: 1 | B9: bazci | C9: sky | D9: 壬丁 | E9: Комбинация НС. Дерево | F9: 0.75
A10: 1 | B10: bazci | C10: sky | D10: 戊癸 | E10: Комбинация НС. Огонь | F10: 0.75
A11: 1 | B11: bazci | C11: sky | D11: 癸戊 | E11: Комбинация НС. Огонь | F11: 0.75
A12: 2 | B12: bazci | C12: sky | D12: 甲庚 | E12: Столкновние НС | F12: -1 | G12: 1
A13: 2 | B13: bazci | C13: sky | D13: 庚甲 | E13: Столкновние НС | F13: -1 | G13: 1
A14: 2 | B14: bazci | C14: sky | D14: 乙辛 | E14: Столкновние НС | F14: -1 | G14: 1
A15: 2 | B15: bazci | C15: sky | D15: 辛乙 | E15: Столкновние НС | F15: -1 | G15: 1
A16: 2 | B16: bazci | C16: sky | D16: 丙壬 | E16: Столкновние НС | F16: -1 | G16: 1
A17: 2 | B17: bazci | C17: sky | D17: 壬丙 | E17: Столкновние НС | F17: -1 | G17: 1
A18: 2 | B18: bazci | C18: sky | D18: 癸丁 | E18: Столкновние НС | F18: -1 | G18: 1
A19: 2 | B19: bazci | C19: sky | D19: 丁癸 | E19: Столкновние НС | F19: -1 | G19: 1
A20: 3 | B20: bazci | C20: earth | D20: 子午 | E20: Столкновение ЗВ | F20: -1 | G20: 1
A21: 3 | B21: bazci | C21: earth | D21: 午子 | E21: Столкновение ЗВ | F21: -1 | G21: 1
A22: 3 | B22: bazci | C22: earth | D22: 寅申 | E22: Столкновение ЗВ | F22: -1 | G22: 1
A23: 3 | B23: bazci | C23: earth | D23: 申寅 | E23: Столкновение ЗВ | F23: -1 | G23: 1
... A31: 3 | B31: bazci | C31: earth | D31: 未丑 | E31: Столкновение ЗВ | F31: -1 | G31: 1
A32: 4 | B32: bazci | C32: earth | D32: 子丑 | E32: Комбинация ЗВ. Земля | F32: 1
A33: 4 | B33: bazci | C33: earth | D33: 丑子 | E33: Комбинация ЗВ. Земля | F33: 1
A34: 4 | B34: bazci | C34: earth | D34: 寅亥 | E34: Комбинация ЗВ. Дерево | F34: 1
A35: 4 | B35: bazci | C35: earth | D35: 亥寅 | E35: Комбинация ЗВ. Дерево | F35: 1
A36: 4 | B36: bazci | C36: earth | D36: 卯戌 | E36: Комбинация ЗВ. Огонь | F36: 1
A37: 4 | B37: bazci | C37: earth | D37: 戌卯 | E37: Комбинация ЗВ. Огонь | F37: 1
A38: 4 | B38: bazci | C38: earth | D38: 辰酉 | E38: Комбинация ЗВ. Металл | F38: 1
A39: 4 | B39: bazci | C39: earth | D39: 酉辰 | E39: Комбинация ЗВ. Металл | F39: 1
A40: 4 | B40: bazci | C40: earth | D40: 巳申 | E40: Комбинация ЗВ. Вода | F40: 1
A41: 4 | B41: bazci | C41: earth | D41: 申巳 | E41: Комбинация ЗВ. Вода | F41: 1
A42: 4 | B42: bazci | C42: earth | D42: 午未 | E42: Комбинация ЗВ. Огонь | F42: 1
A43: 4 | B43: bazci | C43: earth | D43: 未午 | E43: Комбинация ЗВ. Огонь | F43: 1
A44: 5 | B44: bazci | C44: earth | D44: 申子辰 | E44: Комбинация 3х. Вода | H44: Смущает условие, что они д.б. на фазах ЦИ Рождение, процветание и Могила. Это сейчас в фильтре не отражено
A45: 5 | B45: bazci | C45: earth | D45: 申辰子 | E45: Комбинация 3х. Вода
A46: 5 | B46: bazci | C46: earth | D46: 子申辰 | E46: Комбинация 3х. Вода
A47: 5 | B47: bazci | C47: earth | D47: 子辰申 | E47: Комбинация 3х. Вода
A48: 5 | B48: bazci | C48: earth | D48: 辰申子 | E48: Комбинация 3х. Вода
A49: 5 | B49: bazci | C49: earth | D49: 辰子申 | E49: Комбинация 3х. Вода
A50: 5 | B50: bazci | C50: earth | D50: 亥卯未 | E50: Комбинация 3х. Дерево
A51: 5 | B51: bazci | C51: earth | D51: 亥未卯 | E51: Комбинация 3х. Дерево
A52: 5 | B52: bazci | C52: earth | D52: 卯亥未 | E52: Комбинация 3х. Дерево
A53: 5 | B53: bazci | C53: earth | D53: 卯未亥 | E53: Комбинация 3х. Дерево
A54: 5 | B54: bazci | C54: earth | D54: 未亥卯 | E54: Комбинация 3х. Дерево
A55: 5 | B55: bazci | C55: earth | D55: 未卯亥 | E55: Комбинация 3х. Дерево
A56: 5 | B56: bazci | C56: earth | D56: 寅午戌 | E56: Комбинация 3х. Огонь
... A150: 12 | B150: bazci | C150: earth | D150: 戌亥 | E150: Пустота

Sheet Шаблон для ввода
A1: Область ввода | U1: =ЕСЛИ(ЕПУСТО(U3);"";U3) | W1: =ЕСЛИ(ЕПУСТО(W3);"";W3) | AB1: =ЕСЛИ(ЕПУСТО(AB3);"";AB3) | AD1: =ЕСЛИ(ЕПУСТО(AD3);"";AD3)
A2: в базу | B2: Описание | C2: lvl_1_nm | D2: lvl_2_nm | E2: lvl_3_nm | F2: lvl_4_nm | G2: lvl_5_nm | H2: lvl_6_nm | I2: lvl_1 | J2: lvl_2 | K2: lvl_3 | L2: lvl_4 | M2: lvl_5 | N2: lvl_6 | O2: lvl_7 | P2: gr | Q2: id | S2: des | T2: id_season_start | U2: god_stolp_sky | V2: god_stolp_sky_id_5_element | W2: god_stolp_earth | X2: god_stolp_earth_5_element | Y2: god_scdg_element_num | Z2: god_scdg_period_num | AA2: god_scdg_id_5_element | AB2: mes_stolp_sky | AC2: mes_stolp_sky_id_5_element | AD2: mes_stolp_earth | AE2: mes_stolp_earth_id_5_element | AF2: mes_scdg_element_num | AG2: mes_scdg_period_num | AH2: mes_scdg_id_5_element | AI2: den_stolp_sky | AJ2: den_stolp_sky_id_5_element | AK2: den_stolp_earth | AL2: den_stolp_earth_id_5_element | AM2: den_scdg_element_num | AN2: den_scdg_period_num | AO2: den_scdg_id_5_element | AP2: chas_stolp_sky | AQ2: chas_stolp_sky_id_5_element | AR2: chas_stolp_earth | AS2: chas_stolp_earth_id_5_element | AT2: chas_scdg_element_num | AU2: chas_scdg_period_num | AV2: chas_scdg_id_5_element | AW2: palace | AX2: flag_sky_fou_tou | AY2: sky | AZ2: flag_earth_fou_tou | BA2: earth | BB2: gate | BC2: flag_main_gate | BD2: star | BE2: flag_main_star | BF2: spirit | BG2: coef | BH2: activation_use | BI2: activation_stop_factor | BJ2: walk_use | BK2: walk_stop_factor | BL2: scdg_use | BM2: scdg_stop_factor | BN2: date_analyze_use | BO2: date_analyze_stop_factor
R3: Хранилище (Гробница) | U3: 甲 | W3: 丑 | BP3: =_xlfn.AGGREGATE(3,3,BP114:BP1013) -> 342
R4: Хранилище (Гробница) | U4: 甲 | W4: 辰
R5: Хранилище (Гробница) | U5: 甲 | W5: 未
R6: Хранилище (Гробница) | U6: 甲 | W6: 戌
R7: Хранилище (Гробница) | U7: 乙 | W7: 丑
R8: Хранилище (Гробница) | U8: 乙 | W8: 辰
R9: Хранилище (Гробница) | U9: 乙 | W9: 未
R10: Хранилище (Гробница) | U10: 乙 | W10: 戌
R11: Хранилище (Гробница) | U11: 丙 | W11: 丑
R12: Хранилище (Гробница) | U12: 丁 | W12: 丑
R13: Хранилище (Гробница) | U13: 戊 | W13: 辰
R14: Хранилище (Гробница) | U14: 己 | W14: 辰
R15: Хранилище (Гробница) | U15: 庚 | W15: 未
... R40: Небесный чиновник | U40: 癸 | W40: 戌
BR112: god_stolp_sky | BS112: god_stolp_earth | BT112: mes_stolp_sky | BU112: mes_stolp_earth | BV112: den_stolp_sky | BW112: den_stolp_earth | BX112: chas_stolp_sky | BY112: chas_stolp_earth
A113: в базу | B113: Описание | C113: lvl_1_nm | D113: lvl_2_nm | E113: lvl_3_nm | F113: lvl_4_nm | G113: lvl_5_nm | H113: lvl_6_nm | I113: lvl_1 | J113: lvl_2 | K113: lvl_3 | L113: lvl_4 | M113: lvl_5 | N113: lvl_6 | O113: lvl_7 | P113: gr | Q113: id | R113: nm | S113: des | T113: id_season_start | U113: god_stolp_sky | V113: god_stolp_sky_id_5_element | W113: god_stolp_earth | X113: god_stolp_earth_5_element | Y113: god_scdg_element_num | Z113: god_scdg_period_num | AA113: god_scdg_id_5_element | AB113: mes_stolp_sky | AC113: mes_stolp_sky_id_5_element | AD113: mes_stolp_earth | AE113: mes_stolp_earth_id_5_element | AF113: mes_scdg_element_num | AG113: mes_scdg_period_num | AH113: mes_scdg_id_5_element | AI113: den_stolp_sky | AJ113: den_stolp_sky_id_5_element | AK113: den_stolp_earth | AL113: den_stolp_earth_id_5_element | AM113: den_scdg_element_num | AN113: den_scdg_period_num | AO113: den_scdg_id_5_element | AP113: chas_stolp_sky | AQ113: chas_stolp_sky_id_5_element | AR113: chas_stolp_earth | AS113: chas_stolp_earth_id_5_element | AT113: chas_scdg_element_num | AU113: chas_scdg_period_num | AV113: chas_scdg_id_5_element | AW113: palace | AX113: flag_sky_fou_tou | AY113: sky | AZ113: flag_earth_fou_tou | BA113: earth | BB113: gate | BC113: flag_main_gate | BD113: star | BE113: flag_main_star | BF113: spirit | BG113: coef | BH113: activation_use | BI113: activation_stop_factor | BJ113: walk_use | BK113: walk_stop_factor | BL113: scdg_use | BM113: scdg_stop_factor | BN113: date_analyze_use | BO113: date_analyze_stop_factor | BR113: Год НС | BS113: Год ЗВ | BT113: Месяц НС | BU113: Месяц ЗВ | BV113: День НС | BW113: День ЗВ | BX113: Час НС | BY113: Час ЗВ
A114: =IF(CG114<2,"",1) -> 1 | R114: =CONCATENATE(R3," [", BR114,BS114,BT114,BU114,BV114,BW114,BX114,BY114,"]") -> Хранилище (Гробница) [Год НС (甲) и Год ЗВ (丑)] | U114: =IF(ISBLANK(U3),"",U3) -> 甲 | W114: =IF(ISBLANK(W3),"",W3) -> 丑 | BN114: =A114 -> 1 | BP114: 01) Г-Г | BR114: =IF(U114="","",CONCATENATE(BR$113," (",U114,")",IF(OR(W114<>"",AB114<>"",AD114<>"",AI114<>"",AK114<>"",AP114<>"",AR114<>"")," и ",""))) -> Год НС (甲) и | BS114: =IF(W114="","",CONCATENATE(BS$113," (",W114,")",IF(OR(AB114<>"",AD114<>"",AI114<>"",AK114<>"",AP114<>"",AR114<>"")," и ",""))) -> Год ЗВ (丑) | BT114: =IF(AB114="","",CONCATENATE(BT$113," (",AB114,")",IF(OR(AD114<>"",AI114<>"",AK114<>"",AP114<>"",AR114<>"")," и ",""))) | BU114: =IF(AD114="","",CONCATENATE(BU$113," (",AD114,")",IF(OR(AI114<>"",AK114<>"",AP114<>"",AR114<>"")," и ",""))) | BV114: =IF(AI114="","",CONCATENATE(BV$113," (",AI114,")",IF(OR(AK114<>"",AP114<>"",AR114<>"")," и ",""))) | BW114: =IF(AK114="","",CONCATENATE(BW$113," (",AK114,")",IF(OR(AP114<>"",AR114<>"")," и ",""))) | BX114: =IF(AP114="","",CONCATENATE(BX$113," (",AP114,")",IF(OR(AR114<>"")," и ",""))) | BY114: =IF(AR114="","",CONCATENATE(BY$113," (",AR114,")")) | CA114: =IF(OR(W114<>"",AB114<>"",AD114<>"",AI114<>"",AK114<>"",AP114<>"",AR114<>"")," и ","") -> и | CB114: =IF(OR(AB114<>"",AD114<>"",AI114<>"",AK114<>"",AP114<>"",AR114<>"")," и ","") | CC114: =IF(OR(AI114<>"",AK114<>"",AP114<>"",AR114<>"")," и ","") | CD114: =IF(OR(AK114<>"",AP114<>"",AR114<>"")," и ","") | CE114: =IF(OR(AP114<>"",AR114<>"")," и ","") | CG114: =8-COUNTIFS(BR114:BY114,"") -> 2
A115: =IF(CG115<2,"",1) -> 1 | R115: =CONCATENATE(R4," [", BR115,BS115,BT115,BU115,BV115,BW115,BX115,BY115,"]") -> Хранилище (Гробница) [Год НС (甲) и Год ЗВ (辰)] | U115: =IF(ISBLANK(U4),"",U4) -> 甲 | W115: =IF(ISBLANK(W4),"",W4) -> 辰 | BN115: =A115 -> 1 | BP115: 01) Г-Г | BR115: =IF(U115="","",CONCATENATE(BR$113," (",U115,")",IF(OR(W115<>"",AB115<>"",AD115<>"",AI115<>"",AK115<>"",AP115<>"",AR115<>"")," и ",""))) -> Год НС (甲) и | BS115: =IF(W115="","",CONCATENATE(BS$113," (",W115,")",IF(OR(AB115<>"",AD115<>"",AI115<>"",AK115<>"",AP115<>"",AR115<>"")," и ",""))) -> Год ЗВ (辰) | BT115: =IF(AB115="","",CONCATENATE(BT$113," (",AB115,")",IF(OR(AD115<>"",AI115<>"",AK115<>"",AP115<>"",AR115<>"")," и ",""))) | BU115: =IF(AD115="","",CONCATENATE(BU$113," (",AD115,")",IF(OR(AI115<>"",AK115<>"",AP115<>"",AR115<>"")," и ",""))) | BV115: =IF(AI115="","",CONCATENATE(BV$113," (",AI115,")",IF(OR(AK115<>"",AP115<>"",AR115<>"")," и ",""))) | BW115: =IF(AK115="","",CONCATENATE(BW$113," (",AK115,")",IF(OR(AP115<>"",AR115<>"")," и ",""))) | BX115: =IF(AP115="","",CONCATENATE(BX$113," (",AP115,")",IF(OR(AR115<>"")," и ",""))) | BY115: =IF(AR115="","",CONCATENATE(BY$113," (",AR115,")")) | CA115: =IF(OR(W115<>"",AB115<>"",AD115<>"",AI115<>"",AK115<>"",AP115<>"",AR115<>"")," и ","") -> и | CB115: =IF(OR(AB115<>"",AD115<>"",AI115<>"",AK115<>"",AP115<>"",AR115<>"")," и ","") | CC115: =IF(OR(AI115<>"",AK115<>"",AP115<>"",AR115<>"")," и ","") | CD115: =IF(OR(AK115<>"",AP115<>"",AR115<>"")," и ","") | CE115: =IF(OR(AP115<>"",AR115<>"")," и ","") | CG115: =8-COUNTIFS(BR115:BY115,"") -> 2
A116: =IF(CG116<2,"",1) -> 1 | R116: =CONCATENATE(R5," [", BR116,BS116,BT116,BU116,BV116,BW116,BX116,BY116,"]") -> Хранилище (Гробница) [Год НС (甲) и Год ЗВ (未)] | U116: =IF(ISBLANK(U5),"",U5) -> 甲 | W116: =IF(ISBLANK(W5),"",W5) -> 未 | BN116: =A116 -> 1 | BP116: 01) Г-Г | BR116: =IF(U116="","",CONCATENATE(BR$113," (",U116,")",IF(OR(W116<>"",AB116<>"",AD116<>"",AI116<>"",AK116<>"",AP116<>"",AR116<>"")," и ",""))) -> Год НС (甲) и | BS116: =IF(W116="","",CONCATENATE(BS$113," (",W116,")",IF(OR(AB116<>"",AD116<>"",AI116<>"",AK116<>"",AP116<>"",AR116<>"")," и ",""))) -> Год ЗВ (未) | BT116: =IF(AB116="","",CONCATENATE(BT$113," (",AB116,")",IF(OR(AD116<>"",AI116<>"",AK116<>"",AP116<>"",AR116<>"")," и ",""))) | BU116: =IF(AD116="","",CONCATENATE(BU$113," (",AD116,")",IF(OR(AI116<>"",AK116<>"",AP116<>"",AR116<>"")," и ",""))) | BV116: =IF(AI116="","",CONCATENATE(BV$113," (",AI116,")",IF(OR(AK116<>"",AP116<>"",AR116<>"")," и ",""))) | BW116: =IF(AK116="","",CONCATENATE(BW$113," (",AK116,")",IF(OR(AP116<>"",AR116<>"")," и ",""))) | BX116: =IF(AP116="","",CONCATENATE(BX$113," (",AP116,")",IF(OR(AR116<>"")," и ",""))) | BY116: =IF(AR116="","",CONCATENATE(BY$113," (",AR116,")")) | CA116: =IF(OR(W116<>"",AB116<>"",AD116<>"",AI116<>"",AK116<>"",AP116<>"",AR116<>"")," и ","") -> и | CB116: =IF(OR(AB116<>"",AD116<>"",AI116<>"",AK116<>"",AP116<>"",AR116<>"")," и ","") | CC116: =IF(OR(AI116<>"",AK116<>"",AP116<>"",AR116<>"")," и ","") | CD116: =IF(OR(AK116<>"",AP116<>"",AR116<>"")," и ","") | CE116: =IF(OR(AP116<>"",AR116<>"")," и ","") | CG116: =8-COUNTIFS(BR116:BY116,"") -> 2
A117: =IF(CG117<2,"",1) -> 1 | R117: =CONCATENATE(R6," [", BR117,BS117,BT117,BU117,BV117,BW117,BX117,BY117,"]") -> Хранилище (Гробница) [Год НС (甲) и Год ЗВ (戌)] | U117: =IF(ISBLANK(U6),"",U6) -> 甲 | W117: =IF(ISBLANK(W6),"",W6) -> 戌 | BN117: =A117 -> 1 | BP117: 01) Г-Г | BR117: =IF(U117="","",CONCATENATE(BR$113," (",U117,")",IF(OR(W117<>"",AB117<>"",AD117<>"",AI117<>"",AK117<>"",AP117<>"",AR117<>"")," и ",""))) -> Год НС (甲) и | BS117: =IF(W117="","",CONCATENATE(BS$113," (",W117,")",IF(OR(AB117<>"",AD117<>"",AI117<>"",AK117<>"",AP117<>"",AR117<>"")," и ",""))) -> Год ЗВ (戌) | BT117: =IF(AB117="","",CONCATENATE(BT$113," (",AB117,")",IF(OR(AD117<>"",AI117<>"",AK117<>"",AP117<>"",AR117<>"")," и ",""))) | BU117: =IF(AD117="","",CONCATENATE(BU$113," (",AD117,")",IF(OR(AI117<>"",AK117<>"",AP117<>"",AR117<>"")," и ",""))) | BV117: =IF(AI117="","",CONCATENATE(BV$113," (",AI117,")",IF(OR(AK117<>"",AP117<>"",AR117<>"")," и ",""))) | BW117: =IF(AK117="","",CONCATENATE(BW$113," (",AK117,")",IF(OR(AP117<>"",AR117<>"")," и ",""))) | BX117: =IF(AP117="","",CONCATENATE(BX$113," (",AP117,")",IF(OR(AR117<>"")," и ",""))) | BY117: =IF(AR117="","",CONCATENATE(BY$113," (",AR117,")")) | CA117: =IF(OR(W117<>"",AB117<>"",AD117<>"",AI117<>"",AK117<>"",AP117<>"",AR117<>"")," и ","") -> и | CB117: =IF(OR(AB117<>"",AD117<>"",AI117<>"",AK117<>"",AP117<>"",AR117<>"")," и ","") | CC117: =IF(OR(AI117<>"",AK117<>"",AP117<>"",AR117<>"")," и ","") | CD117: =IF(OR(AK117<>"",AP117<>"",AR117<>"")," и ","") | CE117: =IF(OR(AP117<>"",AR117<>"")," и ","") | CG117: =8-COUNTIFS(BR117:BY117,"") -> 2
A118: =IF(CG118<2,"",1) -> 1 | R118: =CONCATENATE(R7," [", BR118,BS118,BT118,BU118,BV118,BW118,BX118,BY118,"]") -> Хранилище (Гробница) [Год НС (乙) и Год ЗВ (丑)] | U118: =IF(ISBLANK(U7),"",U7) -> 乙 | W118: =IF(ISBLANK(W7),"",W7) -> 丑 | BN118: =A118 -> 1 | BP118: 01) Г-Г | BR118: =IF(U118="","",CONCATENATE(BR$113," (",U118,")",IF(OR(W118<>"",AB118<>"",AD118<>"",AI118<>"",AK118<>"",AP118<>"",AR118<>"")," и ",""))) -> Год НС (乙) и | BS118: =IF(W118="","",CONCATENATE(BS$113," (",W118,")",IF(OR(AB118<>"",AD118<>"",AI118<>"",AK118<>"",AP118<>"",AR118<>"")," и ",""))) -> Год ЗВ (丑) | BT118: =IF(AB118="","",CONCATENATE(BT$113," (",AB118,")",IF(OR(AD118<>"",AI118<>"",AK118<>"",AP118<>"",AR118<>"")," и ",""))) | BU118: =IF(AD118="","",CONCATENATE(BU$113," (",AD118,")",IF(OR(AI118<>"",AK118<>"",AP118<>"",AR118<>"")," и ",""))) | BV118: =IF(AI118="","",CONCATENATE(BV$113," (",AI118,")",IF(OR(AK118<>"",AP118<>"",AR118<>"")," и ",""))) | BW118: =IF(AK118="","",CONCATENATE(BW$113," (",AK118,")",IF(OR(AP118<>"",AR118<>"")," и ",""))) | BX118: =IF(AP118="","",CONCATENATE(BX$113," (",AP118,")",IF(OR(AR118<>"")," и ",""))) | BY118: =IF(AR118="","",CONCATENATE(BY$113," (",AR118,")")) | CA118: =IF(OR(W118<>"",AB118<>"",AD118<>"",AI118<>"",AK118<>"",AP118<>"",AR118<>"")," и ","") -> и | CB118: =IF(OR(AB118<>"",AD118<>"",AI118<>"",AK118<>"",AP118<>"",AR118<>"")," и ","") | CC118: =IF(OR(AI118<>"",AK118<>"",AP118<>"",AR118<>"")," и ","") | CD118: =IF(OR(AK118<>"",AP118<>"",AR118<>"")," и ","") | CE118: =IF(OR(AP118<>"",AR118<>"")," и ","") | CG118: =8-COUNTIFS(BR118:BY118,"") -> 2
A119: =IF(CG119<2,"",1) -> 1 | R119: =CONCATENATE(R8," [", BR119,BS119,BT119,BU119,BV119,BW119,BX119,BY119,"]") -> Хранилище (Гробница) [Год НС (乙) и Год ЗВ (辰)] | U119: =IF(ISBLANK(U8),"",U8) -> 乙 | W119: =IF(ISBLANK(W8),"",W8) -> 辰 | BN119: =A119 -> 1 | BP119: 01) Г-Г | BR119: =IF(U119="","",CONCATENATE(BR$113," (",U119,")",IF(OR(W119<>"",AB119<>"",AD119<>"",AI119<>"",AK119<>"",AP119<>"",AR119<>"")," и ",""))) -> Год НС (乙) и | BS119: =IF(W119="","",CONCATENATE(BS$113," (",W119,")",IF(OR(AB119<>"",AD119<>"",AI119<>"",AK119<>"",AP119<>"",AR119<>"")," и ",""))) -> Год ЗВ (辰) | BT119: =IF(AB119="","",CONCATENATE(BT$113," (",AB119,")",IF(OR(AD119<>"",AI119<>"",AK119<>"",AP119<>"",AR119<>"")," и ",""))) | BU119: =IF(AD119="","",CONCATENATE(BU$113," (",AD119,")",IF(OR(AI119<>"",AK119<>"",AP119<>"",AR119<>"")," и ",""))) | BV119: =IF(AI119="","",CONCATENATE(BV$113," (",AI119,")",IF(OR(AK119<>"",AP119<>"",AR119<>"")," и ",""))) | BW119: =IF(AK119="","",CONCATENATE(BW$113," (",AK119,")",IF(OR(AP119<>"",AR119<>"")," и ",""))) | BX119: =IF(AP119="","",CONCATENATE(BX$113," (",AP119,")",IF(OR(AR119<>"")," и ",""))) | BY119: =IF(AR119="","",CONCATENATE(BY$113," (",AR119,")")) | CA119: =IF(OR(W119<>"",AB119<>"",AD119<>"",AI119<>"",AK119<>"",AP119<>"",AR119<>"")," и ","") -> и | CB119: =IF(OR(AB119<>"",AD119<>"",AI119<>"",AK119<>"",AP119<>"",AR119<>"")," и ","") | CC119: =IF(OR(AI119<>"",AK119<>"",AP119<>"",AR119<>"")," и ","") | CD119: =IF(OR(AK119<>"",AP119<>"",AR119<>"")," и ","") | CE119: =IF(OR(AP119<>"",AR119<>"")," и ","") | CG119: =8-COUNTIFS(BR119:BY119,"") -> 2
A120: =IF(CG120<2,"",1) -> 1 | R120: =CONCATENATE(R9," [", BR120,BS120,BT120,BU120,BV120,BW120,BX120,BY120,"]") -> Хранилище (Гробница) [Год НС (乙) и Год ЗВ (未)] | U120: =IF(ISBLANK(U9),"",U9) -> 乙 | W120: =IF(ISBLANK(W9),"",W9) -> 未 | BN120: =A120 -> 1 | BP120: 01) Г-Г | BR120: =IF(U120="","",CONCATENATE(BR$113," (",U120,")",IF(OR(W120<>"",AB120<>"",AD120<>"",AI120<>"",AK120<>"",AP120<>"",AR120<>"")," и ",""))) -> Год НС (乙) и | BS120: =IF(W120="","",CONCATENATE(BS$113," (",W120,")",IF(OR(AB120<>"",AD120<>"",AI120<>"",AK120<>"",AP120<>"",AR120<>"")," и ",""))) -> Год ЗВ (未) | BT120: =IF(AB120="","",CONCATENATE(BT$113," (",AB120,")",IF(OR(AD120<>"",AI120<>"",AK120<>"",AP120<>"",AR120<>"")," и ",""))) | BU120: =IF(AD120="","",CONCATENATE(BU$113," (",AD120,")",IF(OR(AI120<>"",AK120<>"",AP120<>"",AR120<>"")," и ",""))) | BV120: =IF(AI120="","",CONCATENATE(BV$113," (",AI120,")",IF(OR(AK120<>"",AP120<>"",AR120<>"")," и ",""))) | BW120: =IF(AK120="","",CONCATENATE(BW$113," (",AK120,")",IF(OR(AP120<>"",AR120<>"")," и ",""))) | BX120: =IF(AP120="","",CONCATENATE(BX$113," (",AP120,")",IF(OR(AR120<>"")," и ",""))) | BY120: =IF(AR120="","",CONCATENATE(BY$113," (",AR120,")")) | CA120: =IF(OR(W120<>"",AB120<>"",AD120<>"",AI120<>"",AK120<>"",AP120<>"",AR120<>"")," и ","") -> и | CB120: =IF(OR(AB120<>"",AD120<>"",AI120<>"",AK120<>"",AP120<>"",AR120<>"")," и ","") | CC120: =IF(OR(AI120<>"",AK120<>"",AP120<>"",AR120<>"")," и ","") | CD120: =IF(OR(AK120<>"",AP120<>"",AR120<>"")," и ","") | CE120: =IF(OR(AP120<>"",AR120<>"")," и ","") | CG120: =8-COUNTIFS(BR120:BY120,"") -> 2
A121: =IF(CG121<2,"",1) -> 1 | R121: =CONCATENATE(R10," [", BR121,BS121,BT121,BU121,BV121,BW121,BX121,BY121,"]") -> Хранилище (Гробница) [Год НС (乙) и Год ЗВ (戌)] | U121: =IF(ISBLANK(U10),"",U10) -> 乙 | W121: =IF(ISBLANK(W10),"",W10) -> 戌 | BN121: =A121 -> 1 | BP121: 01) Г-Г | BR121: =IF(U121="","",CONCATENATE(BR$113," (",U121,")",IF(OR(W121<>"",AB121<>"",AD121<>"",AI121<>"",AK121<>"",AP121<>"",AR121<>"")," и ",""))) -> Год НС (乙) и | BS121: =IF(W121="","",CONCATENATE(BS$113," (",W121,")",IF(OR(AB121<>"",AD121<>"",AI121<>"",AK121<>"",AP121<>"",AR121<>"")," и ",""))) -> Год ЗВ (戌) | BT121: =IF(AB121="","",CONCATENATE(BT$113," (",AB121,")",IF(OR(AD121<>"",AI121<>"",AK121<>"",AP121<>"",AR121<>"")," и ",""))) | BU121: =IF(AD121="","",CONCATENATE(BU$113," (",AD121,")",IF(OR(AI121<>"",AK121<>"",AP121<>"",AR121<>"")," и ",""))) | BV121: =IF(AI121="","",CONCATENATE(BV$113," (",AI121,")",IF(OR(AK121<>"",AP121<>"",AR121<>"")," и ",""))) | BW121: =IF(AK121="","",CONCATENATE(BW$113," (",AK121,")",IF(OR(AP121<>"",AR121<>"")," и ",""))) | BX121: =IF(AP121="","",CONCATENATE(BX$113," (",AP121,")",IF(OR(AR121<>"")," и ",""))) | BY121: =IF(AR121="","",CONCATENATE(BY$113," (",AR121,")")) | CA121: =IF(OR(W121<>"",AB121<>"",AD121<>"",AI121<>"",AK121<>"",AP121<>"",AR121<>"")," и ","") -> и | CB121: =IF(OR(AB121<>"",AD121<>"",AI121<>"",AK121<>"",AP121<>"",AR121<>"")," и ","") | CC121: =IF(OR(AI121<>"",AK121<>"",AP121<>"",AR121<>"")," и ","") | CD121: =IF(OR(AK121<>"",AP121<>"",AR121<>"")," и ","") | CE121: =IF(OR(AP121<>"",AR121<>"")," и ","") | CG121: =8-COUNTIFS(BR121:BY121,"") -> 2
A122: =IF(CG122<2,"",1) -> 1 | R122: =CONCATENATE(R11," [", BR122,BS122,BT122,BU122,BV122,BW122,BX122,BY122,"]") -> Хранилище (Гробница) [Год НС (丙) и Год ЗВ (丑)] | U122: =IF(ISBLANK(U11),"",U11) -> 丙 | W122: =IF(ISBLANK(W11),"",W11) -> 丑 | BN122: =A122 -> 1 | BP122: 01) Г-Г | BR122: =IF(U122="","",CONCATENATE(BR$113," (",U122,")",IF(OR(W122<>"",AB122<>"",AD122<>"",AI122<>"",AK122<>"",AP122<>"",AR122<>"")," и ",""))) -> Год НС (丙) и | BS122: =IF(W122="","",CONCATENATE(BS$113," (",W122,")",IF(OR(AB122<>"",AD122<>"",AI122<>"",AK122<>"",AP122<>"",AR122<>"")," и ",""))) -> Год ЗВ (丑) | BT122: =IF(AB122="","",CONCATENATE(BT$113," (",AB122,")",IF(OR(AD122<>"",AI122<>"",AK122<>"",AP122<>"",AR122<>"")," и ",""))) | BU122: =IF(AD122="","",CONCATENATE(BU$113," (",AD122,")",IF(OR(AI122<>"",AK122<>"",AP122<>"",AR122<>"")," и ",""))) | BV122: =IF(AI122="","",CONCATENATE(BV$113," (",AI122,")",IF(OR(AK122<>"",AP122<>"",AR122<>"")," и ",""))) | BW122: =IF(AK122="","",CONCATENATE(BW$113," (",AK122,")",IF(OR(AP122<>"",AR122<>"")," и ",""))) | BX122: =IF(AP122="","",CONCATENATE(BX$113," (",AP122,")",IF(OR(AR122<>"")," и ",""))) | BY122: =IF(AR122="","",CONCATENATE(BY$113," (",AR122,")")) | CA122: =IF(OR(W122<>"",AB122<>"",AD122<>"",AI122<>"",AK122<>"",AP122<>"",AR122<>"")," и ","") -> и | CB122: =IF(OR(AB122<>"",AD122<>"",AI122<>"",AK122<>"",AP122<>"",AR122<>"")," и ","") | CC122: =IF(OR(AI122<>"",AK122<>"",AP122<>"",AR122<>"")," и ","") | CD122: =IF(OR(AK122<>"",AP122<>"",AR122<>"")," и ","") | CE122: =IF(OR(AP122<>"",AR122<>"")," и ","") | CG122: =8-COUNTIFS(BR122:BY122,"") -> 2
A123: =IF(CG123<2,"",1) -> 1 | R123: =CONCATENATE(R12," [", BR123,BS123,BT123,BU123,BV123,BW123,BX123,BY123,"]") -> Хранилище (Гробница) [Год НС (丁) и Год ЗВ (丑)] | U123: =IF(ISBLANK(U12),"",U12) -> 丁 | W123: =IF(ISBLANK(W12),"",W12) -> 丑 | BN123: =A123 -> 1 | BP123: 01) Г-Г | BR123: =IF(U123="","",CONCATENATE(BR$113," (",U123,")",IF(OR(W123<>"",AB123<>"",AD123<>"",AI123<>"",AK123<>"",AP123<>"",AR123<>"")," и ",""))) -> Год НС (丁) и | BS123: =IF(W123="","",CONCATENATE(BS$113," (",W123,")",IF(OR(AB123<>"",AD123<>"",AI123<>"",AK123<>"",AP123<>"",AR123<>"")," и ",""))) -> Год ЗВ (丑) | BT123: =IF(AB123="","",CONCATENATE(BT$113," (",AB123,")",IF(OR(AD123<>"",AI123<>"",AK123<>"",AP123<>"",AR123<>"")," и ",""))) | BU123: =IF(AD123="","",CONCATENATE(BU$113," (",AD123,")",IF(OR(AI123<>"",AK123<>"",AP123<>"",AR123<>"")," и ",""))) | BV123: =IF(AI123="","",CONCATENATE(BV$113," (",AI123,")",IF(OR(AK123<>"",AP123<>"",AR123<>"")," и ",""))) | BW123: =IF(AK123="","",CONCATENATE(BW$113," (",AK123,")",IF(OR(AP123<>"",AR123<>"")," и ",""))) | BX123: =IF(AP123="","",CONCATENATE(BX$113," (",AP123,")",IF(OR(AR123<>"")," и ",""))) | BY123: =IF(AR123="","",CONCATENATE(BY$113," (",AR123,")")) | CA123: =IF(OR(W123<>"",AB123<>"",AD123<>"",AI123<>"",AK123<>"",AP123<>"",AR123<>"")," и ","") -> и | CB123: =IF(OR(AB123<>"",AD123<>"",AI123<>"",AK123<>"",AP123<>"",AR123<>"")," и ","") | CC123: =IF(OR(AI123<>"",AK123<>"",AP123<>"",AR123<>"")," и ","") | CD123: =IF(OR(AK123<>"",AP123<>"",AR123<>"")," и ","") | CE123: =IF(OR(AP123<>"",AR123<>"")," и ","") | CG123: =8-COUNTIFS(BR123:BY123,"") -> 2
A124: =IF(CG124<2,"",1) -> 1 | R124: =CONCATENATE(R13," [", BR124,BS124,BT124,BU124,BV124,BW124,BX124,BY124,"]") -> Хранилище (Гробница) [Год НС (戊) и Год ЗВ (辰)] | U124: =IF(ISBLANK(U13),"",U13) -> 戊 | W124: =IF(ISBLANK(W13),"",W13) -> 辰 | BN124: =A124 -> 1 | BP124: 01) Г-Г | BR124: =IF(U124="","",CONCATENATE(BR$113," (",U124,")",IF(OR(W124<>"",AB124<>"",AD124<>"",AI124<>"",AK124<>"",AP124<>"",AR124<>"")," и ",""))) -> Год НС (戊) и | BS124: =IF(W124="","",CONCATENATE(BS$113," (",W124,")",IF(OR(AB124<>"",AD124<>"",AI124<>"",AK124<>"",AP124<>"",AR124<>"")," и ",""))) -> Год ЗВ (辰) | BT124: =IF(AB124="","",CONCATENATE(BT$113," (",AB124,")",IF(OR(AD124<>"",AI124<>"",AK124<>"",AP124<>"",AR124<>"")," и ",""))) | BU124: =IF(AD124="","",CONCATENATE(BU$113," (",AD124,")",IF(OR(AI124<>"",AK124<>"",AP124<>"",AR124<>"")," и ",""))) | BV124: =IF(AI124="","",CONCATENATE(BV$113," (",AI124,")",IF(OR(AK124<>"",AP124<>"",AR124<>"")," и ",""))) | BW124: =IF(AK124="","",CONCATENATE(BW$113," (",AK124,")",IF(OR(AP124<>"",AR124<>"")," и ",""))) | BX124: =IF(AP124="","",CONCATENATE(BX$113," (",AP124,")",IF(OR(AR124<>"")," и ",""))) | BY124: =IF(AR124="","",CONCATENATE(BY$113," (",AR124,")")) | CA124: =IF(OR(W124<>"",AB124<>"",AD124<>"",AI124<>"",AK124<>"",AP124<>"",AR124<>"")," и ","") -> и | CB124: =IF(OR(AB124<>"",AD124<>"",AI124<>"",AK124<>"",AP124<>"",AR124<>"")," и ","") | CC124: =IF(OR(AI124<>"",AK124<>"",AP124<>"",AR124<>"")," и ","") | CD124: =IF(OR(AK124<>"",AP124<>"",AR124<>"")," и ","") | CE124: =IF(OR(AP124<>"",AR124<>"")," и ","") | CG124: =8-COUNTIFS(BR124:BY124,"") -> 2
